{
    "C_DATA": [
        "yIwkCuXszXUYrunp",
        "W8HF1P8pYzhu56G6"
    ],
    "enc_code2": [
        "SayGDUzddadBSoR2",
        "r7szzcxqkohS6EYZ"
    ],
    "enc_code1": [
        "RM3I5kmhHyN5Uuxf",
        "sOFoP2d0YYvtEuMz"
    ],
    "IG_dict": {
        "2401": "eO5ceGjsYrh0f3yJ",
        "2402": "eOVeuYGYvGRcOF88",
        "2404": "eOgRsTtemoTJRdjd",
        "2405": "eVZdG1cAb89uJhVd",
        "2406": "eYF7PIwsS6PsKRPN",
        "2408": "ec4G8cdndttKXLzQ",
        "2134": "UR232GeLoTozOwSG",
        "2135": "UTFdPRe3fGxtMRPK",
        "2137": "UTQZS0QwBRrrLxUj",
        "2139": "UVfcSCa6hwPMBLAR",
        "2141": "UZ2HVHGI597PAp07",
        "2142": "UjPLhekBjxnYHoaR",
        "2144": "UkMJ2R6IzS6UJe8b",
        "2145": "Ul6eHYZlU7IKzlfm",
        "2147": "UrVGROAv8GZ7sjpW",
        "2409": "ehDcmSgLNMz6mYoe",
        "2411": "eiAdWvHXti4fjM5R",
        "2412": "eoE3yfqsqBfCOF3T",
        "2413": "f0RyOEgYUTcL1qcF",
        "2414": "fBqYZEtZnKnyn96U",
        "1366": "00ZLq1KDLX8Pydd6",
        "1368": "08cwzAYpDHeUCHFm",
        "1369": "0FLcYeEF528vUtYv",
        "1370": "0G2sdGowjTF7HANG",
        "1371": "0KCXmug2fz6HD4QN",
        "1372": "0MARmcuQAxi7MUrO",
        "1374": "0OdPOXHTZx5oYvkO",
        "1376": "0YKVFf0bIlZQM7YA",
        "1378": "0iAp7rF3Xr9PY6OJ",
        "1380": "0kMv0OslTQ7apmjr",
        "1382": "0p5eTESDYNJjZcX4",
        "1383": "0xHvzaY55byhbUTv",
        "1384": "0yuqwe49URZeNC7V",
        "1385": "10Qvwlx1x3BTCipW",
        "1387": "11lLzY2qYaswNybm",
        "1389": "13f3IomW8BKFpsc7",
        "1390": "14kwLy1qENcz2pFb",
        "1392": "15i7WCkfYqx9T1M5",
        "1394": "1CA4dj6ett9jhGKv",
        "1396": "1DUGhYdC6aeE5uKR",
        "1397": "1EJeiiCTV0mPZ0cq",
        "1399": "1HCxW0nOrV4sTlSk",
        "1400": "1LCw0eugd5yg5Z8z",
        "1402": "1Q2zuBru3B0xtzZL",
        "1403": "1SjlpTpHzyDEBxKC",
        "1404": "1XVIrCtO5Szo9aZC",
        "1406": "1hJVIXNnLu0lUDIi",
        "1407": "1kMceMyYZ1lx9CQz",
        "1409": "1u4JjO9R5bWILU53",
        "1411": "214ZvA66E6HqI26o",
        "1413": "25ksHoKSVRRRoHJi",
        "1415": "2843G7neWmiDntHc",
        "1417": "2Gx3eCbSef0daMQG",
        "1419": "2IYeIYYaKUrdTgga",
        "2310": "adb7IgOikWLaQq1r",
        "2311": "alDer5Bmw8BbJMjo",
        "2313": "aoMYfdtbNryiH7qv",
        "2315": "aqwr0zZbJQNxnScL",
        "2316": "at2i9N2Tm32dFm5W",
        "2318": "axPoBSoxerca0IRN",
        "2320": "ayUcDlIPgCpGHZaY",
        "2322": "b4uZADgrYzMVbC3X",
        "2324": "b7aMQyGdeSXXL02I",
        "2326": "bCc66uRPkQYI2U07",
        "2328": "bFN7jo2xvUnkQj5M",
        "2330": "bFWvHGZnYqKtLES0",
        "2332": "bMqRV4nkiiEqqLK7",
        "2333": "bQl0o8yOl0Z3ZwCQ",
        "2334": "bSkZY9JtLtfj985g",
        "2335": "bZif7z2gH1hjg4x5",
        "2337": "bbvV99IJzw2kQT6R",
        "2338": "bhG4QSfVaaqjtlKe",
        "2339": "bjh9UASMYsM1wIED",
        "2340": "bmGrNe2Nces5jwxy",
        "2342": "bmtffdo09e6lw10y",
        "2343": "byB9eB1qGqRuIxNa",
        "2344": "c1BpJfNRnlCYfkPg",
        "2345": "c24FSWSCpiQXCy2N",
        "2346": "c2s89JHcsSjTFpHy",
        "2348": "c47czgCiAdiNLePd",
        "2350": "cIXYAuCeO8D4xnW1",
        "2351": "cKENG5uaG2EyyeoC",
        "2353": "cOkp08LreOBnN5Nt",
        "2354": "cW4NUWdUCWe8lirD",
        "2355": "cXgyRdnlCur9OFyr",
        "2357": "chS7tSE0JVB1bOtn",
        "2358": "cjrqB3k9PQJDzpaJ",
        "2359": "cnFJZVE1HA9zYB9z",
        "2360": "ct6JYjOl2Jpnmt9M",
        "2361": "ctHPn9rn1dwIvxwb",
        "2362": "cyBFGrYb4Ve23niA",
        "2363": "czsQqvh7Qec1tweb",
        "2365": "d1vjjMRs0EwNzP8q",
        "2367": "d9hylTJPg57o3EIO",
        "2369": "dBLh3j7VAEM92uDl",
        "2370": "dC3eoRacXgylTuB3",
        "2372": "dCvWLaelO15ighoZ",
        "2374": "dEUXYMMmUjwxpLHT",
        "2376": "dJ0W34hCmXhVj31X",
        "2377": "dJE4DCqAUFVX6gZR",
        "2378": "dKEi7f4ndl0xiCdo",
        "2379": "dOUT3I4EkVO0ccFH",
        "2380": "dPgKxGF9UJI7ASh2",
        "2381": "dR9a2cH1neLKQHUm",
        "2382": "dSpeucirY6pwTWtd",
        "2383": "dTCaBSbkl2mtXHSw",
        "2384": "dafhyzV1ZR1oS4kq",
        "2385": "ddsuHlyEUgp3jJVY",
        "2387": "di1vL42H0nqbIBsL",
        "2388": "dp0HjiZGaGhwTqGE",
        "2389": "duO4pfwHuIrg45HE",
        "2390": "e0naJG4XrvhAuTiu",
        "2392": "e2mbmKrZpGvZb0v0",
        "2394": "e6P2YFclioBqC5dK",
        "2395": "eDXWyeotmO0kSrs9",
        "2396": "eF2AG8jMy6lIoxaF",
        "2397": "eJ8464rKRYdJi4y0",
        "2398": "eLAxW1e0si8cF7jj",
        "2203": "XRuDtmqwCxaIz0Tj",
        "2205": "XRzQvqenrj3OlkQe",
        "2207": "XVN3MUBjvKO6BVm6",
        "2209": "XZCgK9c613CDXUKM",
        "2210": "Xc355iJ1OoUXs23I",
        "2212": "XceDx15OPrKZkqjP",
        "2214": "XchHv7EcoXD3m84z",
        "2216": "Xdv5F3EYhKstcRFw",
        "2217": "Xek6E1BBjF2JDeX2",
        "2218": "XfSHve9n8M37xhYd",
        "2220": "XlN9NETfGZT3x7e9",
        "2222": "XoCjtpG9c01YzsaM",
        "2224": "Xt3GDyQJ9dSk02zh",
        "2225": "Xys0qA4PyTTP2xsX",
        "2227": "XznZ8z47PpQ0yQzA",
        "2228": "Y1OJZ4uhP0nRGaW6",
        "2230": "Y2FBuSfZ8lsUb48d",
        "2231": "Y6vqIEpW6vzsw44c",
        "2232": "Y7FP9kzTmvgdwbRp",
        "2234": "Y8x8ke2B0Mp2aRKV",
        "2236": "Y9eZSE13EHOM8eq5",
        "2237": "YC8OOvChjFJaHuOg",
        "2239": "YLGDguxqJovnXQgy",
        "2240": "YNwaWpK84SLJXHlo",
        "2242": "YQEpfqeIk9Y5R5rm",
        "2244": "YSwKGJImchI13Fxg",
        "2246": "YaNlHykreRvzm3nB",
        "2248": "YcPYvP7C7bdGKop9",
        "2250": "YgFhSO8zNHrkkGXJ",
        "2251": "Yj3Q2DgLcH7k3xgX",
        "2252": "YlRJOcLhZftETsZ5",
        "2254": "Ypcyp5dyMIJd9bHZ",
        "2255": "YqxYTYUJsps6TILf",
        "2257": "YwEfZYI8teQYjUZP",
        "2259": "Yy0b857IqCSri0WF",
        "2261": "Z2nA34k4vZUs9YHo",
        "2263": "Z3QzZOXmsa4x3Igp",
        "2265": "ZAI3AIMBviCLr75I",
        "2266": "ZBrY7khPS98iS0Pd",
        "2268": "ZCWg7fE5OakmXdHt",
        "2269": "ZDUS8Ce7kitgfR1r",
        "2271": "ZGzzUVM1eJuk8v3x",
        "2273": "ZKEQDLX7vjwU1jv9",
        "2275": "ZQ3nEYBXEUnMFBFQ",
        "2276": "ZR8Jho2KNaYwCIGb",
        "2277": "ZSkbYfFjl9dY2K8M",
        "2278": "ZT4Pvku61R64Z33u",
        "2279": "ZV0nICCUcebJNpiO",
        "2281": "ZWqdpZNH61a9LMZt",
        "2283": "ZYZ7XcNyM3nIWjD9",
        "2285": "ZZiE3PsZblNfrZ4P",
        "2287": "Zs0MOEoWs758tLhu",
        "2288": "ZyHsFIsjFb8bUOyv",
        "2290": "ZyYfQgmYEqsKH0IQ",
        "2292": "ZyuiDiepVDUOsnRK",
        "2293": "a3ow5EE8O3B7Lvx4",
        "2295": "a46EzYoXxGjO6plZ",
        "2297": "a5Bec1FwEECf8WqG",
        "2298": "aClWTUS2isExH1KT",
        "2300": "aI8Lzb2tcaYhJUj8",
        "2302": "aIyTRTLSUHE9eU5K",
        "2304": "aLYJ9dTjsu0TS3Tf",
        "2306": "aMHyz4rUzuS7oE6J",
        "2308": "aSFkeP0MW2EzBkLk",
        "2098": "SzaZuOdKXmpVhe3s",
        "2099": "T0ihACruHGtwpG43",
        "2101": "T2WUcZEX0brmq1Gn",
        "2103": "T4H9fKjud0XRnBjO",
        "2105": "T8cnXenWfsNydKqS",
        "2107": "TGYCHa24AJ3NG6Mf",
        "2109": "THh6DRVWuqMUkn43",
        "2110": "TMJ0RZbr3tUk1CzV",
        "2111": "TQ1FFN2XGE9VnNdI",
        "2113": "TVCrIX0rXfnzyMuE",
        "2115": "TVrtMANFcApSfKIs",
        "2117": "TXeSSpuoGZ5fLiaX",
        "2119": "TXk3e4BTj2yosTBG",
        "2121": "TgMO1eontpeUJKB4",
        "2122": "TgRLSVqx5JIjQPB3",
        "2123": "ThdF7wHL37veu4sL",
        "2125": "TiLd7Y3SzwO9fuF3",
        "2127": "TibT82JLWlRPSuCc",
        "1855": "Jxd6oZgz1ryTlRab",
        "2128": "Tm0sF92nuE35beUx",
        "2129": "TtTYzK7bkGynx4hQ",
        "2131": "TxrUMTYDsdPI0nQ4",
        "1857": "JxfTRIRd1SM8PINp",
        "1859": "K1nsWUkdzeACjgcA",
        "1861": "K7ImhqkfyPAUbfc8",
        "1862": "KAJtVusKSmQJnBWE",
        "1863": "KQM36xX8E52tb05I",
        "1864": "KUd5bdEqzzLrd47J",
        "1865": "KXhPo50ptOKVIZeH",
        "1866": "KZTC0WwWqyeStZD2",
        "2133": "UC0uDFgqHkEOnKg9",
        "2149": "V5zZsTHd0yqyCN0u",
        "2150": "V6AlpgGwMaf1LCjx",
        "2151": "V9HZBD11TZHGsibY",
        "2153": "VE8YKMXQFB7OLEhO",
        "2155": "VNhz9TAfU6tMpKMc",
        "2157": "VOR1yf7q8r5kw1d1",
        "2158": "VXImPy3UHN3hiyy8",
        "2159": "VY9iB7Lsix6VYBVq",
        "2161": "Vc1tjbgsyvHvC2lv",
        "2162": "VeFzsAm1nE4KG6EI",
        "2164": "VkDmiOtmimOWgzlR",
        "2166": "Vmtlbu7FyKKhzIH8",
        "2167": "Vn2VY6FVNrb4PjTe",
        "2169": "W4nc6rH9ECaeXgRI",
        "2170": "W7qH1qMG2MvxGNX3",
        "2172": "W8FpR9xeenTngrfv",
        "2173": "W8X9Oo4ESPDZWxge",
        "2174": "WJ4o6efY3BN9pTvj",
        "2176": "WMCfUXIcSxO8CTAp",
        "2177": "WMDvgfiga5qKEUGx",
        "2179": "WQkscSgSsFNDpPyx",
        "2181": "WUzVjtbo4mtjPKcA",
        "2183": "WVoIwZOT3RSG3n93",
        "2184": "WXgNRdADPc9hx06Z",
        "2185": "WcrBCVNheEMydkY5",
        "2187": "Wjf7ZLF1E93b7OHt",
        "2189": "Wk13YyT0kzeBw51j",
        "2191": "Wk1cfA5e0bMI57DE",
        "2193": "WrZsB5bL1bGa3DVZ",
        "2195": "Wt1D1Xmvd6RGkSaO",
        "2197": "X1owaOH7Iy8JQj3S",
        "2199": "XAISZw0Sig3YZbnS",
        "2201": "XGjg1yx9LtPRXgHn",
        "2000": "PiHc2uITovlIouDo",
        "2002": "PkYdswKQGRxLVG0b",
        "2003": "PwbvR8bH2IFLAVY2",
        "2004": "PzVC5j3RcKSCP1EH",
        "2005": "PzwJjXm8YBOjOHwi",
        "2006": "Q1IgR5mpgRcobCE5",
        "2008": "Q3X65vo0EN91hSAO",
        "2010": "QCV7fn7QylbaT15q",
        "2011": "QCWrsMg4kjhaKQvy",
        "2013": "QEF9fkiQeiVscc2i",
        "2015": "QJRq9BmZ2WFpUkkM",
        "2016": "QNCP3ShCfXLgdEbs",
        "2018": "QSfKBUpcDYenYRAi",
        "2020": "QTDRuf86sCnSQkfi",
        "2022": "QU4dxXsY7fFecOkW",
        "2023": "QUZRP2X08GYUQmVH",
        "2025": "QaqyDd9JkG2Db46o",
        "2027": "Qc3PWQ0vvAby55E7",
        "2028": "QcLHWuN7WGzfHIZf",
        "2030": "QesvWRu3ZUUDrMjX",
        "2032": "Qkw0fXrU62Nf41E4",
        "2033": "QlAHv7mnI4IgjtaD",
        "2035": "Qnym2qS63nIIr6MO",
        "2036": "QsCfYQ5JaxrGkiLl",
        "2038": "QsWWOyHbMJju4dYD",
        "2040": "QwE7uPFSeHScMcz4",
        "2041": "Qzl9tjVRtaDryqYX",
        "2043": "R2bCnwdSc2nu1O8n",
        "2045": "R5koyp41aIvYS9AI",
        "2047": "R5nUikLFwuYMkl9R",
        "2048": "R7ZsW0pu77PQL6xa",
        "2050": "R9cSaKPI7VQTWVEE",
        "2052": "RFFHmGt5ABP3cH5i",
        "2053": "RFxr6zbdSNoFIQx1",
        "2054": "RPq3KM4Tputu6Jmd",
        "2056": "RPtdkjSCvt6PgUxv",
        "2058": "RRDcOylGpEZKxU4G",
        "2059": "RcHkAOSDs9ghMzJY",
        "2060": "RdNmObWkViKausX1",
        "2062": "RffaN9f318Gcfh5o",
        "2064": "RgJt5kIX8C4C2TYu",
        "2065": "RkSkEPNqKNrlvwyZ",
        "2066": "Rl6Rfj8mPkwa232l",
        "2067": "Rn4UauoqK2HW1yjK",
        "2068": "Rq6KClpW5Xj05rBL",
        "2070": "Ruv30XgurswmElNo",
        "2071": "S1Y4aFILwaubCS2x",
        "2072": "S3szXa2Zi2QAtk9T",
        "2073": "SAZ1F0CfDzfErM3R",
        "2075": "SAoM7flxDDCMYhCL",
        "2077": "SJy65Orsw4jajEV4",
        "2079": "SQZ6Go9wKnOb3DNt",
        "2080": "SR57POjpKNIQToyW",
        "2082": "SRFey7GaiTW4c21p",
        "2084": "SUe1tHRIGZ3eGgFP",
        "2086": "SWgzPD9QLGmh7kPi",
        "2088": "SX9Za5tK7LcGwj0B",
        "2089": "ScmtSxXycUeCDTs6",
        "2091": "SekZry0cgCkpubUw",
        "2092": "SfYOtDoXrNOxVf7F",
        "2093": "SiBoHudZEbcANSVJ",
        "2095": "SrhJPb7hLXrN03gG",
        "2096": "Sv1Bfg35zN9SXniC",
        "2097": "SvVNHGFbIdZ8EadO",
        "1905": "LihCqT3hlippcYb6",
        "1906": "LkaYzJ2se2IDQLNE",
        "1907": "Lo3bzIZLbBwl85Rg",
        "1909": "Lo5joLHByf6S4jS1",
        "1911": "LqgWs6rcu24xSajF",
        "1912": "LtI5DJQaZlG0Q060",
        "1913": "LuHU8BVZgKxnF1JZ",
        "1914": "LvBKSAkc7WBoi437",
        "1915": "M35gAB2nFpOUvE9b",
        "1917": "M3v3TWxbOSA4dnXj",
        "1919": "MAvEmfrabjU6E9G6",
        "1921": "MDe1KbsSNtgJhlTC",
        "1922": "MGnMkop427OjdB7a",
        "1923": "ML1geW0kBCUtVXld",
        "1924": "MMrKUYpElMWCgMEd",
        "1926": "MNgy7zEIDIRYVJ2k",
        "1927": "MQ0YVAt8qFiOh0yZ",
        "1929": "MRoI82ND2f7DuHvY",
        "1930": "MfL2OSzTxQ6F6aYK",
        "1932": "MmvIA6Jr481afxEE",
        "1934": "MnCygK8Hdz48maLm",
        "1936": "MnKwY6WYVyuTRiBm",
        "1938": "MyBaV808WPbBxBzN",
        "1939": "N0j0BczB2xwezepf",
        "1940": "N7U6QufSGjNIx5En",
        "1942": "N9wVpTYWol5XcckL",
        "1943": "NGDQj0QttBJ0jtPY",
        "1945": "NMzm2XtWZ6VbG3Es",
        "1946": "NdqhjV2BuCnYcsfx",
        "1948": "NdwrFKgPnBfQmzVV",
        "1950": "Np3BVuIwoHgdwXwe",
        "1952": "NqEjJvfyOiOPwBkh",
        "1953": "NqWS0F5S8fCixPDO",
        "1954": "NtTuEOa39pZLAmpx",
        "1956": "NvTVI0gRUBsdFmPs",
        "1957": "Nw3KLhdIiNedQR9L",
        "1959": "O6a3DYdcqqL8LrJL",
        "1961": "O7wUqwnU72VDd27X",
        "1963": "OAntOkPx802P7M12",
        "1965": "OEniRjhlDYJkgPKd",
        "1967": "ONn0lPswKO9Os7HS",
        "1968": "OOl8q1gnEGeVqb4R",
        "1969": "ORuqsJ6TxQMplnwH",
        "1970": "OU3V8vdYTC0hJG0R",
        "1971": "OhGLtLEF8ohpSr2K",
        "1973": "OkWZxyzhGhIxK47Y",
        "1974": "Ol6gLpcIBTIyiCty",
        "1975": "OleVNIObxHebp13P",
        "1977": "OomeumstrctEHCUe",
        "1979": "P0uZg3wQ6fb9Er7d",
        "1981": "P1VFd7CeNEuUXpwx",
        "1983": "P2tFR6yJHVFszXe8",
        "1985": "P7U30bqH1WKmaIcQ",
        "1986": "P7ozXkrTvwKdNcOY",
        "1987": "P9JWNO9alOjxF12S",
        "1988": "P9Q9FXSkaRK1hOKY",
        "1990": "PEpRK5RrMSYJqjpT",
        "1991": "PGw05vbQFZ3DLVnW",
        "1992": "PWs4YRUCffmAN1sy",
        "1994": "PXoFduoxCQdlulSd",
        "1996": "PYG4vhVxksOYQJdt",
        "1997": "Pb43lYcwND8ALiX8",
        "1998": "PctWhME0kQb7ZBge",
        "1999": "PgCoTMYkFY6Ab9Qw",
        "2878": "xzj8cM4HmNjJY1jr",
        "2879": "y2bwSL5SUx5mJorA",
        "2881": "y39Vfhczfpl0xqKf",
        "2882": "y4PbTyWuW47s10kR",
        "2884": "y4qpif6hZJwIssRy",
        "2886": "yCNnhEl2moNe9VrK",
        "2888": "yD6xNhFsG5L4WUni",
        "2889": "yGjNowCohNesZhg3",
        "2890": "yP35NaW3Bp3oDeum",
        "2891": "yPzo9TKFjMANzKEj",
        "2893": "yS7BcoGpnPcoisjL",
        "2895": "yXP8AbEQAQqPgpVB",
        "2897": "yZ0ANEtcdS95y8D0",
        "2899": "yb8nWd74n3u7Zm3P",
        "2900": "yhcWD2kmRSc4v6Ay",
        "2901": "yjBfJcoxA70BTbtL",
        "2903": "ysv9nUHnKCeLGmuB",
        "2904": "ytI4wFckZKlPbMow",
        "2906": "yvJOej36kvtlzDAA",
        "2908": "yzDsChr2MzCdd8uT",
        "2910": "z1aKFd2RotweJZjZ",
        "2912": "z2HybH0w1ejxZSyx",
        "2914": "zAWEjOep8YPVThBc",
        "2915": "zD0VAcarbPWWKnWa",
        "2916": "zQnUGH2ygnkIxGVv",
        "2917": "zXYMEerUPv3ZZQZk",
        "2919": "zaAZHZiCJvuZpQ0E",
        "2920": "zanZsmMbBdEBsKWb",
        "2921": "zfkYPBz2TRQRqCmb",
        "2923": "znkheykGjSHmMzfx",
        "2924": "znvpBIsGX5x3lyeC",
        "2925": "ztjXEHv3n3AdRsYw",
        "2927": "zvSTvQVRpKMoAHn6",
        "2698": "r27JbsuIc0K0m8s0",
        "2699": "r42tI9aDNIxtSkXB",
        "2701": "r6BDi7UNuMfPRIhi",
        "2703": "r7uJPSTUuAGLVZRB",
        "2704": "r9riRtxsBNiaQOpp",
        "2706": "rB1oM6Z823bTo4tJ",
        "2707": "rFUEZbSoAiwz9c3H",
        "2708": "rItS8RYG0dpr2lYH",
        "2710": "rLCFPTQUOMYTkcRX",
        "1867": "KcPD1WVrpaFxWq4r",
        "1868": "Kccc0y7QALRIHU98",
        "1870": "Kf2zkFlfrsUMLhjW",
        "1872": "Krbq7kKYsb7Mo2xE",
        "1873": "KyTOqbWe54vDV7jI",
        "1874": "L07rqXH6yt3gmiUt",
        "1876": "L2XQdRcarJ8JnPME",
        "1878": "L2g1uDmvU8Q22zzm",
        "1879": "L57NdcjnXfhYTxDT",
        "1881": "L5ndNlE7Knna3xYP",
        "1883": "L8YhaqlrIsb20nzg",
        "1885": "LEJhtBQA3vksnqQh",
        "1886": "LG69HvkzMpP2s4nL",
        "1888": "LILrFkaruEc0Fq46",
        "1889": "LLFHRxXqmPMdDP6d",
        "1891": "LQOdxZEzCNMDt99U",
        "1893": "LQSTThA7a35kYgQ1",
        "1895": "LQoWn3hKpiPc2QUp",
        "1897": "LYv3uXGFSreLLVun",
        "1899": "Lc93VOv0qImh4qmX",
        "1901": "LgutUca9Xcvsii80",
        "1903": "LhYiLsYh9qqGp6ET",
        "2783": "tmAH116dOGsOatcE",
        "2785": "tpoWAXIZvHA7rnKf",
        "2786": "tx9HFjKpPnzIvFkl",
        "2787": "txmDHaYDv6nU3b3n",
        "2788": "tyEKPD7PO4CYGTXH",
        "2790": "tzxEzzczIimssQ6v",
        "2792": "u4Do6yGYTI4EJxkd",
        "2794": "u9eaKn9sIaw0IaTa",
        "2795": "uFSsN75pxt8mdQMz",
        "2797": "uJiB1JDcVQ8DSfPk",
        "2798": "uMVf4A42balgVxBb",
        "2800": "uTUKWarqMMwelAkS",
        "2801": "uW9TVWOIs7DBKnhB",
        "2802": "uYkvYjZEDotAHE9O",
        "2803": "uizGg3YRWPVB7oMz",
        "2805": "ukg9utcO3o2REfDw",
        "2806": "ul1YLtMzRftm31Tn",
        "2808": "ulIYHicIUmJuBccI",
        "2809": "un8MiUQ3idnN7zSZ",
        "2811": "unAMUl00qxJCBpaC",
        "2812": "uojxeyfbaXsd6Nwo",
        "2814": "ur6nERX3v075ttDz",
        "2815": "utyiheZSj6nFvMSB",
        "2817": "uzFdx5ToCRMNslNe",
        "2819": "v2QcGBxqgzDLJ0mI",
        "2820": "v3q7X4XGkXspyHCB",
        "2821": "v7QXjlDHorm2O0Hb",
        "2822": "v9UnitYhQ0OxQ0kA",
        "2823": "vLC0YHfMIv2GEXEW",
        "2825": "vPimQPFG4xgl1p9N",
        "2827": "vg2UrbMiMMPyZhds",
        "2829": "vlv3eqWNAOO81GCw",
        "2830": "vmoX341szA2ZgIEz",
        "2831": "vprp9YiaQMuTonms",
        "2833": "vtNvl44kAAbhfSm4",
        "2835": "vuJjTvER8J7TzRz9",
        "2836": "w7RQywyfafFWEQR0",
        "2837": "wAU8hijdcMkK8DU1",
        "2838": "wKcAC4Rs70OFYSOo",
        "2839": "wOzCua8hLfLaPUFq",
        "2841": "wPiyyagKBnHKWPhd",
        "2843": "wQBTV1oi4ceBrGxi",
        "2844": "wbnkbzRMygKcM25I",
        "2845": "wfRRLigCuHZVKnuw",
        "2846": "wjWm1VK5MPmUAhxq",
        "2848": "wp16EyRhkYcqtrFo",
        "2850": "wp1cGLxdBzCrg7V1",
        "2852": "wpFjRs9tDs4KuFBD",
        "2853": "wqmDx9080YKwa7DY",
        "2854": "wsKqtRmlB8qxBChB",
        "2855": "wtYHSRkHAKChv9JQ",
        "2857": "wxC0GvN1vFnJ1kK3",
        "2859": "x1wIvaHppuNezCFY",
        "2861": "x225oMNAyEQdQuoa",
        "2863": "x6o5qQaicRQlCueW",
        "2864": "x7dOUGFl5Jiq3SKz",
        "2865": "x9jqX5rCXR2Qk9Ej",
        "2867": "xB2XylkAEX52wMwc",
        "2868": "xC02He2is1lZPxAz",
        "2870": "xGsOLRfkd7YM8TNR",
        "2872": "xHbaaPsu0Ac83mM2",
        "2874": "xYI2R5bR1woEeFRh",
        "2876": "xrAIIbUE6QpIX79u",
        "2877": "xuRCuCdINKmFDVVv",
        "2684": "pjobUJuuzwhmGQD3",
        "2686": "q1FChXgHKQXWQYbp",
        "2688": "q1oLuLVN3qIlSPSF",
        "2689": "q6BHpVerVd84fE7N",
        "2690": "q95VgRcugr6518xt",
        "2692": "qPPwOL8TunheCIUl",
        "2693": "qdduMcr9uzCaNgrC",
        "2415": "fEN9gK2eFZnceQBq",
        "2417": "fNOPCx5iz1gaNQ0o",
        "2418": "fQSowFHeimZTrVtd",
        "2420": "fUUrYLyawnSVDIPb",
        "2421": "fYHDyMOgxHDXj6Ul",
        "2422": "fdZmhNwuqqxg3F3e",
        "2424": "feV5ufsWy4FtfODt",
        "2694": "qfIT5ZYwrnkmNTXJ",
        "2696": "qjnWOJhH2flS3Gr3",
        "2426": "fejDqZJg2zyx6y08",
        "2427": "flOjAovmKffy2p53",
        "2712": "rLMy5MsV3hathDfH",
        "2714": "rS2AONWahApjTbY7",
        "2715": "rUM3edVnEdXdRzas",
        "2716": "rZIlBBIDNwQNndCr",
        "2718": "rcm52TR3QBCReTxe",
        "2720": "rfpb9ZsMkjkLYA7T",
        "2722": "rj741qCC5kMVdDg1",
        "2724": "rmRr7O8w6tLqxIyX",
        "2725": "ry9P6pkEcL1lD4aw",
        "2727": "ryL1fn18hCb4KMvk",
        "2728": "s8yNZGoUhwdLt2r8",
        "2730": "s92YnHzUgxWK0SY7",
        "2731": "sABIypkIRl2JPiAa",
        "2732": "sF8AXXy4GvRZXeKP",
        "2734": "sI10ZwGRS2yANkPP",
        "2735": "sNiP6qJ89SDCjYep",
        "2736": "sPx7hwx7AaMMNl79",
        "2738": "sSvu9b1R2By2OtN8",
        "2740": "sZGttZeV3RbaNf6W",
        "2741": "sZiyLhz2FsakS2M7",
        "2742": "scGHMikoQh6rH84B",
        "2744": "scNZW5qPqwTiP3lj",
        "2746": "scpBsdf1g3HNciSq",
        "2748": "sesu48Z5vqcQjz2G",
        "2749": "sneGA2rp3M1BN773",
        "2751": "sqH6qp1erZkDh3VD",
        "2753": "sz1YE7moEByEsyYu",
        "2754": "t11J6CIRxsDO6xJP",
        "2755": "t9Gk7i1jBjLkPEah",
        "2757": "tA4uV90dZx3VxLa7",
        "2759": "tASeMHxGOVLLnchh",
        "2761": "tBfDQvysB0IAYrKq",
        "2763": "tGZoYUBReaCZJKDn",
        "2764": "tL0b728Ezr5GKbL4",
        "2765": "tMEuO9wvV6AoPfpt",
        "2767": "tRTToAtzOAV7UVIB",
        "2768": "tUdRI5fBCyNuw3Ir",
        "2770": "tY88DMvmnPkeoMai",
        "2771": "tZOyLsmBBiT6Dncd",
        "2773": "tbwtgF2sERpiBIQn",
        "2774": "tcCpycv5DsMdQrqA",
        "2776": "td0wPrJMwt0VO40X",
        "2777": "tfP4WugO8f7StOPW",
        "2779": "tg9ElfobRjPpCyjo",
        "2781": "thvYsOPqIFqdD1TQ",
        "2782": "tiEC71thwa0WVQrU",
        "2584": "lfu9ZOnGYIkIX8oE",
        "2585": "lkVOg8fk7fCQKfjb",
        "2587": "ll8JkzR6zw65LqV1",
        "2588": "loDf3AGZssocuv2Y",
        "2589": "lonPsrmA4Igv9m9K",
        "2591": "lspVwJkyy7tezhFx",
        "2592": "mCnilIqqsmVhOfCP",
        "2593": "mDFzoAIfrHfuSOvs",
        "2594": "mG8GgyaY1hHRCmyQ",
        "2596": "mH9qS8lpUKnQy3tq",
        "2598": "mKVgstDMIgoGDmgp",
        "2600": "mUTuLI5eZHK8k8XE",
        "2601": "mYzFuAVpcCC7kiQc",
        "2603": "mZOMnW4Z8UNo3diy",
        "2605": "mb81HIz0v43cZEAk",
        "2606": "mbN06iV5qa9RAnYd",
        "2607": "mdoDaJ30dXcofgCc",
        "2609": "me3WdlaQ4tpAjnLc",
        "2610": "mg6TnSAXudBvCJPX",
        "2612": "mq6Dcu4HNrwNOsnV",
        "2613": "mvjUP8siF41K3SOF",
        "2615": "n1lhS5edo870Gcic",
        "2617": "n2FSQghxIl3vcM4H",
        "2619": "n2QHIn4FDiiuGble",
        "2620": "nEiRE9Q0CEI77W2v",
        "2621": "nGyjOeHggeIgkSSs",
        "2623": "nIBfgaQYGzduZyWH",
        "2625": "nMvz5QZqNmw9ox9t",
        "2627": "nQrnILB8qyBfcg0t",
        "2629": "nYSE7e0aLWoQoe1C",
        "2631": "nZHRmVirYlUvTsD6",
        "2633": "nfsjvUvYCcD9c0Tr",
        "2634": "npnbP3lkNWxnbsNR",
        "2635": "nqHWVtH3hO0ZVm12",
        "2637": "nu0KNXZnovgqqxLW",
        "2639": "nvWOJxUuLQBK5u8Z",
        "2640": "nxWajGMlQ7sdagMr",
        "2642": "o3bVIfK8qgIlQKp9",
        "2644": "o6LMnyIuYZxiHM4k",
        "2646": "oKYOo3lPJBrwtUlK",
        "2647": "oO8E9elbOapCgB6t",
        "2649": "oS0w8GC7q0pEWpKU",
        "2651": "oTsA3jNLl79kQm2t",
        "2653": "oVYldGVEdwpQQOkF",
        "2654": "oXnncWINzqDwybOX",
        "2656": "oYDtHzYGZuIHrojO",
        "2657": "obDr44hqV7tvEOPQ",
        "2659": "oc5TnuznJ8jzmpcC",
        "2660": "oexOpaNQz0Q6xU0U",
        "2662": "oqRVa6wAS71cOvGQ",
        "2663": "oqlkNROt1268Tobk",
        "2664": "osS963vWLssNpNws",
        "2666": "ozSE6Ne7dCj3ivaL",
        "2668": "p2HsnpAL2YsPqbVd",
        "2669": "p3mbEaRhcF1iGmbv",
        "2670": "p3qF7YUGd0KNWGnH",
        "2671": "p7npEiAs3SofeUA2",
        "2672": "p9rqW9AZSiRR6yPN",
        "2674": "pDxThjN1JPO1glem",
        "2675": "pFhkeciS33YXn4Hk",
        "2677": "pIkxYIJhK9bVvRed",
        "2679": "pRvfSdZHoTs1ES6F",
        "2681": "pXP0bf5h0uvEauca",
        "2683": "pfzoQ2SbgLDwP9L4",
        "2483": "i8QqORuQsOCPsaaP",
        "2485": "iDWqgFha6Ap1JNyM",
        "2487": "iDfCIqtpk3mfNC2D",
        "2488": "iHNj56WgckePXerJ",
        "2490": "iW982ZUd4T5mY9VY",
        "2491": "iZhltOKyEhFWfgm9",
        "2493": "iaKwtWDYOROA7h06",
        "2494": "icY6WZNL0N62zVin",
        "2496": "ideewz04V1ESRfr8",
        "2498": "ih7mGW7kjKSemAVg",
        "2500": "irf6PB4Gl4zpmm0S",
        "2502": "j4JOVyJM2uftpLor",
        "2504": "j83ptuoDfEusX0x0",
        "2505": "j8TXCXvURQCnwq2E",
        "2506": "j8g7dj5SNP63HPBq",
        "2508": "jAC32g1GwHazzg9L",
        "2509": "jCTfPB4Lt44ygFQk",
        "2511": "jGJuIkS1EjxjbbmP",
        "2512": "jOAvapazrGE5Is5C",
        "2514": "jPAQzmJleO2BzpKU",
        "2515": "jRt1Qyv6dpmfJL9g",
        "2517": "jTBQBr8Ra1MApPxc",
        "2518": "jYtL7Z7C0HKbQSzI",
        "2519": "jYxXFTWAl2qdYHHn",
        "2521": "jdrpp1KZIfGVkTkv",
        "2523": "jfAnxxDEVJMsZtWi",
        "2525": "jhT487wMpvhJoKr3",
        "2527": "jk1C0auQt33rhwbl",
        "2529": "jk91lcSylu6JwniO",
        "2530": "jkXRXM7gDaUKvpUb",
        "2531": "jlagOAiYTy7hrYIU",
        "2532": "jnpR1KPG7H6edLxw",
        "2533": "jpdsDVxjtsD6CmWa",
        "2535": "jqwpNl87ApWZg2mq",
        "2536": "jtJwFXELmYjjtMtE",
        "2538": "jtQzXvrbWcOyAFqR",
        "2540": "jvbfVQmUTDOOZ6ff",
        "2542": "kA5ZIB0Q13k0bqhc",
        "2543": "kBKcseEPT2m9GkFA",
        "2544": "kEJ4XPSfGmq3t1x7",
        "2546": "kHYPKuLvSTULGn0T",
        "2547": "kIq7QbFkMyOFcdVJ",
        "2548": "kZjYbQHy0WvJkcC2",
        "2549": "kaOzK6kJyAMhsAGO",
        "2551": "kawyHFy7cGql4o7G",
        "2552": "khKEkQfs1POovGvL",
        "2553": "kjq3tL0D1OpA7gRp",
        "2555": "kvso2Fmrni5biQOI",
        "2557": "kytzLT5CBkwxLc96",
        "2558": "l1UnuAWXW5YyvqXy",
        "2559": "l7DuYohnM0YEnAWx",
        "2561": "l9Xps9SV7yxlA3QM",
        "2563": "lEMABEV7JDIAyWHv",
        "2565": "lIgvqGAGRZ7WNlh4",
        "2567": "lPSDoSXYFQBrBNbw",
        "2569": "lQXfLcsHjgyGjlIP",
        "2571": "lRIrPIWWXVvwAdHp",
        "2573": "lT8hlAQ5s45IEVWZ",
        "2574": "lYRcpE2G7vkxaCIb",
        "2576": "lZTo3H8Bbp8inrTi",
        "2578": "lacUn4JUctRhBD9E",
        "2580": "laicK7OYj4v4KtPO",
        "2582": "lcVRggEwCerbVmHq",
        "2583": "lethzihZsE76etll",
        "1823": "IrGFFT8aMxnP9I28",
        "1825": "IxOKOPAxOdQzx17x",
        "1826": "J8SSeOntSQr6nWTH",
        "1827": "J9EttFtLTKVBCeun",
        "1829": "JIrs4iJEY1f2QZYV",
        "1831": "JJwXFRU8lgMLASEd",
        "1833": "JMSA7NHoyY7I6spd",
        "1835": "JQT1g01nfT3lHdhH",
        "1837": "JSqWWbUhyf6Q9Rw6",
        "1838": "JVpLyrXmGaL6OR57",
        "1839": "JVuGBem9tkVKy1Uh",
        "1840": "JcPlNf5lbcv3C4DW",
        "1841": "JezJ3MOYEUpuukv0",
        "1843": "JfOutQHPGLrEDA05",
        "1845": "JgFcUIRaXeKiXiVi",
        "1846": "Jlv0oBetxMsHH21Y",
        "1847": "JmDJ3wG4tSE3fewG",
        "1849": "JnNCfP3OJevvTNNU",
        "1851": "JpfSKeKQhEExI2PD",
        "1853": "Jwyhh4UqLDxefhcT",
        "1580": "8PG3e4ZPtHm83qZ1",
        "1581": "8Q5yzFIftSBcxwXb",
        "1583": "8RYBXtRDmyR5wO5T",
        "1584": "8S3LObD87hUJ42G6",
        "1586": "8lKpu05qAG4g3QDU",
        "1588": "8usYDzo4orNgk9zB",
        "1590": "99p7GqHhvdYoFzny",
        "1592": "9AgoaqYPhMPQtiis",
        "1593": "9BFVnkY9IxrZ64d2",
        "2428": "fo84TCZ3wyYL9zTa",
        "2429": "frG38SbsPyW91HNZ",
        "2431": "frwmNVUVVDb2yeRz",
        "2433": "fvGJRFRXFWhL1wed",
        "2434": "g2hij5R3M6uRAcDO",
        "2436": "g80dXwL7joogBOvF",
        "2437": "gIoHb9GvvOpG7DAz",
        "2438": "gOsYvgSa7sce2WiW",
        "2439": "gRFprKqL8c9PUSm4",
        "2441": "gYF6Ilxyx2oxCThK",
        "2443": "gagnC8YET4I7te73",
        "2445": "gibgsq4PRRLl8gC6",
        "2447": "gk3nWln1T0U8y5ZY",
        "2449": "gpIoztJQEwMRfEy4",
        "2451": "gqLLzqUyFBEyc4kr",
        "2452": "gxKOcKp4IQzJ4Hbl",
        "2453": "h18tkGyDs6sLCS6A",
        "2454": "h5LdnWrI4jwrt27O",
        "2456": "hCuZjjxZ4yoUcfLK",
        "2457": "hKZtqp9lZCwDuKoN",
        "2458": "hNEBkacbQotMveCz",
        "2459": "hPeoIEpoHySH4qjF",
        "2461": "hS1HPbwqKx9g7YSm",
        "2463": "hSfSil54HbmZQphL",
        "2464": "hfddtGLSGZjcQTGR",
        "2466": "hgT4dAJer1a64cV4",
        "2468": "hi4j7uBis9U2B3kX",
        "2470": "hjzsXdMTs4sRhW2F",
        "2472": "hnFs49GPsB7nuGGj",
        "2473": "hvdvJ1zh8VbiSKEk",
        "2474": "hwLAhgxTJFxZgRfF",
        "2475": "hx4Htu5eN8H4XyMb",
        "2477": "i0cqI7AQ8OeRbEpz",
        "2479": "i47ZGgHeRb69hHVC",
        "2481": "i87M1Da7jN3WjVq3",
        "1728": "EbromMbPXt2JuMs6",
        "1730": "EkbxdZjZSXwhGnon",
        "1732": "EnpeyD0GKkM8ur9m",
        "1733": "Eqsn6SkYOjdJ4uCB",
        "1735": "Ex8LWuhSaBeXUf52",
        "1736": "F1XK6jlL3vTQjOiP",
        "1737": "F4BXEKStIQ8jqR1b",
        "1739": "FD9QLE4bzdMA3cGG",
        "1741": "FIm3fHAxGsdIl8pE",
        "1742": "FN0cCRwLruW2JvCR",
        "1743": "FNl5Jd22lYNaqCi5",
        "1744": "FPmBtOWiq02U85pW",
        "1745": "FV0EtTgkyDtRulTv",
        "1746": "FWC3Ktbu7lvk0rtH",
        "1748": "FYyK7HBkaLhcspog",
        "1750": "FZFTKSiEJGud9lyN",
        "1752": "Fegxv7YcuBFVRc4V",
        "1754": "FfELFObgNBqCXOXH",
        "1756": "FhL0c2rg9AUOtaf7",
        "1758": "Fp7Vj9OvdGPtL9E0",
        "1760": "FszJp9LqbwG2C2qX",
        "1762": "FuwZdTIe7mCltjWG",
        "1763": "FwXsx5qCP2ItIAL4",
        "1765": "G4EHXMALUVTuAfQu",
        "1766": "GAEfw1a1CPq3dAYM",
        "1767": "GMETb1dy2EjMUVYZ",
        "1768": "GWNAfOIBTegrHYNM",
        "1769": "GbLdhrBKusEpdkpc",
        "1770": "Gpy1pi2DNixfvljB",
        "1772": "GufP17wJWNXROfnc",
        "1774": "GvppZbTaihIzVROh",
        "1776": "GzX9TzzgB5EJl0kv",
        "1778": "GzoG2WfvGLR3BxJR",
        "1779": "H9MN9Lw8tXjTz92i",
        "1781": "H9XHY6Zl4laSKVVa",
        "1783": "HEEq7tubUPWBUHxx",
        "1784": "HGyJn3co3Yu6o2xq",
        "1785": "HMtGRTF62ENMYN18",
        "1787": "HNUFMwBJrlwzRGoX",
        "1788": "HWSEzYLP4bZESRdj",
        "1789": "Ha1sF40LlLqlttxl",
        "1791": "HcD0GtbZWMzZudzk",
        "1792": "Hfg5AvzqPpzZqApa",
        "1793": "HjVCFmB43IPttda4",
        "1794": "HovBZ8qGj5MPSPru",
        "1795": "Htf9k60mlW2qrOpP",
        "1796": "HuCFGRTD63muTthp",
        "1798": "HuSIHlPQofNyRq7F",
        "1799": "I9u08bje9nV10xzP",
        "1801": "IDoZWXMOvwu6TzGs",
        "1802": "IGovwKj1D2p01Jrt",
        "1804": "IJrIW0K1ZB0qDcjk",
        "1805": "ILCw0xu5gnQMNuEF",
        "1806": "IPBQ8OyyRRJQ5kWf",
        "1807": "IT8AGNIM4XGy22I8",
        "1809": "ITKziVwPDOEwWExs",
        "1811": "ITpLXn2YfUgSmaJG",
        "1812": "IUSxKjxrNQ2OHGuf",
        "1814": "IWrmyTekc7YO23M9",
        "1815": "Ig02q6KHYgzR2Pfd",
        "1817": "IiDPlhtFynWUcRLZ",
        "1818": "Inp6T1elcQV3ph1L",
        "1820": "IoCuVYEFwrveUtMV",
        "1822": "IpWoOiBA5VWGfg62",
        "1631": "BAYbuJguBLTM7iZF",
        "1632": "BD3dB7fVD2dvlGwM",
        "1633": "BJa9wyZJoTzQDwHh",
        "1635": "BWLoOJ2PNne7r5aX",
        "1636": "BjhVzgTcW7OL7CFL",
        "1638": "Br4PLRz6uvNQuhLQ",
        "1640": "BsSBULHRdqwwl7XD",
        "1642": "BwL4JzKHFJscYTlO",
        "1644": "C08Bm0vvRQ9mdO3m",
        "1646": "C10fvKJ2CnDZklSq",
        "1647": "C8Ei186F7D2kWWd5",
        "1649": "C9J57qJn05CPPBrx",
        "1651": "CDzPahk16pFtpOV9",
        "1653": "CI937Qw95h3P4Eox",
        "1654": "CJ5eOXwk2eBpj0hJ",
        "1656": "CM7BYW3F44fvPHe2",
        "1657": "COty1HpXD9fd5eIB",
        "1659": "CPhXd7i6t1UTfoxa",
        "1660": "CQWcmbLYYKzMh4ul",
        "1661": "CVzoxDeIO307FZXP",
        "1662": "CW6rymI3Q20u5K0m",
        "1663": "CYrODTV3YGVwnFdg",
        "1664": "CbR0ilsI7lKKnEk7",
        "1665": "CkARpbEwPj9bIzBP",
        "1667": "Cm32S3GLBtfzL5q5",
        "1669": "CmeOe5OEo9jl6fIy",
        "1670": "Co0Av5l98cc2dhFB",
        "1671": "CoGalxkksPV3vgZj",
        "1673": "CwEw7ogWGNpe33O6",
        "1675": "Cwhvb2hkfJ0aWoGb",
        "1677": "Cxdi6CQ8JhbpkXJV",
        "1679": "CzBR8I5rSI28NKJg",
        "1681": "D2t0pUP8CaUT2BB1",
        "1683": "DGA0J0JN5YOsHn71",
        "1684": "DGArk7jIqKVHNlqG",
        "1685": "DHAXpdbSDO2LojTJ",
        "1687": "DNShdQNlh996Gu32",
        "1688": "DXpQAKpXUaTphvOz",
        "1690": "DXv6FewRYYuKDPQb",
        "1692": "DXwMauwGaVVIgkCG",
        "1693": "DbasXqIFxWstt7j3",
        "1694": "DdG7jvQ9vTSr5VpC",
        "1695": "Df0WBjZMWblyI7eH",
        "1696": "DfM8yrhJkevzkN9G",
        "1697": "Dh2W0RJ5y1EnfR30",
        "1699": "DjMVf3F9s8hgtamV",
        "1701": "DjXrUCWE9GFYWwN3",
        "1703": "DmAFUN0bLMCBGTKC",
        "1704": "DmqQ9mrrB5orH9H6",
        "1706": "E3ODgZh9pvWcD0gl",
        "1708": "E4aitqIZiKVwnCil",
        "1710": "EBDXSGR7nBkO7gIU",
        "1711": "EBZgsvbNTj5Tl98j",
        "1713": "ECsk1xXz8QLwCyQh",
        "1714": "EHhtwdmdmfQPjcSr",
        "1715": "EME46WbyFePipfgC",
        "1716": "EMXiYmtzBqY5rS7K",
        "1717": "ERfOv3fM8flOVvJR",
        "1719": "ESnW6fIzypDGAH5b",
        "1720": "EVd8foGnSfeeH3v5",
        "1722": "EWy6zaQ0U7oacvn6",
        "1723": "EXbtA1ToTvnCVAQw",
        "1725": "EYkVZQRGDiAOHIXX",
        "1726": "EZLJe8nOBXblDV1t",
        "1520": "6SEosIk6BI1SmtIi",
        "1522": "6Wy08MyCwK4cacPT",
        "1524": "6XHbyiMRhLoDxxPt",
        "1525": "6cyewkVndJbWx3vM",
        "1527": "6dMpO9kai0VM7htd",
        "1529": "6fVsBVHuNbcbURCT",
        "1531": "6jKCZJJIo8TvzdiY",
        "1533": "6lSojeHIZdLwjHVd",
        "1535": "6mNagliKRtj8CioC",
        "1536": "6my8LuDHg0OBHMIg",
        "1537": "6poiqEx0OjNcCqNt",
        "1538": "6ysMlHgThDE49wF3",
        "1539": "74PDJoHaXHkJfX1D",
        "1540": "7AocP2TgemCNWzou",
        "1541": "7CIpDIlTYuvHMEKU",
        "1543": "7F9qGrc9Qm1j7dEt",
        "1544": "7L5dhs4JqBknD4wL",
        "1546": "7LJYZ9osj83ixFOs",
        "1547": "7LfxD8PXsjbMMHkD",
        "1548": "7PXOAkqMBAP2aatK",
        "1550": "7RCT4kfSJY4aRQdY",
        "1551": "7TKnZzrHQF5MigQT",
        "1553": "7XQGCyxgULvnJLF7",
        "1554": "7YfmBhNddtWSwJYO",
        "1555": "7c6d1rcMprq8jga3",
        "1557": "7dnHl7glrU8EKIcS",
        "1558": "7gXypp4e7APjga6x",
        "1559": "7jsUxjkupaNtPCqz",
        "1560": "7n6QYxbgc2jbPbgy",
        "1562": "7phe1Pud5T5WABwC",
        "1564": "81LiDCVYq6vPe663",
        "1565": "85ZqxzkIABIRrwH2",
        "1567": "88FnprhuZz3NCD1q",
        "1569": "8A9qSKSHrgUhZphU",
        "1571": "8IBF3pD0M0VMc4PQ",
        "1573": "8IsPG8bygFiQThZO",
        "1575": "8JGvIhVQNmgYImJQ",
        "1576": "8JVwTnsuTQB1jcGv",
        "1577": "8LZkm15knEYTHgqD",
        "1579": "8OLk0wbw6KiWWx5o",
        "1594": "9D87olupmywDiKyR",
        "1595": "9F7oKXbYNkLPWjtq",
        "1596": "9J7Xd8sy1nBpWHU0",
        "1597": "9VGT0riTxKKfqvVh",
        "1599": "9ZZACFAG3x2P83cR",
        "1601": "9cATZDKIdBc6K6qy",
        "1602": "9dYI1Q6eMxTGWmK8",
        "1603": "9sBHp0aUiGWyymKQ",
        "1605": "9xFLWzkd0yNR2c7b",
        "1607": "9xJ6aBbMYI51AXZl",
        "1609": "9xiJPHCn0MdH7rAc",
        "1611": "A5lwUbd8FcQqTXWN",
        "1613": "A9A7caU9RyBsQkXR",
        "1614": "ADw4wJev0Mqdc3DG",
        "1616": "AL3WCQrvR011OgNN",
        "1617": "ANwNHHgHOt9cy4sF",
        "1619": "ARZnQRV3q4S5LJhx",
        "1621": "AYBwigyw8uFPeN9P",
        "1623": "AfunqnSLVVtu47wV",
        "1625": "AqncKTJx9bKJgo7G",
        "1626": "AvGXfoznfRoo3C0Y",
        "1627": "B14pEq01bYrZXImz",
        "1628": "B5eC72MoNDHKko1t",
        "1629": "B6O88et8USKanX8T",
        "1421": "2KGaZKv1aDjjNHLP",
        "1422": "2L8Hme9kEEh7FOAL",
        "1424": "2MOsf5GGGOT7rOIG",
        "1426": "2TRNMlbGphF6ibbA",
        "1428": "2Wbfgl8xvcDzgIok",
        "1430": "2XmWyyLYH9TzbRiT",
        "1432": "2aW3MQsm983fvOWC",
        "1434": "2cslxwGAjzKGNK5S",
        "1435": "2gwlGZLXhsFiKAYH",
        "1437": "2kRnlcgUSHhfOI3h",
        "1438": "2l7aW8WATIziFh5f",
        "1439": "2oQP06HkAfFiRwA3",
        "1441": "31RBKdpRsjjHsTV6",
        "1443": "31wKDVGyxZNMEP5H",
        "1445": "33ENz4N0FD7bNzwt",
        "1446": "35JiqPEVR3E6gYDQ",
        "1447": "3Hogee86Gm5P7bXS",
        "1448": "3JuUBgCvek6X3CcH",
        "1449": "3TCayelJfuF0L0iy",
        "1451": "3ZFL044D5tbuamUu",
        "1452": "3aIrVBmOa1mMj5TI",
        "1453": "3iHRJ1a53Ame69vR",
        "1455": "3kJQJHffDD9pRnBQ",
        "1457": "3sA78EzT0dI46mbF",
        "1459": "41EuFRn1RqO0NdG3",
        "1460": "476QrgdtX8CVvmsG",
        "1462": "47dF17GxVZMqycaq",
        "1463": "49gmWBTm2tKTeX0a",
        "1464": "4B4aeYcTjaaoSmrX",
        "1465": "4RMcH0ZllXAXFaTG",
        "1466": "4Rx5qYzzIbNwibEV",
        "1467": "4TaqfCA3Hd5MWh6y",
        "1469": "4eETYIwR5lTMc9q7",
        "1471": "4hvnxg5aHrjalpus",
        "1473": "4jA9CqdHnuKnFNMq",
        "1474": "4mL4l8vEiziedl1v",
        "1476": "4sGrhA3lJQQwfDBu",
        "1478": "4zw3b1GqvA06l3JP",
        "1480": "52ua8y32xmzEPQP1",
        "1482": "56DOGL5fwmz4OtvO",
        "1483": "57EuEU1pi8DnyulC",
        "1484": "57Vl4ZVd4Jo2f4m8",
        "1485": "5Bkm1q4MI2Q4H81m",
        "1487": "5Jb4qOlflyrndU60",
        "1489": "5U72BMCuE9htRpFt",
        "1490": "5Yr7M5KtgbyecQGA",
        "1491": "5ZBjfHBmw36rrFD1",
        "1492": "5husYBEFjd8qEV2h",
        "1494": "5inauXpN8UdXkSu2",
        "1496": "5kKqrG5kVU7tyjUh",
        "1497": "5l7GvvSPvwXQpUC0",
        "1499": "5mIrrZCyk5CN0Fh1",
        "1501": "5rKUKu5JpcX18f4q",
        "1502": "5rSXkR7bCCVYeMRv",
        "1504": "5rjlhAXnAVw3Dt51",
        "1505": "5uhOCvSSGi7XkYB8",
        "1507": "5x9pboO3NN44skkX",
        "1508": "5xuW6ywJPnSOViYt",
        "1510": "67K3YFDxIXOHdUdk",
        "1512": "68Uz20iFWDv8ygz9",
        "1514": "6EDSTzk9wGt1lg0b",
        "1515": "6FhO564dvr8Z0Ya1",
        "1516": "6LeDwmHiGRjktjuL",
        "1518": "6OYdhJAG9Pd3exXG",
        "299856": "nYSE7e0aLWoQoe1C",
        "299857": "BsSBULHRdqwwl7XD",
        "299858": "DjXrUCWE9GFYWwN3",
        "299860": "tg9ElfobRjPpCyjo",
        "299862": "pFhkeciS33YXn4Hk",
        "299864": "R7ZsW0pu77PQL6xa",
        "299865": "pfzoQ2SbgLDwP9L4",
        "299867": "rj741qCC5kMVdDg1",
        "299868": "CVzoxDeIO307FZXP",
        "299870": "68Uz20iFWDv8ygz9",
        "299871": "L2g1uDmvU8Q22zzm",
        "299872": "tRTToAtzOAV7UVIB",
        "299873": "q6BHpVerVd84fE7N",
        "299874": "Rl6Rfj8mPkwa232l",
        "299876": "jtJwFXELmYjjtMtE",
        "299877": "Np3BVuIwoHgdwXwe",
        "299878": "UTFdPRe3fGxtMRPK",
        "299879": "GzoG2WfvGLR3BxJR",
        "299880": "fUUrYLyawnSVDIPb",
        "299881": "YwEfZYI8teQYjUZP",
        "299883": "Y9eZSE13EHOM8eq5",
        "299885": "XZCgK9c613CDXUKM",
        "299887": "w7RQywyfafFWEQR0",
        "299888": "cyBFGrYb4Ve23niA",
        "299890": "HcD0GtbZWMzZudzk",
        "299892": "I9u08bje9nV10xzP",
        "299893": "rItS8RYG0dpr2lYH",
        "299894": "7c6d1rcMprq8jga3",
        "299895": "0KCXmug2fz6HD4QN",
        "299896": "OleVNIObxHebp13P",
        "299897": "lkVOg8fk7fCQKfjb",
        "299899": "IT8AGNIM4XGy22I8",
        "299900": "PzVC5j3RcKSCP1EH",
        "299902": "ZV0nICCUcebJNpiO",
        "299903": "yS7BcoGpnPcoisjL",
        "299905": "i47ZGgHeRb69hHVC",
        "299906": "6my8LuDHg0OBHMIg",
        "299908": "scNZW5qPqwTiP3lj",
        "299910": "Sv1Bfg35zN9SXniC",
        "299912": "XceDx15OPrKZkqjP",
        "299914": "BJa9wyZJoTzQDwHh",
        "299915": "sF8AXXy4GvRZXeKP",
        "299916": "JnNCfP3OJevvTNNU",
        "299917": "Vn2VY6FVNrb4PjTe",
        "299918": "HGyJn3co3Yu6o2xq",
        "299920": "vprp9YiaQMuTonms",
        "299922": "PGw05vbQFZ3DLVnW",
        "299923": "GAEfw1a1CPq3dAYM",
        "299925": "laicK7OYj4v4KtPO",
        "299926": "Rq6KClpW5Xj05rBL",
        "299928": "rLMy5MsV3hathDfH",
        "299930": "IoCuVYEFwrveUtMV",
        "299931": "s8yNZGoUhwdLt2r8",
        "299933": "5l7GvvSPvwXQpUC0",
        "299934": "tyEKPD7PO4CYGTXH",
        "299935": "yGjNowCohNesZhg3",
        "299936": "PzwJjXm8YBOjOHwi",
        "299938": "T2WUcZEX0brmq1Gn",
        "299939": "CoGalxkksPV3vgZj",
        "299940": "XlN9NETfGZT3x7e9",
        "299942": "74PDJoHaXHkJfX1D",
        "299943": "lQXfLcsHjgyGjlIP",
        "299944": "MnCygK8Hdz48maLm",
        "299945": "un8MiUQ3idnN7zSZ",
        "299947": "CJ5eOXwk2eBpj0hJ",
        "299948": "loDf3AGZssocuv2Y",
        "299949": "h5LdnWrI4jwrt27O",
        "299951": "ZT4Pvku61R64Z33u",
        "299953": "Y8x8ke2B0Mp2aRKV",
        "299954": "wPiyyagKBnHKWPhd",
        "299956": "0iAp7rF3Xr9PY6OJ",
        "299957": "EZLJe8nOBXblDV1t",
        "299959": "eOVeuYGYvGRcOF88",
        "299960": "2IYeIYYaKUrdTgga",
        "299962": "3ZFL044D5tbuamUu",
        "299964": "xYI2R5bR1woEeFRh",
        "299966": "x7dOUGFl5Jiq3SKz",
        "299967": "LQOdxZEzCNMDt99U",
        "299968": "QCV7fn7QylbaT15q",
        "299969": "9ZZACFAG3x2P83cR",
        "299970": "RFxr6zbdSNoFIQx1",
        "299971": "cIXYAuCeO8D4xnW1",
        "299973": "hnFs49GPsB7nuGGj",
        "299975": "WUzVjtbo4mtjPKcA",
        "299977": "Q1IgR5mpgRcobCE5",
        "299978": "tZOyLsmBBiT6Dncd",
        "299980": "oKYOo3lPJBrwtUlK",
        "299981": "eMZwgpw0WO4Qv6dV",
        "299983": "Xc355iJ1OoUXs23I",
        "299984": "11lLzY2qYaswNybm",
        "299986": "EBZgsvbNTj5Tl98j",
        "299987": "gibgsq4PRRLl8gC6",
        "299988": "FPmBtOWiq02U85pW",
        "299989": "QsWWOyHbMJju4dYD",
        "299990": "scGHMikoQh6rH84B",
        "299991": "ZKEQDLX7vjwU1jv9",
        "299992": "wbnkbzRMygKcM25I",
        "299993": "hS1HPbwqKx9g7YSm",
        "299995": "yPzo9TKFjMANzKEj",
        "299996": "2TRNMlbGphF6ibbA",
        "299997": "LQoWn3hKpiPc2QUp",
        "299998": "gRFprKqL8c9PUSm4",
        "299999": "L8YhaqlrIsb20nzg",
        "300000": "thvYsOPqIFqdD1TQ",
        "300002": "IGovwKj1D2p01Jrt",
        "300003": "ih7mGW7kjKSemAVg",
        "300005": "jRt1Qyv6dpmfJL9g",
        "300007": "1EJeiiCTV0mPZ0cq",
        "300009": "B5eC72MoNDHKko1t",
        "300011": "nQrnILB8qyBfcg0t",
        "300012": "oVYldGVEdwpQQOkF",
        "300013": "5Bkm1q4MI2Q4H81m",
        "300014": "sI10ZwGRS2yANkPP",
        "300015": "0MARmcuQAxi7MUrO",
        "300017": "NtTuEOa39pZLAmpx",
        "300018": "YaNlHykreRvzm3nB",
        "300020": "XchHv7EcoXD3m84z",
        "300021": "ytI4wFckZKlPbMow",
        "300023": "NqEjJvfyOiOPwBkh",
        "300024": "Xek6E1BBjF2JDeX2",
        "300025": "SX9Za5tK7LcGwj0B",
        "300026": "cXgyRdnlCur9OFyr",
        "300028": "7LfxD8PXsjbMMHkD",
        "300029": "5inauXpN8UdXkSu2",
        "300030": "QesvWRu3ZUUDrMjX",
        "300031": "yD6xNhFsG5L4WUni",
        "300032": "5Yr7M5KtgbyecQGA",
        "300033": "7RCT4kfSJY4aRQdY",
        "300035": "IpWoOiBA5VWGfg62",
        "300037": "jk91lcSylu6JwniO",
        "300039": "alDer5Bmw8BbJMjo",
        "300041": "frG38SbsPyW91HNZ",
        "300043": "V6AlpgGwMaf1LCjx",
        "300045": "xzj8cM4HmNjJY1jr",
        "300046": "N0j0BczB2xwezepf",
        "300048": "DbasXqIFxWstt7j3",
        "300050": "4eETYIwR5lTMc9q7",
        "300052": "8JGvIhVQNmgYImJQ",
        "300053": "QEF9fkiQeiVscc2i",
        "300054": "8JVwTnsuTQB1jcGv",
        "300056": "6XHbyiMRhLoDxxPt",
        "300057": "vLC0YHfMIv2GEXEW",
        "300059": "TXeSSpuoGZ5fLiaX",
        "300061": "MRoI82ND2f7DuHvY",
        "300062": "2gwlGZLXhsFiKAYH",
        "300064": "t9Gk7i1jBjLkPEah",
        "300066": "8OLk0wbw6KiWWx5o",
        "300068": "SAZ1F0CfDzfErM3R",
        "300069": "E3ODgZh9pvWcD0gl",
        "300071": "EnpeyD0GKkM8ur9m",
        "300072": "lIgvqGAGRZ7WNlh4",
        "300074": "7YfmBhNddtWSwJYO",
        "300076": "wQBTV1oi4ceBrGxi",
        "300078": "EMXiYmtzBqY5rS7K",
        "300079": "dR9a2cH1neLKQHUm",
        "300081": "8LZkm15knEYTHgqD",
        "300082": "ZGzzUVM1eJuk8v3x",
        "300084": "jpdsDVxjtsD6CmWa",
        "300085": "FZFTKSiEJGud9lyN",
        "300086": "iZhltOKyEhFWfgm9",
        "300088": "3JuUBgCvek6X3CcH",
        "300090": "CDzPahk16pFtpOV9",
        "300092": "yzDsChr2MzCdd8uT",
        "300094": "9BFVnkY9IxrZ64d2",
        "300095": "wAU8hijdcMkK8DU1",
        "300097": "znvpBIsGX5x3lyeC",
        "300098": "FN0cCRwLruW2JvCR",
        "300100": "MyBaV808WPbBxBzN",
        "300102": "n1lhS5edo870Gcic",
        "300103": "4RMcH0ZllXAXFaTG",
        "300105": "dSpeucirY6pwTWtd",
        "300106": "nMvz5QZqNmw9ox9t",
        "300107": "rLCFPTQUOMYTkcRX",
        "300108": "b7aMQyGdeSXXL02I",
        "300110": "F4BXEKStIQ8jqR1b",
        "300111": "fQSowFHeimZTrVtd",
        "300112": "J9EttFtLTKVBCeun",
        "300114": "IrGFFT8aMxnP9I28",
        "300116": "EME46WbyFePipfgC",
        "300118": "y4PbTyWuW47s10kR",
        "300120": "2XmWyyLYH9TzbRiT",
        "300122": "c2s89JHcsSjTFpHy",
        "300124": "eOgRsTtemoTJRdjd",
        "300125": "HEEq7tubUPWBUHxx",
        "300126": "obDr44hqV7tvEOPQ",
        "300127": "ZSkbYfFjl9dY2K8M",
        "300128": "LILrFkaruEc0Fq46",
        "300129": "TQ1FFN2XGE9VnNdI",
        "300130": "7gXypp4e7APjga6x",
        "300131": "RkSkEPNqKNrlvwyZ",
        "300133": "QSfKBUpcDYenYRAi",
        "300135": "N7U6QufSGjNIx5En",
        "300136": "7phe1Pud5T5WABwC",
        "300137": "x6o5qQaicRQlCueW",
        "300138": "TVCrIX0rXfnzyMuE",
        "300139": "25ksHoKSVRRRoHJi",
        "300141": "ThdF7wHL37veu4sL",
        "300143": "aIyTRTLSUHE9eU5K",
        "300145": "WJ4o6efY3BN9pTvj",
        "300147": "a46EzYoXxGjO6plZ",
        "300149": "EbromMbPXt2JuMs6",
        "300151": "kaOzK6kJyAMhsAGO",
        "300164": "6LeDwmHiGRjktjuL",
        "300165": "gxKOcKp4IQzJ4Hbl",
        "300167": "TVrtMANFcApSfKIs",
        "300168": "jGJuIkS1EjxjbbmP",
        "300169": "ZBrY7khPS98iS0Pd",
        "300171": "Fp7Vj9OvdGPtL9E0",
        "300172": "Krbq7kKYsb7Mo2xE",
        "300174": "Ex8LWuhSaBeXUf52",
        "300176": "W4nc6rH9ECaeXgRI",
        "300177": "81LiDCVYq6vPe663",
        "300178": "JmDJ3wG4tSE3fewG",
        "300179": "RcHkAOSDs9ghMzJY",
        "300181": "14kwLy1qENcz2pFb",
        "300182": "XAISZw0Sig3YZbnS",
        "300184": "1CA4dj6ett9jhGKv",
        "300185": "9D87olupmywDiKyR",
        "300187": "2L8Hme9kEEh7FOAL",
        "300188": "mq6Dcu4HNrwNOsnV",
        "300189": "A5lwUbd8FcQqTXWN",
        "300191": "OhGLtLEF8ohpSr2K",
        "300193": "uJiB1JDcVQ8DSfPk",
        "300194": "b4uZADgrYzMVbC3X",
        "300196": "uojxeyfbaXsd6Nwo",
        "300198": "SJy65Orsw4jajEV4",
        "300199": "AL3WCQrvR011OgNN",
        "300201": "SrhJPb7hLXrN03gG",
        "300202": "NGDQj0QttBJ0jtPY",
        "300203": "W8FpR9xeenTngrfv",
        "300205": "HWSEzYLP4bZESRdj",
        "300206": "byB9eB1qGqRuIxNa",
        "300208": "jOAvapazrGE5Is5C",
        "300210": "nxWajGMlQ7sdagMr",
        "300212": "ztjXEHv3n3AdRsYw",
        "300213": "jkXRXM7gDaUKvpUb",
        "300214": "mZOMnW4Z8UNo3diy",
        "300216": "p3mbEaRhcF1iGmbv",
        "300217": "Ul6eHYZlU7IKzlfm",
        "300218": "rmRr7O8w6tLqxIyX",
        "300220": "xrAIIbUE6QpIX79u",
        "300222": "Wk1cfA5e0bMI57DE",
        "300224": "BAYbuJguBLTM7iZF",
        "300226": "XGjg1yx9LtPRXgHn",
        "300227": "bFWvHGZnYqKtLES0",
        "300228": "JcPlNf5lbcv3C4DW",
        "300229": "QNCP3ShCfXLgdEbs",
        "300230": "3Hogee86Gm5P7bXS",
        "300232": "D2t0pUP8CaUT2BB1",
        "300233": "OOl8q1gnEGeVqb4R",
        "300235": "ZZiE3PsZblNfrZ4P",
        "300237": "SWgzPD9QLGmh7kPi",
        "300239": "uizGg3YRWPVB7oMz",
        "300241": "B6O88et8USKanX8T",
        "300243": "wjWm1VK5MPmUAhxq",
        "300244": "lT8hlAQ5s45IEVWZ",
        "300246": "lZTo3H8Bbp8inrTi",
        "300247": "XoCjtpG9c01YzsaM",
        "300248": "ZDUS8Ce7kitgfR1r",
        "300249": "TMJ0RZbr3tUk1CzV",
        "300250": "sPx7hwx7AaMMNl79",
        "300251": "ctHPn9rn1dwIvxwb",
        "300252": "L5ndNlE7Knna3xYP",
        "300254": "E4aitqIZiKVwnCil",
        "300255": "GbLdhrBKusEpdkpc",
        "300256": "Lo3bzIZLbBwl85Rg",
        "300257": "l7DuYohnM0YEnAWx",
        "300258": "kA5ZIB0Q13k0bqhc",
        "300259": "Cwhvb2hkfJ0aWoGb",
        "300261": "67K3YFDxIXOHdUdk",
        "300263": "rFUEZbSoAiwz9c3H",
        "300265": "EHhtwdmdmfQPjcSr",
        "300266": "nfsjvUvYCcD9c0Tr",
        "300268": "oexOpaNQz0Q6xU0U",
        "300269": "tGZoYUBReaCZJKDn",
        "300271": "6SEosIk6BI1SmtIi",
        "300272": "Lc93VOv0qImh4qmX",
        "300273": "n2FSQghxIl3vcM4H",
        "300275": "cjrqB3k9PQJDzpaJ",
        "300276": "nvWOJxUuLQBK5u8Z",
        "300278": "o6LMnyIuYZxiHM4k",
        "300280": "W7qH1qMG2MvxGNX3",
        "300282": "lcVRggEwCerbVmHq",
        "300284": "s92YnHzUgxWK0SY7",
        "300286": "X1owaOH7Iy8JQj3S",
        "300288": "tx9HFjKpPnzIvFkl",
        "300289": "LYv3uXGFSreLLVun",
        "300291": "g80dXwL7joogBOvF",
        "300293": "SiBoHudZEbcANSVJ",
        "300295": "h18tkGyDs6sLCS6A",
        "300296": "lfu9ZOnGYIkIX8oE",
        "300298": "l9Xps9SV7yxlA3QM",
        "300299": "K1nsWUkdzeACjgcA",
        "300300": "UZ2HVHGI597PAp07",
        "300301": "OkWZxyzhGhIxK47Y",
        "300302": "Ypcyp5dyMIJd9bHZ",
        "300303": "lonPsrmA4Igv9m9K",
        "300305": "xuRCuCdINKmFDVVv",
        "300306": "bjh9UASMYsM1wIED",
        "300307": "C8Ei186F7D2kWWd5",
        "300308": "P7U30bqH1WKmaIcQ",
        "300310": "DfM8yrhJkevzkN9G",
        "300311": "v2QcGBxqgzDLJ0mI",
        "300313": "OomeumstrctEHCUe",
        "300315": "CzBR8I5rSI28NKJg",
        "300317": "9J7Xd8sy1nBpWHU0",
        "300318": "kBKcseEPT2m9GkFA",
        "300320": "mG8GgyaY1hHRCmyQ",
        "300322": "MnKwY6WYVyuTRiBm",
        "300324": "bSkZY9JtLtfj985g",
        "300325": "T4H9fKjud0XRnBjO",
        "300327": "2Gx3eCbSef0daMQG",
        "300328": "hi4j7uBis9U2B3kX",
        "300330": "49gmWBTm2tKTeX0a",
        "300332": "iHNj56WgckePXerJ",
        "300333": "NdwrFKgPnBfQmzVV",
        "300335": "dC3eoRacXgylTuB3",
        "300337": "unAMUl00qxJCBpaC",
        "300338": "PEpRK5RrMSYJqjpT",
        "300339": "1DUGhYdC6aeE5uKR",
        "300340": "1kMceMyYZ1lx9CQz",
        "300341": "SR57POjpKNIQToyW",
        "300342": "mYzFuAVpcCC7kiQc",
        "300344": "8usYDzo4orNgk9zB",
        "300345": "qPPwOL8TunheCIUl",
        "300347": "476QrgdtX8CVvmsG",
        "300348": "FWC3Ktbu7lvk0rtH",
        "300350": "r27JbsuIc0K0m8s0",
        "300351": "XRzQvqenrj3OlkQe",
        "300353": "8lKpu05qAG4g3QDU",
        "300354": "0p5eTESDYNJjZcX4",
        "300356": "9xJ6aBbMYI51AXZl",
        "300358": "npnbP3lkNWxnbsNR",
        "300359": "BWLoOJ2PNne7r5aX",
        "300360": "gIoHb9GvvOpG7DAz",
        "300361": "Htf9k60mlW2qrOpP",
        "300363": "mbN06iV5qa9RAnYd",
        "300365": "4B4aeYcTjaaoSmrX",
        "300367": "SfYOtDoXrNOxVf7F",
        "300368": "Gpy1pi2DNixfvljB",
        "300369": "tASeMHxGOVLLnchh",
        "300371": "ILCw0xu5gnQMNuEF",
        "300372": "WcrBCVNheEMydkY5",
        "300373": "icY6WZNL0N62zVin",
        "300374": "hNEBkacbQotMveCz",
        "300375": "kytzLT5CBkwxLc96",
        "300377": "d1vjjMRs0EwNzP8q",
        "300378": "SRFey7GaiTW4c21p",
        "300380": "z1aKFd2RotweJZjZ",
        "300381": "7CIpDIlTYuvHMEKU",
        "300383": "G4EHXMALUVTuAfQu",
        "300385": "4zw3b1GqvA06l3JP",
        "300386": "qjnWOJhH2flS3Gr3",
        "300388": "kIq7QbFkMyOFcdVJ",
        "300389": "YqxYTYUJsps6TILf",
        "300390": "CW6rymI3Q20u5K0m",
        "300391": "Nw3KLhdIiNedQR9L",
        "300392": "SzaZuOdKXmpVhe3s",
        "300394": "MQ0YVAt8qFiOh0yZ",
        "300396": "dJE4DCqAUFVX6gZR",
        "300398": "UrVGROAv8GZ7sjpW",
        "300399": "ec4G8cdndttKXLzQ",
        "300400": "00ZLq1KDLX8Pydd6",
        "300401": "iDfCIqtpk3mfNC2D",
        "300403": "9xiJPHCn0MdH7rAc",
        "300405": "YQEpfqeIk9Y5R5rm",
        "300406": "dPgKxGF9UJI7ASh2",
        "300408": "e0naJG4XrvhAuTiu",
        "300410": "dp0HjiZGaGhwTqGE",
        "300412": "Q3X65vo0EN91hSAO",
        "300152": "6jKCZJJIo8TvzdiY",
        "300153": "tL0b728Ezr5GKbL4",
        "300154": "pIkxYIJhK9bVvRed",
        "300155": "fBqYZEtZnKnyn96U",
        "300157": "kjq3tL0D1OpA7gRp",
        "300159": "l1UnuAWXW5YyvqXy",
        "300161": "SekZry0cgCkpubUw",
        "300162": "pDxThjN1JPO1glem",
        "300163": "Z3QzZOXmsa4x3Igp",
        "300427": "ddsuHlyEUgp3jJVY",
        "300428": "ANwNHHgHOt9cy4sF",
        "300430": "p2HsnpAL2YsPqbVd",
        "300431": "jhT487wMpvhJoKr3",
        "300432": "5Jb4qOlflyrndU60",
        "300433": "Qkw0fXrU62Nf41E4",
        "300434": "JpfSKeKQhEExI2PD",
        "300436": "EWy6zaQ0U7oacvn6",
        "300437": "ERfOv3fM8flOVvJR",
        "300438": "zQnUGH2ygnkIxGVv",
        "300439": "1hJVIXNnLu0lUDIi",
        "300440": "MDe1KbsSNtgJhlTC",
        "300441": "ryL1fn18hCb4KMvk",
        "300442": "O6a3DYdcqqL8LrJL",
        "300443": "ZAI3AIMBviCLr75I",
        "300445": "0OdPOXHTZx5oYvkO",
        "300446": "VOR1yf7q8r5kw1d1",
        "300448": "AYBwigyw8uFPeN9P",
        "300450": "YC8OOvChjFJaHuOg",
        "300451": "r42tI9aDNIxtSkXB",
        "300452": "QlAHv7mnI4IgjtaD",
        "300453": "Ol6gLpcIBTIyiCty",
        "300454": "txmDHaYDv6nU3b3n",
        "300456": "UVfcSCa6hwPMBLAR",
        "300457": "JMSA7NHoyY7I6spd",
        "300458": "mKVgstDMIgoGDmgp",
        "300459": "RffaN9f318Gcfh5o",
        "300461": "kZjYbQHy0WvJkcC2",
        "300462": "uzFdx5ToCRMNslNe",
        "300464": "QsCfYQ5JaxrGkiLl",
        "300466": "ZCWg7fE5OakmXdHt",
        "300467": "DXv6FewRYYuKDPQb",
        "300468": "jnpR1KPG7H6edLxw",
        "300470": "B14pEq01bYrZXImz",
        "300471": "IWrmyTekc7YO23M9",
        "300472": "LvBKSAkc7WBoi437",
        "300474": "wKcAC4Rs70OFYSOo",
        "300475": "ZWqdpZNH61a9LMZt",
        "300476": "ayUcDlIPgCpGHZaY",
        "300477": "QCWrsMg4kjhaKQvy",
        "300478": "2843G7neWmiDntHc",
        "300479": "47dF17GxVZMqycaq",
        "300481": "ECsk1xXz8QLwCyQh",
        "300482": "eDXWyeotmO0kSrs9",
        "300484": "ONn0lPswKO9Os7HS",
        "300485": "dCvWLaelO15ighoZ",
        "300486": "56DOGL5fwmz4OtvO",
        "300488": "bhG4QSfVaaqjtlKe",
        "300489": "DdG7jvQ9vTSr5VpC",
        "300491": "uFSsN75pxt8mdQMz",
        "300493": "dTCaBSbkl2mtXHSw",
        "300494": "5rjlhAXnAVw3Dt51",
        "300495": "JxfTRIRd1SM8PINp",
        "300496": "A9A7caU9RyBsQkXR",
        "300497": "IPBQ8OyyRRJQ5kWf",
        "300498": "CPhXd7i6t1UTfoxa",
        "300499": "rZIlBBIDNwQNndCr",
        "300501": "osS963vWLssNpNws",
        "300502": "L2XQdRcarJ8JnPME",
        "300504": "IDoZWXMOvwu6TzGs",
        "300506": "4Rx5qYzzIbNwibEV",
        "300508": "c1BpJfNRnlCYfkPg",
        "300510": "R5koyp41aIvYS9AI",
        "300511": "Lo5joLHByf6S4jS1",
        "300512": "4sGrhA3lJQQwfDBu",
        "300514": "frwmNVUVVDb2yeRz",
        "300516": "Fegxv7YcuBFVRc4V",
        "300518": "fYHDyMOgxHDXj6Ul",
        "300520": "6ysMlHgThDE49wF3",
        "300522": "S3szXa2Zi2QAtk9T",
        "300523": "RPq3KM4Tputu6Jmd",
        "300524": "xGsOLRfkd7YM8TNR",
        "300526": "czsQqvh7Qec1tweb",
        "300527": "qdduMcr9uzCaNgrC",
        "300528": "SvVNHGFbIdZ8EadO",
        "300530": "ORuqsJ6TxQMplnwH",
        "300531": "COty1HpXD9fd5eIB",
        "300532": "R9cSaKPI7VQTWVEE",
        "300533": "a5Bec1FwEECf8WqG",
        "300535": "y39Vfhczfpl0xqKf",
        "300536": "j8TXCXvURQCnwq2E",
        "300537": "JezJ3MOYEUpuukv0",
        "300538": "LqgWs6rcu24xSajF",
        "300540": "hSfSil54HbmZQphL",
        "300542": "RgJt5kIX8C4C2TYu",
        "300543": "7LJYZ9osj83ixFOs",
        "300545": "dKEi7f4ndl0xiCdo",
        "300547": "oqlkNROt1268Tobk",
        "300549": "mCnilIqqsmVhOfCP",
        "300551": "yZ0ANEtcdS95y8D0",
        "300552": "oqRVa6wAS71cOvGQ",
        "300554": "p3qF7YUGd0KNWGnH",
        "300555": "AqncKTJx9bKJgo7G",
        "300556": "P9Q9FXSkaRK1hOKY",
        "300558": "d9hylTJPg57o3EIO",
        "300559": "hwLAhgxTJFxZgRfF",
        "300561": "Jlv0oBetxMsHH21Y",
        "300562": "2Wbfgl8xvcDzgIok",
        "300564": "10Qvwlx1x3BTCipW",
        "300566": "chS7tSE0JVB1bOtn",
        "300568": "q95VgRcugr6518xt",
        "300569": "YNwaWpK84SLJXHlo",
        "300571": "eJ8464rKRYdJi4y0",
        "300572": "dEUXYMMmUjwxpLHT",
        "300574": "eVZdG1cAb89uJhVd",
        "300576": "V9HZBD11TZHGsibY",
        "300577": "bCc66uRPkQYI2U07",
        "300579": "UjPLhekBjxnYHoaR",
        "300581": "iaKwtWDYOROA7h06",
        "300583": "Qnym2qS63nIIr6MO",
        "300584": "6Wy08MyCwK4cacPT",
        "300585": "P9JWNO9alOjxF12S",
        "300586": "2kRnlcgUSHhfOI3h",
        "300588": "Ruv30XgurswmElNo",
        "300590": "jk1C0auQt33rhwbl",
        "300592": "FuwZdTIe7mCltjWG",
        "300593": "MmvIA6Jr481afxEE",
        "300594": "u9eaKn9sIaw0IaTa",
        "300595": "mg6TnSAXudBvCJPX",
        "300596": "gk3nWln1T0U8y5ZY",
        "300597": "tUdRI5fBCyNuw3Ir",
        "300599": "2oQP06HkAfFiRwA3",
        "300600": "YlRJOcLhZftETsZ5",
        "300601": "ozSE6Ne7dCj3ivaL",
        "300603": "nEiRE9Q0CEI77W2v",
        "300604": "ur6nERX3v075ttDz",
        "300605": "hPeoIEpoHySH4qjF",
        "300607": "t11J6CIRxsDO6xJP",
        "300609": "RdNmObWkViKausX1",
        "300610": "iDWqgFha6Ap1JNyM",
        "300612": "MNgy7zEIDIRYVJ2k",
        "300613": "KcPD1WVrpaFxWq4r",
        "300615": "u4Do6yGYTI4EJxkd",
        "300616": "Vmtlbu7FyKKhzIH8",
        "300618": "P0uZg3wQ6fb9Er7d",
        "300620": "H9XHY6Zl4laSKVVa",
        "300622": "q1FChXgHKQXWQYbp",
        "300624": "FV0EtTgkyDtRulTv",
        "300625": "eLAxW1e0si8cF7jj",
        "300627": "oO8E9elbOapCgB6t",
        "300629": "KyTOqbWe54vDV7jI",
        "300631": "Ig02q6KHYgzR2Pfd",
        "300632": "TibT82JLWlRPSuCc",
        "300634": "JQT1g01nfT3lHdhH",
        "300635": "vg2UrbMiMMPyZhds",
        "300637": "ehDcmSgLNMz6mYoe",
        "300638": "6lSojeHIZdLwjHVd",
        "300640": "Rn4UauoqK2HW1yjK",
        "300642": "KXhPo50ptOKVIZeH",
        "300643": "KZTC0WwWqyeStZD2",
        "300644": "PYG4vhVxksOYQJdt",
        "300646": "bbvV99IJzw2kQT6R",
        "300647": "uYkvYjZEDotAHE9O",
        "300648": "yb8nWd74n3u7Zm3P",
        "300650": "3TCayelJfuF0L0iy",
        "300652": "rcm52TR3QBCReTxe",
        "300653": "tA4uV90dZx3VxLa7",
        "300654": "YSwKGJImchI13Fxg",
        "300656": "jdrpp1KZIfGVkTkv",
        "300658": "08cwzAYpDHeUCHFm",
        "300660": "BwL4JzKHFJscYTlO",
        "300661": "pRvfSdZHoTs1ES6F",
        "300663": "CM7BYW3F44fvPHe2",
        "300664": "QwE7uPFSeHScMcz4",
        "300666": "BD3dB7fVD2dvlGwM",
        "300667": "v3q7X4XGkXspyHCB",
        "300668": "fo84TCZ3wyYL9zTa",
        "300670": "LtI5DJQaZlG0Q060",
        "300413": "aqwr0zZbJQNxnScL",
        "300414": "qfIT5ZYwrnkmNTXJ",
        "300416": "bQl0o8yOl0Z3ZwCQ",
        "300418": "yvJOej36kvtlzDAA",
        "300420": "dBLh3j7VAEM92uDl",
        "300421": "xB2XylkAEX52wMwc",
        "300422": "9cATZDKIdBc6K6qy",
        "300423": "r7uJPSTUuAGLVZRB",
        "300425": "tzxEzzczIimssQ6v",
        "301092": "VY9iB7Lsix6VYBVq",
        "301094": "ysv9nUHnKCeLGmuB",
        "301095": "XznZ8z47PpQ0yQzA",
        "301097": "QJRq9BmZ2WFpUkkM",
        "301098": "RPtdkjSCvt6PgUxv",
        "301100": "31RBKdpRsjjHsTV6",
        "301101": "57EuEU1pi8DnyulC",
        "301103": "Hfg5AvzqPpzZqApa",
        "301105": "PXoFduoxCQdlulSd",
        "301106": "oXnncWINzqDwybOX",
        "301107": "P7ozXkrTvwKdNcOY",
        "301108": "ry9P6pkEcL1lD4aw",
        "301110": "1HCxW0nOrV4sTlSk",
        "301111": "uTUKWarqMMwelAkS",
        "301112": "9AgoaqYPhMPQtiis",
        "301113": "VkDmiOtmimOWgzlR",
        "301115": "gOsYvgSa7sce2WiW",
        "301116": "Br4PLRz6uvNQuhLQ",
        "301118": "NdqhjV2BuCnYcsfx",
        "301119": "Inp6T1elcQV3ph1L",
        "301120": "PctWhME0kQb7ZBge",
        "301122": "9dYI1Q6eMxTGWmK8",
        "301123": "uMVf4A42balgVxBb",
        "301125": "NMzm2XtWZ6VbG3Es",
        "301127": "EkbxdZjZSXwhGnon",
        "301129": "7PXOAkqMBAP2aatK",
        "301130": "x1wIvaHppuNezCFY",
        "301132": "yjBfJcoxA70BTbtL",
        "301134": "Ha1sF40LlLqlttxl",
        "301135": "fejDqZJg2zyx6y08",
        "301137": "5husYBEFjd8qEV2h",
        "301139": "Wt1D1Xmvd6RGkSaO",
        "301140": "ll8JkzR6zw65LqV1",
        "301141": "DXwMauwGaVVIgkCG",
        "301143": "td0wPrJMwt0VO40X",
        "301145": "tmAH116dOGsOatcE",
        "301147": "QcLHWuN7WGzfHIZf",
        "301148": "DjMVf3F9s8hgtamV",
        "301149": "lRIrPIWWXVvwAdHp",
        "301151": "zaAZHZiCJvuZpQ0E",
        "301153": "yhcWD2kmRSc4v6Ay",
        "301155": "oYDtHzYGZuIHrojO",
        "301157": "1LCw0eugd5yg5Z8z",
        "301158": "IiDPlhtFynWUcRLZ",
        "301159": "4TaqfCA3Hd5MWh6y",
        "301160": "jYxXFTWAl2qdYHHn",
        "301162": "WMCfUXIcSxO8CTAp",
        "301163": "PgCoTMYkFY6Ab9Qw",
        "301164": "tY88DMvmnPkeoMai",
        "301166": "Tm0sF92nuE35beUx",
        "301168": "UR232GeLoTozOwSG",
        "301169": "rB1oM6Z823bTo4tJ",
        "301171": "JJwXFRU8lgMLASEd",
        "301173": "aI8Lzb2tcaYhJUj8",
        "301174": "wp16EyRhkYcqtrFo",
        "301175": "ML1geW0kBCUtVXld",
        "301176": "tiEC71thwa0WVQrU",
        "301178": "ZyYfQgmYEqsKH0IQ",
        "301180": "WVoIwZOT3RSG3n93",
        "301181": "jCTfPB4Lt44ygFQk",
        "301182": "hKZtqp9lZCwDuKoN",
        "301184": "L57NdcjnXfhYTxDT",
        "301186": "CmeOe5OEo9jl6fIy",
        "301187": "sZiyLhz2FsakS2M7",
        "301189": "CQWcmbLYYKzMh4ul",
        "301190": "sABIypkIRl2JPiAa",
        "301192": "0YKVFf0bIlZQM7YA",
        "301193": "pjobUJuuzwhmGQD3",
        "301195": "2cslxwGAjzKGNK5S",
        "301196": "FhL0c2rg9AUOtaf7",
        "301198": "LihCqT3hlippcYb6",
        "301200": "Vc1tjbgsyvHvC2lv",
        "301202": "hCuZjjxZ4yoUcfLK",
        "301204": "y4qpif6hZJwIssRy",
        "301206": "Qc3PWQ0vvAby55E7",
        "301207": "g2hij5R3M6uRAcDO",
        "301208": "9xFLWzkd0yNR2c7b",
        "301209": "rfpb9ZsMkjkLYA7T",
        "301210": "7AocP2TgemCNWzou",
        "301212": "aClWTUS2isExH1KT",
        "301213": "bMqRV4nkiiEqqLK7",
        "301214": "FYyK7HBkaLhcspog",
        "301215": "di1vL42H0nqbIBsL",
        "301217": "6poiqEx0OjNcCqNt",
        "301218": "c24FSWSCpiQXCy2N",
        "301220": "1XVIrCtO5Szo9aZC",
        "301221": "WMDvgfiga5qKEUGx",
        "301223": "sesu48Z5vqcQjz2G",
        "301224": "Eqsn6SkYOjdJ4uCB",
        "301225": "MAvEmfrabjU6E9G6",
        "301227": "lspVwJkyy7tezhFx",
        "301229": "VNhz9TAfU6tMpKMc",
        "301230": "JVpLyrXmGaL6OR57",
        "301232": "ul1YLtMzRftm31Tn",
        "301233": "n2QHIn4FDiiuGble",
        "301235": "sZGttZeV3RbaNf6W",
        "301237": "C08Bm0vvRQ9mdO3m",
        "301238": "7L5dhs4JqBknD4wL",
        "301240": "ZyuiDiepVDUOsnRK",
        "301242": "9sBHp0aUiGWyymKQ",
        "301244": "dOUT3I4EkVO0ccFH",
        "301246": "HovBZ8qGj5MPSPru",
        "301248": "6FhO564dvr8Z0Ya1",
        "301250": "N9wVpTYWol5XcckL",
        "301252": "tMEuO9wvV6AoPfpt",
        "301253": "GvppZbTaihIzVROh",
        "301255": "13f3IomW8BKFpsc7",
        "301257": "0yuqwe49URZeNC7V",
        "301259": "Xdv5F3EYhKstcRFw",
        "301261": "6EDSTzk9wGt1lg0b",
        "301263": "R5nUikLFwuYMkl9R",
        "301265": "tfP4WugO8f7StOPW",
        "301267": "j4JOVyJM2uftpLor",
        "301269": "JfOutQHPGLrEDA05",
        "301270": "DmAFUN0bLMCBGTKC",
        "301013": "sz1YE7moEByEsyYu",
        "301015": "jYtL7Z7C0HKbQSzI",
        "301017": "FD9QLE4bzdMA3cGG",
        "301019": "PkYdswKQGRxLVG0b",
        "301020": "oS0w8GC7q0pEWpKU",
        "301022": "lYRcpE2G7vkxaCIb",
        "301023": "JSqWWbUhyf6Q9Rw6",
        "301024": "cKENG5uaG2EyyeoC",
        "301025": "DNShdQNlh996Gu32",
        "301026": "vmoX341szA2ZgIEz",
        "301028": "mvjUP8siF41K3SOF",
        "301029": "hfddtGLSGZjcQTGR",
        "301031": "gpIoztJQEwMRfEy4",
        "301032": "znkheykGjSHmMzfx",
        "301033": "KQM36xX8E52tb05I",
        "301035": "MMrKUYpElMWCgMEd",
        "301036": "lethzihZsE76etll",
        "301037": "r9riRtxsBNiaQOpp",
        "301039": "QaqyDd9JkG2Db46o",
        "301041": "oTsA3jNLl79kQm2t",
        "301043": "DGArk7jIqKVHNlqG",
        "301044": "LgutUca9Xcvsii80",
        "301046": "0FLcYeEF528vUtYv",
        "301048": "FIm3fHAxGsdIl8pE",
        "301050": "5xuW6ywJPnSOViYt",
        "301051": "3sA78EzT0dI46mbF",
        "301053": "zfkYPBz2TRQRqCmb",
        "301055": "bFN7jo2xvUnkQj5M",
        "301056": "rS2AONWahApjTbY7",
        "301058": "yP35NaW3Bp3oDeum",
        "301060": "2MOsf5GGGOT7rOIG",
        "301061": "TtTYzK7bkGynx4hQ",
        "301062": "utyiheZSj6nFvMSB",
        "301063": "Yj3Q2DgLcH7k3xgX",
        "301064": "VXImPy3UHN3hiyy8",
        "301066": "ITpLXn2YfUgSmaJG",
        "301067": "UC0uDFgqHkEOnKg9",
        "301068": "tpoWAXIZvHA7rnKf",
        "301069": "jvbfVQmUTDOOZ6ff",
        "301070": "ARZnQRV3q4S5LJhx",
        "301072": "lacUn4JUctRhBD9E",
        "301074": "8S3LObD87hUJ42G6",
        "301076": "Zs0MOEoWs758tLhu",
        "301077": "wqmDx9080YKwa7DY",
        "301079": "KUd5bdEqzzLrd47J",
        "301081": "FNl5Jd22lYNaqCi5",
        "301083": "NqWS0F5S8fCixPDO",
        "301084": "sqH6qp1erZkDh3VD",
        "301086": "57Vl4ZVd4Jo2f4m8",
        "301088": "Wk13YyT0kzeBw51j",
        "301089": "LG69HvkzMpP2s4nL",
        "301090": "wtYHSRkHAKChv9JQ",
        "301091": "WXgNRdADPc9hx06Z",
        "301271": "wfRRLigCuHZVKnuw",
        "301273": "Cm32S3GLBtfzL5q5",
        "301275": "ideewz04V1ESRfr8",
        "301276": "9F7oKXbYNkLPWjtq",
        "301278": "eO5ceGjsYrh0f3yJ",
        "301280": "wxC0GvN1vFnJ1kK3",
        "301281": "0kMv0OslTQ7apmjr",
        "301282": "mH9qS8lpUKnQy3tq",
        "301284": "0xHvzaY55byhbUTv",
        "301285": "ulIYHicIUmJuBccI",
        "301286": "YLGDguxqJovnXQgy",
        "301287": "hgT4dAJer1a64cV4",
        "301289": "at2i9N2Tm32dFm5W",
        "301290": "2KGaZKv1aDjjNHLP",
        "301291": "SAoM7flxDDCMYhCL",
        "301292": "khKEkQfs1POovGvL",
        "301293": "AvGXfoznfRoo3C0Y",
        "301294": "mdoDaJ30dXcofgCc",
        "301295": "DXpQAKpXUaTphvOz",
        "301297": "adb7IgOikWLaQq1r",
        "301298": "5mIrrZCyk5CN0Fh1",
        "301300": "99p7GqHhvdYoFzny",
        "301301": "5U72BMCuE9htRpFt",
        "301303": "aSFkeP0MW2EzBkLk",
        "301305": "LQSTThA7a35kYgQ1",
        "301306": "6dMpO9kai0VM7htd",
        "301308": "CwEw7ogWGNpe33O6",
        "301310": "kHYPKuLvSTULGn0T",
        "301311": "H9MN9Lw8tXjTz92i",
        "301312": "HuSIHlPQofNyRq7F",
        "301314": "QTDRuf86sCnSQkfi",
        "301316": "1SjlpTpHzyDEBxKC",
        "301318": "YcPYvP7C7bdGKop9",
        "301319": "fNOPCx5iz1gaNQ0o",
        "301320": "ZyHsFIsjFb8bUOyv",
        "301321": "Y6vqIEpW6vzsw44c",
        "301323": "JIrs4iJEY1f2QZYV",
        "301325": "VE8YKMXQFB7OLEhO",
        "301327": "r6BDi7UNuMfPRIhi",
        "301328": "p7npEiAs3SofeUA2",
        "301330": "hjzsXdMTs4sRhW2F",
        "301332": "aMHyz4rUzuS7oE6J",
        "301333": "8IBF3pD0M0VMc4PQ",
        "301334": "1u4JjO9R5bWILU53",
        "301336": "mb81HIz0v43cZEAk",
        "301338": "0G2sdGowjTF7HANG",
        "301339": "4hvnxg5aHrjalpus",
        "301340": "2l7aW8WATIziFh5f",
        "301342": "HMtGRTF62ENMYN18",
        "301343": "YgFhSO8zNHrkkGXJ",
        "301345": "ct6JYjOl2Jpnmt9M",
        "301347": "RFFHmGt5ABP3cH5i",
        "301349": "OEniRjhlDYJkgPKd",
        "301350": "eF2AG8jMy6lIoxaF",
        "301352": "2aW3MQsm983fvOWC",
        "301353": "ukg9utcO3o2REfDw",
        "301355": "Co0Av5l98cc2dhFB",
        "301357": "TiLd7Y3SzwO9fuF3",
        "301359": "DmqQ9mrrB5orH9H6",
        "301361": "ITKziVwPDOEwWExs",
        "301363": "GufP17wJWNXROfnc",
        "300672": "SUe1tHRIGZ3eGgFP",
        "300673": "EYkVZQRGDiAOHIXX",
        "300674": "UkMJ2R6IzS6UJe8b",
        "300675": "OU3V8vdYTC0hJG0R",
        "300676": "Y7FP9kzTmvgdwbRp",
        "300678": "Jwyhh4UqLDxefhcT",
        "300679": "vuJjTvER8J7TzRz9",
        "300681": "zD0VAcarbPWWKnWa",
        "300683": "eiAdWvHXti4fjM5R",
        "300685": "axPoBSoxerca0IRN",
        "300687": "33ENz4N0FD7bNzwt",
        "300688": "jqwpNl87ApWZg2mq",
        "300689": "LkaYzJ2se2IDQLNE",
        "300691": "C10fvKJ2CnDZklSq",
        "300692": "hx4Htu5eN8H4XyMb",
        "300693": "P1VFd7CeNEuUXpwx",
        "300694": "EXbtA1ToTvnCVAQw",
        "300695": "sNiP6qJ89SDCjYep",
        "300697": "W8X9Oo4ESPDZWxge",
        "300698": "x225oMNAyEQdQuoa",
        "300699": "sSvu9b1R2By2OtN8",
        "300701": "TgRLSVqx5JIjQPB3",
        "300703": "jfAnxxDEVJMsZtWi",
        "300705": "7n6QYxbgc2jbPbgy",
        "300707": "7TKnZzrHQF5MigQT",
        "300708": "TgMO1eontpeUJKB4",
        "300710": "R2bCnwdSc2nu1O8n",
        "300712": "MfL2OSzTxQ6F6aYK",
        "300714": "ESnW6fIzypDGAH5b",
        "300716": "fdZmhNwuqqxg3F3e",
        "300718": "a3ow5EE8O3B7Lvx4",
        "300720": "Wjf7ZLF1E93b7OHt",
        "300722": "6fVsBVHuNbcbURCT",
        "300724": "T8cnXenWfsNydKqS",
        "300726": "88FnprhuZz3NCD1q",
        "300728": "VeFzsAm1nE4KG6EI",
        "300729": "q1oLuLVN3qIlSPSF",
        "300731": "Kf2zkFlfrsUMLhjW",
        "300732": "ADw4wJev0Mqdc3DG",
        "300733": "v9UnitYhQ0OxQ0kA",
        "300734": "41EuFRn1RqO0NdG3",
        "300736": "wOzCua8hLfLaPUFq",
        "300738": "8IsPG8bygFiQThZO",
        "300740": "nIBfgaQYGzduZyWH",
        "300741": "vlv3eqWNAOO81GCw",
        "300742": "8PG3e4ZPtHm83qZ1",
        "300744": "Pb43lYcwND8ALiX8",
        "300745": "QUZRP2X08GYUQmVH",
        "300746": "FszJp9LqbwG2C2qX",
        "300748": "zAWEjOep8YPVThBc",
        "300749": "MGnMkop427OjdB7a",
        "300750": "DHAXpdbSDO2LojTJ",
        "300752": "me3WdlaQ4tpAjnLc",
        "300767": "vtNvl44kAAbhfSm4",
        "300769": "dJ0W34hCmXhVj31X",
        "300771": "NvTVI0gRUBsdFmPs",
        "300773": "9VGT0riTxKKfqvVh",
        "300775": "LuHU8BVZgKxnF1JZ",
        "300776": "5uhOCvSSGi7XkYB8",
        "300777": "v7QXjlDHorm2O0Hb",
        "300779": "wsKqtRmlB8qxBChB",
        "300780": "gYF6Ilxyx2oxCThK",
        "300782": "e6P2YFclioBqC5dK",
        "300784": "OAntOkPx802P7M12",
        "300786": "xHbaaPsu0Ac83mM2",
        "300788": "hvdvJ1zh8VbiSKEk",
        "300790": "35JiqPEVR3E6gYDQ",
        "300791": "sneGA2rp3M1BN773",
        "300792": "5rKUKu5JpcX18f4q",
        "300793": "uW9TVWOIs7DBKnhB",
        "300794": "XfSHve9n8M37xhYd",
        "300795": "CI937Qw95h3P4Eox",
        "300796": "LLFHRxXqmPMdDP6d",
        "300797": "flOjAovmKffy2p53",
        "300799": "T0ihACruHGtwpG43",
        "300800": "lPSDoSXYFQBrBNbw",
        "300802": "mDFzoAIfrHfuSOvs",
        "300803": "rUM3edVnEdXdRzas",
        "300804": "y2bwSL5SUx5mJorA",
        "300806": "J8SSeOntSQr6nWTH",
        "300808": "JVuGBem9tkVKy1Uh",
        "300810": "RRDcOylGpEZKxU4G",
        "300812": "Yy0b857IqCSri0WF",
        "300813": "ScmtSxXycUeCDTs6",
        "300815": "SQZ6Go9wKnOb3DNt",
        "300817": "jtQzXvrbWcOyAFqR",
        "300819": "Xys0qA4PyTTP2xsX",
        "300820": "nGyjOeHggeIgkSSs",
        "300822": "wpFjRs9tDs4KuFBD",
        "300823": "7jsUxjkupaNtPCqz",
        "300824": "CkARpbEwPj9bIzBP",
        "300825": "Qzl9tjVRtaDryqYX",
        "300827": "O7wUqwnU72VDd27X",
        "300828": "gqLLzqUyFBEyc4kr",
        "300829": "GzX9TzzgB5EJl0kv",
        "300830": "KAJtVusKSmQJnBWE",
        "300831": "IUSxKjxrNQ2OHGuf",
        "300833": "Xt3GDyQJ9dSk02zh",
        "300834": "tcCpycv5DsMdQrqA",
        "300836": "duO4pfwHuIrg45HE",
        "300838": "S1Y4aFILwaubCS2x",
        "300840": "jAC32g1GwHazzg9L",
        "300842": "zXYMEerUPv3ZZQZk",
        "300843": "Cxdi6CQ8JhbpkXJV",
        "300844": "EBDXSGR7nBkO7gIU",
        "300846": "i87M1Da7jN3WjVq3",
        "300848": "UTQZS0QwBRrrLxUj",
        "300850": "aoMYfdtbNryiH7qv",
        "300851": "PwbvR8bH2IFLAVY2",
        "300852": "fEN9gK2eFZnceQBq",
        "300854": "7XQGCyxgULvnJLF7",
        "300856": "j8g7dj5SNP63HPBq",
        "300857": "GWNAfOIBTegrHYNM",
        "300858": "tBfDQvysB0IAYrKq",
        "300860": "dafhyzV1ZR1oS4kq",
        "300862": "aLYJ9dTjsu0TS3Tf",
        "300863": "xC02He2is1lZPxAz",
        "300865": "ZYZ7XcNyM3nIWjD9",
        "300866": "zvSTvQVRpKMoAHn6",
        "300867": "Jxd6oZgz1ryTlRab",
        "300868": "TGYCHa24AJ3NG6Mf",
        "300869": "XRuDtmqwCxaIz0Tj",
        "300870": "Y1OJZ4uhP0nRGaW6",
        "300871": "p9rqW9AZSiRR6yPN",
        "300872": "LEJhtBQA3vksnqQh",
        "300874": "Df0WBjZMWblyI7eH",
        "300875": "cnFJZVE1HA9zYB9z",
        "300876": "M35gAB2nFpOUvE9b",
        "300877": "iW982ZUd4T5mY9VY",
        "300879": "cOkp08LreOBnN5Nt",
        "300881": "eoE3yfqsqBfCOF3T",
        "300882": "bZif7z2gH1hjg4x5",
        "300883": "PiHc2uITovlIouDo",
        "300884": "jlagOAiYTy7hrYIU",
        "300885": "1Q2zuBru3B0xtzZL",
        "300886": "5x9pboO3NN44skkX",
        "300887": "i8QqORuQsOCPsaaP",
        "300888": "DGA0J0JN5YOsHn71",
        "300890": "4mL4l8vEiziedl1v",
        "300892": "C9J57qJn05CPPBrx",
        "300893": "85ZqxzkIABIRrwH2",
        "300894": "5ZBjfHBmw36rrFD1",
        "300896": "yXP8AbEQAQqPgpVB",
        "300897": "z2HybH0w1ejxZSyx",
        "300898": "FfELFObgNBqCXOXH",
        "300899": "kvso2Fmrni5biQOI",
        "300900": "FwXsx5qCP2ItIAL4",
        "300901": "5kKqrG5kVU7tyjUh",
        "300903": "scpBsdf1g3HNciSq",
        "300904": "HjVCFmB43IPttda4",
        "300906": "HuCFGRTD63muTthp",
        "300907": "i0cqI7AQ8OeRbEpz",
        "300909": "8A9qSKSHrgUhZphU",
        "300911": "8RYBXtRDmyR5wO5T",
        "300913": "irf6PB4Gl4zpmm0S",
        "300914": "3kJQJHffDD9pRnBQ",
        "300915": "bmtffdo09e6lw10y",
        "300917": "F1XK6jlL3vTQjOiP",
        "300918": "nqHWVtH3hO0ZVm12",
        "300919": "lEMABEV7JDIAyWHv",
        "300921": "31wKDVGyxZNMEP5H",
        "300922": "3iHRJ1a53Ame69vR",
        "300923": "WrZsB5bL1bGa3DVZ",
        "300924": "jTBQBr8Ra1MApPxc",
        "300925": "QU4dxXsY7fFecOkW",
        "300927": "c47czgCiAdiNLePd",
        "300929": "o3bVIfK8qgIlQKp9",
        "300931": "WQkscSgSsFNDpPyx",
        "300932": "e2mbmKrZpGvZb0v0",
        "300934": "XVN3MUBjvKO6BVm6",
        "300936": "214ZvA66E6HqI26o",
        "300937": "LhYiLsYh9qqGp6ET",
        "300938": "TXk3e4BTj2yosTBG",
        "300940": "3aIrVBmOa1mMj5TI",
        "300941": "V5zZsTHd0yqyCN0u",
        "300942": "Kccc0y7QALRIHU98",
        "300943": "eYF7PIwsS6PsKRPN",
        "300945": "TxrUMTYDsdPI0nQ4",
        "300946": "JgFcUIRaXeKiXiVi",
        "300947": "HNUFMwBJrlwzRGoX",
        "300948": "wp1cGLxdBzCrg7V1",
        "300950": "THh6DRVWuqMUkn43",
        "300951": "5rSXkR7bCCVYeMRv",
        "300953": "AfunqnSLVVtu47wV",
        "300955": "cW4NUWdUCWe8lirD",
        "300956": "P2tFR6yJHVFszXe8",
        "300958": "7F9qGrc9Qm1j7dEt",
        "300960": "15i7WCkfYqx9T1M5",
        "300962": "EVd8foGnSfeeH3v5",
        "300964": "bmGrNe2Nces5jwxy",
        "300966": "CYrODTV3YGVwnFdg",
        "300968": "BjhVzgTcW7OL7CFL",
        "300969": "IxOKOPAxOdQzx17x",
        "300971": "vPimQPFG4xgl1p9N",
        "300972": "52ua8y32xmzEPQP1",
        "300973": "tbwtgF2sERpiBIQn",
        "300974": "jPAQzmJleO2BzpKU",
        "300976": "IJrIW0K1ZB0qDcjk",
        "300978": "CbR0ilsI7lKKnEk7",
        "300980": "f0RyOEgYUTcL1qcF",
        "300981": "6cyewkVndJbWx3vM",
        "300983": "pXP0bf5h0uvEauca",
        "300985": "fvGJRFRXFWhL1wed",
        "300987": "gagnC8YET4I7te73",
        "300988": "6mNagliKRtj8CioC",
        "300990": "L07rqXH6yt3gmiUt",
        "300992": "kawyHFy7cGql4o7G",
        "300993": "x9jqX5rCXR2Qk9Ej",
        "300994": "PWs4YRUCffmAN1sy",
        "300995": "Y2FBuSfZ8lsUb48d",
        "300997": "K7ImhqkfyPAUbfc8",
        "300999": "zanZsmMbBdEBsKWb",
        "301001": "4jA9CqdHnuKnFNMq",
        "301003": "yCNnhEl2moNe9VrK",
        "301004": "6OYdhJAG9Pd3exXG",
        "301005": "Dh2W0RJ5y1EnfR30",
        "301007": "nu0KNXZnovgqqxLW",
        "301009": "oc5TnuznJ8jzmpcC",
        "301010": "8Q5yzFIftSBcxwXb",
        "301011": "j83ptuoDfEusX0x0",
        "301012": "Z2nA34k4vZUs9YHo",
        "300753": "feV5ufsWy4FtfODt",
        "300755": "7dnHl7glrU8EKIcS",
        "300756": "GMETb1dy2EjMUVYZ",
        "300757": "kEJ4XPSfGmq3t1x7",
        "300758": "ZR8Jho2KNaYwCIGb",
        "300759": "mUTuLI5eZHK8k8XE",
        "300761": "nZHRmVirYlUvTsD6",
        "300763": "ZQ3nEYBXEUnMFBFQ",
        "300765": "eMZwgpw0WO4Qv6dV"
    }
}