{"C_DATA": ["EnLO0M6wsLuAgah4", "VCwK8QlId6Qa0HG2"], "enc_code2": ["QFlnmAIO0mlE9gXk", "wZFHCdFZIdtVwCmR"], "enc_code1": ["1irni0v7E42VwJuB", "DigH2brqNQIvlrFP"], "IG_dict": {"30719": "g80dXwL7joogBOvF", "30721": "SiBoHudZEbcANSVJ", "30722": "h18tkGyDs6sLCS6A", "30724": "lfu9ZOnGYIkIX8oE", "30726": "l9Xps9SV7yxlA3QM", "30728": "K1nsWUkdzeACjgcA", "30729": "UZ2HVHGI597PAp07", "30730": "OkWZxyzhGhIxK47Y", "30732": "Ypcyp5dyMIJd9bHZ", "30734": "xuRCuCdINKmFDVVv", "30735": "bjh9UASMYsM1wIED", "30736": "C8Ei186F7D2kWWd5", "30738": "P7U30bqH1WKmaIcQ", "30739": "DfM8yrhJkevzkN9G", "30740": "v2QcGBxqgzDLJ0mI", "30741": "OomeumstrctEHCUe", "30742": "CzBR8I5rSI28NKJg", "30745": "kBKcseEPT2m9GkFA", "30746": "MnKwY6WYVyuTRiBm", "30748": "bSkZY9JtLtfj985g", "30750": "T4H9fKjud0XRnBjO", "30751": "2Gx3eCbSef0daMQG", "30752": "hi4j7uBis9U2B3kX", "30754": "49gmWBTm2tKTeX0a", "30756": "iHNj56WgckePXerJ", "30757": "NdwrFKgPnBfQmzVV", "30758": "dC3eoRacXgylTuB3", "30759": "unAMUl00qxJCBpaC", "30761": "1DUGhYdC6aeE5uKR", "30762": "1kMceMyYZ1lx9CQz", "30763": "SR57POjpKNIQToyW", "30765": "mYzFuAVpcCC7kiQc", "30767": "8usYDzo4orNgk9zB", "30769": "qPPwOL8TunheCIUl", "30770": "476QrgdtX8CVvmsG", "30772": "FWC3Ktbu7lvk0rtH", "30773": "r27JbsuIc0K0m8s0", "30774": "XRzQvqenrj3OlkQe", "30775": "0p5eTESDYNJjZcX4", "30777": "9xJ6aBbMYI51AXZl", "30778": "npnbP3lkNWxnbsNR", "30779": "BWLoOJ2PNne7r5aX", "30780": "gIoHb9GvvOpG7DAz", "30781": "Htf9k60mlW2qrOpP", "30782": "mbN06iV5qa9RAnYd", "30783": "4B4aeYcTjaaoSmrX", "30784": "SfYOtDoXrNOxVf7F", "30785": "Gpy1pi2DNixfvljB", "30787": "WcrBCVNheEMydkY5", "30788": "icY6WZNL0N62zVin", "30789": "hNEBkacbQotMveCz", "30791": "kytzLT5CBkwxLc96", "30792": "d1vjjMRs0EwNzP8q", "30794": "SRFey7GaiTW4c21p", "30795": "z1aKFd2RotweJZjZ", "30796": "7CIpDIlTYuvHMEKU", "30798": "G4EHXMALUVTuAfQu", "30799": "4zw3b1GqvA06l3JP", "30800": "kIq7QbFkMyOFcdVJ", "30802": "YqxYTYUJsps6TILf", "30803": "CW6rymI3Q20u5K0m", "30804": "Nw3KLhdIiNedQR9L", "30806": "SzaZuOdKXmpVhe3s", "30807": "MQ0YVAt8qFiOh0yZ", "30809": "dJE4DCqAUFVX6gZR", "30811": "UrVGROAv8GZ7sjpW", "30813": "ec4G8cdndttKXLzQ", "30814": "00ZLq1KDLX8Pydd6", "30815": "9xiJPHCn0MdH7rAc", "30816": "YQEpfqeIk9Y5R5rm", "30818": "dPgKxGF9UJI7ASh2", "30819": "e0naJG4XrvhAuTiu", "30821": "dp0HjiZGaGhwTqGE", "30822": "Q3X65vo0EN91hSAO", "30824": "aqwr0zZbJQNxnScL", "30825": "qfIT5ZYwrnkmNTXJ", "30826": "bQl0o8yOl0Z3ZwCQ", "30827": "yvJOej36kvtlzDAA", "30828": "xB2XylkAEX52wMwc", "30829": "9cATZDKIdBc6K6qy", "30831": "r7uJPSTUuAGLVZRB", "30832": "tzxEzzczIimssQ6v", "30833": "ddsuHlyEUgp3jJVY", "30835": "ANwNHHgHOt9cy4sF", "30837": "p2HsnpAL2YsPqbVd", "30838": "jhT487wMpvhJoKr3", "30839": "5Jb4qOlflyrndU60", "30840": "Qkw0fXrU62Nf41E4", "30842": "EWy6zaQ0U7oacvn6", "30844": "ERfOv3fM8flOVvJR", "30846": "zQnUGH2ygnkIxGVv", "30848": "1hJVIXNnLu0lUDIi", "30849": "MDe1KbsSNtgJhlTC", "30851": "ryL1fn18hCb4KMvk", "30853": "O6a3DYdcqqL8LrJL", "30854": "ZAI3AIMBviCLr75I", "30856": "0OdPOXHTZx5oYvkO", "30857": "VOR1yf7q8r5kw1d1", "30858": "YC8OOvChjFJaHuOg", "30860": "r42tI9aDNIxtSkXB", "30861": "QlAHv7mnI4IgjtaD", "30863": "Ol6gLpcIBTIyiCty", "30865": "txmDHaYDv6nU3b3n", "30866": "UVfcSCa6hwPMBLAR", "30868": "JMSA7NHoyY7I6spd", "30870": "mKVgstDMIgoGDmgp", "30872": "RffaN9f318Gcfh5o", "30873": "kZjYbQHy0WvJkcC2", "30874": "QsCfYQ5JaxrGkiLl", "30875": "ZCWg7fE5OakmXdHt", "30877": "DXv6FewRYYuKDPQb", "30878": "jnpR1KPG7H6edLxw", "30880": "B14pEq01bYrZXImz", "30881": "IWrmyTekc7YO23M9", "30882": "LvBKSAkc7WBoi437", "30883": "wKcAC4Rs70OFYSOo", "30884": "ZWqdpZNH61a9LMZt", "30886": "ayUcDlIPgCpGHZaY", "30888": "2843G7neWmiDntHc", "30890": "47dF17GxVZMqycaq", "30891": "ECsk1xXz8QLwCyQh", "30892": "eDXWyeotmO0kSrs9", "30893": "ONn0lPswKO9Os7HS", "30895": "dCvWLaelO15ighoZ", "30896": "56DOGL5fwmz4OtvO", "30898": "bhG4QSfVaaqjtlKe", "30899": "DdG7jvQ9vTSr5VpC", "30900": "uFSsN75pxt8mdQMz", "30902": "5rjlhAXnAVw3Dt51", "30903": "JxfTRIRd1SM8PINp", "30905": "A9A7caU9RyBsQkXR", "30907": "IPBQ8OyyRRJQ5kWf", "30908": "CPhXd7i6t1UTfoxa", "30910": "rZIlBBIDNwQNndCr", "30912": "osS963vWLssNpNws", "30914": "L2XQdRcarJ8JnPME", "30915": "IDoZWXMOvwu6TzGs", "30917": "4Rx5qYzzIbNwibEV", "30918": "R5koyp41aIvYS9AI", "30920": "Lo5joLHByf6S4jS1", "30922": "4sGrhA3lJQQwfDBu", "30923": "frwmNVUVVDb2yeRz", "30925": "Fegxv7YcuBFVRc4V", "30926": "fYHDyMOgxHDXj6Ul", "30927": "6ysMlHgThDE49wF3", "30929": "S3szXa2Zi2QAtk9T", "30931": "RPq3KM4Tputu6Jmd", "30933": "xGsOLRfkd7YM8TNR", "30935": "SvVNHGFbIdZ8EadO", "30936": "ORuqsJ6TxQMplnwH", "30938": "COty1HpXD9fd5eIB", "30940": "R9cSaKPI7VQTWVEE", "30942": "a5Bec1FwEECf8WqG", "30944": "y39Vfhczfpl0xqKf", "30946": "j8TXCXvURQCnwq2E", "30948": "JezJ3MOYEUpuukv0", "30950": "LqgWs6rcu24xSajF", "30952": "hSfSil54HbmZQphL", "30954": "7LJYZ9osj83ixFOs", "30956": "dKEi7f4ndl0xiCdo", "30957": "oqlkNROt1268Tobk", "30959": "mCnilIqqsmVhOfCP", "30960": "yZ0ANEtcdS95y8D0", "30961": "oqRVa6wAS71cOvGQ", "30962": "p3qF7YUGd0KNWGnH", "30964": "AqncKTJx9bKJgo7G", "30966": "P9Q9FXSkaRK1hOKY", "30968": "d9hylTJPg57o3EIO", "30969": "Jlv0oBetxMsHH21Y", "30971": "2Wbfgl8xvcDzgIok", "30973": "10Qvwlx1x3BTCipW", "30974": "chS7tSE0JVB1bOtn", "30976": "q95VgRcugr6518xt", "30977": "YNwaWpK84SLJXHlo", "30978": "eJ8464rKRYdJi4y0", "30979": "dEUXYMMmUjwxpLHT", "30980": "eVZdG1cAb89uJhVd", "30982": "V9HZBD11TZHGsibY", "30984": "UjPLhekBjxnYHoaR", "30986": "iaKwtWDYOROA7h06", "30988": "Qnym2qS63nIIr6MO", "30990": "6Wy08MyCwK4cacPT", "30991": "P9JWNO9alOjxF12S", "30993": "2kRnlcgUSHhfOI3h", "30995": "Ruv30XgurswmElNo", "30996": "jk1C0auQt33rhwbl", "30997": "FuwZdTIe7mCltjWG", "30743": "9J7Xd8sy1nBpWHU0", "30999": "MmvIA6Jr481afxEE", "31000": "mg6TnSAXudBvCJPX", "31002": "gk3nWln1T0U8y5ZY", "31003": "tUdRI5fBCyNuw3Ir", "31004": "2oQP06HkAfFiRwA3", "31006": "YlRJOcLhZftETsZ5", "31007": "ozSE6Ne7dCj3ivaL", "31008": "nEiRE9Q0CEI77W2v", "31010": "ur6nERX3v075ttDz", "31012": "hPeoIEpoHySH4qjF", "31013": "t11J6CIRxsDO6xJP", "31014": "iDWqgFha6Ap1JNyM", "31016": "MNgy7zEIDIRYVJ2k", "31017": "KcPD1WVrpaFxWq4r", "31019": "u4Do6yGYTI4EJxkd", "31020": "Vmtlbu7FyKKhzIH8", "31022": "P0uZg3wQ6fb9Er7d", "31024": "H9XHY6Zl4laSKVVa", "31026": "q1FChXgHKQXWQYbp", "31027": "FV0EtTgkyDtRulTv", "31028": "eLAxW1e0si8cF7jj", "31029": "KyTOqbWe54vDV7jI", "31030": "Ig02q6KHYgzR2Pfd", "31031": "TibT82JLWlRPSuCc", "31032": "JQT1g01nfT3lHdhH", "31034": "vg2UrbMiMMPyZhds", "31035": "ehDcmSgLNMz6mYoe", "31036": "6lSojeHIZdLwjHVd", "31038": "Rn4UauoqK2HW1yjK", "31039": "KXhPo50ptOKVIZeH", "31040": "KZTC0WwWqyeStZD2", "31041": "bbvV99IJzw2kQT6R", "31042": "uYkvYjZEDotAHE9O", "31044": "yb8nWd74n3u7Zm3P", "31045": "3TCayelJfuF0L0iy", "31046": "rcm52TR3QBCReTxe", "31047": "tA4uV90dZx3VxLa7", "31049": "YSwKGJImchI13Fxg", "31050": "jdrpp1KZIfGVkTkv", "31051": "08cwzAYpDHeUCHFm", "31053": "BwL4JzKHFJscYTlO", "31055": "CM7BYW3F44fvPHe2", "31056": "QwE7uPFSeHScMcz4", "31058": "BD3dB7fVD2dvlGwM", "31060": "v3q7X4XGkXspyHCB", "31062": "fo84TCZ3wyYL9zTa", "31064": "LtI5DJQaZlG0Q060", "31066": "SUe1tHRIGZ3eGgFP", "31067": "EYkVZQRGDiAOHIXX", "31069": "UkMJ2R6IzS6UJe8b", "31071": "OU3V8vdYTC0hJG0R", "31073": "Jwyhh4UqLDxefhcT", "31074": "vuJjTvER8J7TzRz9", "31075": "zD0VAcarbPWWKnWa", "31077": "eiAdWvHXti4fjM5R", "31078": "axPoBSoxerca0IRN", "31080": "33ENz4N0FD7bNzwt", "31082": "jqwpNl87ApWZg2mq", "31083": "LkaYzJ2se2IDQLNE", "31084": "C10fvKJ2CnDZklSq", "31086": "hx4Htu5eN8H4XyMb", "31087": "sNiP6qJ89SDCjYep", "31089": "W8X9Oo4ESPDZWxge", "31090": "x225oMNAyEQdQuoa", "31091": "sSvu9b1R2By2OtN8", "31093": "TgRLSVqx5JIjQPB3", "31095": "jfAnxxDEVJMsZtWi", "31097": "7n6QYxbgc2jbPbgy", "31098": "7TKnZzrHQF5MigQT", "31100": "TgMO1eontpeUJKB4", "31101": "R2bCnwdSc2nu1O8n", "31103": "ESnW6fIzypDGAH5b", "31104": "fdZmhNwuqqxg3F3e", "31105": "a3ow5EE8O3B7Lvx4", "31106": "Wjf7ZLF1E93b7OHt", "31108": "6fVsBVHuNbcbURCT", "31109": "T8cnXenWfsNydKqS", "31111": "88FnprhuZz3NCD1q", "31113": "VeFzsAm1nE4KG6EI", "31115": "q1oLuLVN3qIlSPSF", "31116": "Kf2zkFlfrsUMLhjW", "31118": "v9UnitYhQ0OxQ0kA", "31120": "41EuFRn1RqO0NdG3", "31121": "wOzCua8hLfLaPUFq", "31123": "8IsPG8bygFiQThZO", "31125": "nIBfgaQYGzduZyWH", "31127": "vlv3eqWNAOO81GCw", "31128": "8PG3e4ZPtHm83qZ1", "31129": "Pb43lYcwND8ALiX8", "31130": "QUZRP2X08GYUQmVH", "31132": "FszJp9LqbwG2C2qX", "31134": "MGnMkop427OjdB7a", "31135": "DHAXpdbSDO2LojTJ", "31137": "me3WdlaQ4tpAjnLc", "31138": "feV5ufsWy4FtfODt", "31139": "7dnHl7glrU8EKIcS", "31140": "GMETb1dy2EjMUVYZ", "31142": "kEJ4XPSfGmq3t1x7", "31144": "ZR8Jho2KNaYwCIGb", "31146": "mUTuLI5eZHK8k8XE", "31147": "nZHRmVirYlUvTsD6", "31149": "M3v3TWxbOSA4dnXj", "31150": "vtNvl44kAAbhfSm4", "29676": "xHbaaPsu0Ac83mM2", "29677": "hvdvJ1zh8VbiSKEk", "29679": "35JiqPEVR3E6gYDQ", "29680": "sneGA2rp3M1BN773", "29682": "5rKUKu5JpcX18f4q", "29684": "uW9TVWOIs7DBKnhB", "29686": "XfSHve9n8M37xhYd", "29687": "CI937Qw95h3P4Eox", "29688": "LLFHRxXqmPMdDP6d", "29689": "T0ihACruHGtwpG43", "29691": "lPSDoSXYFQBrBNbw", "29692": "mDFzoAIfrHfuSOvs", "29693": "rUM3edVnEdXdRzas", "29695": "y2bwSL5SUx5mJorA", "29696": "J8SSeOntSQr6nWTH", "29697": "JVuGBem9tkVKy1Uh", "29698": "RRDcOylGpEZKxU4G", "29699": "Yy0b857IqCSri0WF", "29700": "ScmtSxXycUeCDTs6", "29702": "jtQzXvrbWcOyAFqR", "29703": "Xys0qA4PyTTP2xsX", "29705": "nGyjOeHggeIgkSSs", "29706": "wpFjRs9tDs4KuFBD", "29708": "7jsUxjkupaNtPCqz", "29709": "CkARpbEwPj9bIzBP", "29710": "Qzl9tjVRtaDryqYX", "29712": "O7wUqwnU72VDd27X", "29714": "gqLLzqUyFBEyc4kr", "29716": "GzX9TzzgB5EJl0kv", "29717": "IUSxKjxrNQ2OHGuf", "29719": "Xt3GDyQJ9dSk02zh", "29721": "tcCpycv5DsMdQrqA", "29723": "duO4pfwHuIrg45HE", "29724": "S1Y4aFILwaubCS2x", "29726": "jAC32g1GwHazzg9L", "29728": "zXYMEerUPv3ZZQZk", "29730": "Cxdi6CQ8JhbpkXJV", "29731": "EBDXSGR7nBkO7gIU", "29733": "i87M1Da7jN3WjVq3", "29735": "aoMYfdtbNryiH7qv", "29736": "PwbvR8bH2IFLAVY2", "29737": "fEN9gK2eFZnceQBq", "29739": "7XQGCyxgULvnJLF7", "29740": "j8g7dj5SNP63HPBq", "29742": "GWNAfOIBTegrHYNM", "29744": "tBfDQvysB0IAYrKq", "29746": "dafhyzV1ZR1oS4kq", "29748": "aLYJ9dTjsu0TS3Tf", "29749": "xC02He2is1lZPxAz", "29750": "Jxd6oZgz1ryTlRab", "29751": "TGYCHa24AJ3NG6Mf", "29752": "XRuDtmqwCxaIz0Tj", "29754": "Y1OJZ4uhP0nRGaW6", "29756": "p9rqW9AZSiRR6yPN", "29757": "LEJhtBQA3vksnqQh", "29759": "Df0WBjZMWblyI7eH", "29761": "cnFJZVE1HA9zYB9z", "29762": "M35gAB2nFpOUvE9b", "29764": "iW982ZUd4T5mY9VY", "29766": "eoE3yfqsqBfCOF3T", "29767": "bZif7z2gH1hjg4x5", "29768": "PiHc2uITovlIouDo", "29770": "jlagOAiYTy7hrYIU", "29771": "1Q2zuBru3B0xtzZL", "29773": "5x9pboO3NN44skkX", "29775": "i8QqORuQsOCPsaaP", "29777": "DGA0J0JN5YOsHn71", "29779": "4mL4l8vEiziedl1v", "29780": "C9J57qJn05CPPBrx", "29782": "5ZBjfHBmw36rrFD1", "29783": "yXP8AbEQAQqPgpVB", "29784": "z2HybH0w1ejxZSyx", "29786": "FfELFObgNBqCXOXH", "29788": "kvso2Fmrni5biQOI", "29789": "FwXsx5qCP2ItIAL4", "29791": "5kKqrG5kVU7tyjUh", "29792": "scpBsdf1g3HNciSq", "29794": "HjVCFmB43IPttda4", "29796": "HuCFGRTD63muTthp", "29798": "8A9qSKSHrgUhZphU", "29799": "8RYBXtRDmyR5wO5T", "29801": "irf6PB4Gl4zpmm0S", "29802": "3kJQJHffDD9pRnBQ", "29804": "bmtffdo09e6lw10y", "29805": "F1XK6jlL3vTQjOiP", "29807": "nqHWVtH3hO0ZVm12", "29808": "lEMABEV7JDIAyWHv", "29810": "31wKDVGyxZNMEP5H", "29812": "3iHRJ1a53Ame69vR", "29813": "jTBQBr8Ra1MApPxc", "29814": "QU4dxXsY7fFecOkW", "29816": "c47czgCiAdiNLePd", "29818": "o3bVIfK8qgIlQKp9", "29820": "WQkscSgSsFNDpPyx", "29821": "e2mbmKrZpGvZb0v0", "29823": "XVN3MUBjvKO6BVm6", "29825": "214ZvA66E6HqI26o", "29827": "LhYiLsYh9qqGp6ET", "29828": "TXk3e4BTj2yosTBG", "29830": "V5zZsTHd0yqyCN0u", "29832": "Kccc0y7QALRIHU98", "29834": "eYF7PIwsS6PsKRPN", "29835": "TxrUMTYDsdPI0nQ4", "29837": "JgFcUIRaXeKiXiVi", "29838": "HNUFMwBJrlwzRGoX", "29839": "wp1cGLxdBzCrg7V1", "29840": "THh6DRVWuqMUkn43", "29841": "5rSXkR7bCCVYeMRv", "29843": "AfunqnSLVVtu47wV", "29845": "P2tFR6yJHVFszXe8", "29847": "7F9qGrc9Qm1j7dEt", "29849": "15i7WCkfYqx9T1M5", "29850": "EVd8foGnSfeeH3v5", "29851": "bmGrNe2Nces5jwxy", "29853": "CYrODTV3YGVwnFdg", "29855": "BjhVzgTcW7OL7CFL", "29856": "IxOKOPAxOdQzx17x", "29857": "vPimQPFG4xgl1p9N", "29859": "52ua8y32xmzEPQP1", "29860": "jPAQzmJleO2BzpKU", "29861": "IJrIW0K1ZB0qDcjk", "29862": "CbR0ilsI7lKKnEk7", "29864": "f0RyOEgYUTcL1qcF", "29865": "6cyewkVndJbWx3vM", "29866": "pXP0bf5h0uvEauca", "29867": "fvGJRFRXFWhL1wed", "29869": "gagnC8YET4I7te73", "29870": "6mNagliKRtj8CioC", "29871": "L07rqXH6yt3gmiUt", "29872": "x9jqX5rCXR2Qk9Ej", "29874": "PWs4YRUCffmAN1sy", "29876": "Y2FBuSfZ8lsUb48d", "29878": "K7ImhqkfyPAUbfc8", "29880": "zanZsmMbBdEBsKWb", "29882": "4jA9CqdHnuKnFNMq", "29883": "yCNnhEl2moNe9VrK", "29884": "6OYdhJAG9Pd3exXG", "29886": "Dh2W0RJ5y1EnfR30", "29887": "nu0KNXZnovgqqxLW", "29888": "8Q5yzFIftSBcxwXb", "29890": "j83ptuoDfEusX0x0", "29891": "Z2nA34k4vZUs9YHo", "29892": "sz1YE7moEByEsyYu", "29893": "jYtL7Z7C0HKbQSzI", "29895": "FD9QLE4bzdMA3cGG", "29896": "PkYdswKQGRxLVG0b", "29898": "oS0w8GC7q0pEWpKU", "29899": "lYRcpE2G7vkxaCIb", "29900": "JSqWWbUhyf6Q9Rw6", "29901": "vmoX341szA2ZgIEz", "29902": "mvjUP8siF41K3SOF", "29904": "hfddtGLSGZjcQTGR", "29905": "gpIoztJQEwMRfEy4", "29907": "znkheykGjSHmMzfx", "29908": "KQM36xX8E52tb05I", "29909": "MMrKUYpElMWCgMEd", "29910": "lethzihZsE76etll", "29912": "r9riRtxsBNiaQOpp", "29913": "QaqyDd9JkG2Db46o", "29915": "DGArk7jIqKVHNlqG", "29917": "LgutUca9Xcvsii80", "29918": "0FLcYeEF528vUtYv", "29919": "FIm3fHAxGsdIl8pE", "29921": "5xuW6ywJPnSOViYt", "29922": "3sA78EzT0dI46mbF", "29923": "zfkYPBz2TRQRqCmb", "29924": "bFN7jo2xvUnkQj5M", "29926": "rS2AONWahApjTbY7", "29664": "dJ0W34hCmXhVj31X", "29666": "NvTVI0gRUBsdFmPs", "29667": "9VGT0riTxKKfqvVh", "29668": "LuHU8BVZgKxnF1JZ", "29669": "5uhOCvSSGi7XkYB8", "29670": "v7QXjlDHorm2O0Hb", "29671": "wsKqtRmlB8qxBChB", "29673": "gYF6Ilxyx2oxCThK", "29674": "OAntOkPx802P7M12", "29942": "ARZnQRV3q4S5LJhx", "29943": "lacUn4JUctRhBD9E", "29945": "Zs0MOEoWs758tLhu", "29946": "wqmDx9080YKwa7DY", "29947": "KUd5bdEqzzLrd47J", "29948": "FNl5Jd22lYNaqCi5", "29950": "NqWS0F5S8fCixPDO", "29951": "sqH6qp1erZkDh3VD", "29952": "57Vl4ZVd4Jo2f4m8", "29953": "Wk13YyT0kzeBw51j", "29955": "LG69HvkzMpP2s4nL", "29956": "wtYHSRkHAKChv9JQ", "29958": "VY9iB7Lsix6VYBVq", "29960": "ysv9nUHnKCeLGmuB", "29961": "XznZ8z47PpQ0yQzA", "29962": "QJRq9BmZ2WFpUkkM", "29963": "RPtdkjSCvt6PgUxv", "29965": "31RBKdpRsjjHsTV6", "29967": "57EuEU1pi8DnyulC", "29968": "Hfg5AvzqPpzZqApa", "29970": "PXoFduoxCQdlulSd", "29972": "oXnncWINzqDwybOX", "29974": "ry9P6pkEcL1lD4aw", "29976": "1HCxW0nOrV4sTlSk", "29977": "uTUKWarqMMwelAkS", "29978": "9AgoaqYPhMPQtiis", "29980": "VkDmiOtmimOWgzlR", "29981": "gOsYvgSa7sce2WiW", "29983": "Br4PLRz6uvNQuhLQ", "29985": "NdqhjV2BuCnYcsfx", "29987": "Inp6T1elcQV3ph1L", "29988": "PctWhME0kQb7ZBge", "29989": "uMVf4A42balgVxBb", "29991": "NMzm2XtWZ6VbG3Es", "29993": "EkbxdZjZSXwhGnon", "29995": "7PXOAkqMBAP2aatK", "29997": "x1wIvaHppuNezCFY", "29998": "yjBfJcoxA70BTbtL", "30000": "Ha1sF40LlLqlttxl", "30001": "fejDqZJg2zyx6y08", "30002": "5husYBEFjd8qEV2h", "30003": "Wt1D1Xmvd6RGkSaO", "30005": "DXwMauwGaVVIgkCG", "30006": "td0wPrJMwt0VO40X", "30007": "tmAH116dOGsOatcE", "30009": "QcLHWuN7WGzfHIZf", "30010": "DjMVf3F9s8hgtamV", "30011": "lRIrPIWWXVvwAdHp", "30013": "zaAZHZiCJvuZpQ0E", "30015": "yhcWD2kmRSc4v6Ay", "30017": "oYDtHzYGZuIHrojO", "30019": "1LCw0eugd5yg5Z8z", "30020": "4TaqfCA3Hd5MWh6y", "30021": "jYxXFTWAl2qdYHHn", "30022": "WMCfUXIcSxO8CTAp", "30024": "PgCoTMYkFY6Ab9Qw", "30025": "tY88DMvmnPkeoMai", "30026": "Tm0sF92nuE35beUx", "30028": "UR232GeLoTozOwSG", "30030": "rB1oM6Z823bTo4tJ", "30031": "JJwXFRU8lgMLASEd", "30032": "aI8Lzb2tcaYhJUj8", "30033": "ML1geW0kBCUtVXld", "30034": "tiEC71thwa0WVQrU", "30036": "ZyYfQgmYEqsKH0IQ", "30038": "WVoIwZOT3RSG3n93", "30039": "jCTfPB4Lt44ygFQk", "30041": "hKZtqp9lZCwDuKoN", "30042": "L57NdcjnXfhYTxDT", "30044": "CmeOe5OEo9jl6fIy", "30046": "sZiyLhz2FsakS2M7", "30048": "CQWcmbLYYKzMh4ul", "30049": "pjobUJuuzwhmGQD3", "30051": "2cslxwGAjzKGNK5S", "30053": "FhL0c2rg9AUOtaf7", "30055": "LihCqT3hlippcYb6", "30056": "Vc1tjbgsyvHvC2lv", "30058": "hCuZjjxZ4yoUcfLK", "30060": "y4qpif6hZJwIssRy", "30061": "Qc3PWQ0vvAby55E7", "30063": "g2hij5R3M6uRAcDO", "30065": "9xFLWzkd0yNR2c7b", "30066": "7AocP2TgemCNWzou", "30068": "aClWTUS2isExH1KT", "30069": "bMqRV4nkiiEqqLK7", "30071": "FYyK7HBkaLhcspog", "30073": "di1vL42H0nqbIBsL", "30075": "6poiqEx0OjNcCqNt", "30077": "c24FSWSCpiQXCy2N", "30079": "1XVIrCtO5Szo9aZC", "30081": "WMDvgfiga5qKEUGx", "30083": "sesu48Z5vqcQjz2G", "30084": "MAvEmfrabjU6E9G6", "30086": "lspVwJkyy7tezhFx", "30088": "VNhz9TAfU6tMpKMc", "30089": "JVpLyrXmGaL6OR57", "30091": "ul1YLtMzRftm31Tn", "30092": "n2QHIn4FDiiuGble", "30094": "sZGttZeV3RbaNf6W", "30095": "C08Bm0vvRQ9mdO3m", "30096": "7L5dhs4JqBknD4wL", "30098": "ZyuiDiepVDUOsnRK", "30100": "dOUT3I4EkVO0ccFH", "30102": "HovBZ8qGj5MPSPru", "30103": "6FhO564dvr8Z0Ya1", "30105": "N9wVpTYWol5XcckL", "30107": "tMEuO9wvV6AoPfpt", "30108": "GvppZbTaihIzVROh", "30109": "13f3IomW8BKFpsc7", "30111": "0yuqwe49URZeNC7V", "30113": "Xdv5F3EYhKstcRFw", "30114": "6EDSTzk9wGt1lg0b", "30116": "tfP4WugO8f7StOPW", "30117": "j4JOVyJM2uftpLor", "30118": "JfOutQHPGLrEDA05", "30119": "DmAFUN0bLMCBGTKC", "30121": "wfRRLigCuHZVKnuw", "30123": "Cm32S3GLBtfzL5q5", "30124": "ideewz04V1ESRfr8", "30125": "9F7oKXbYNkLPWjtq", "30126": "eO5ceGjsYrh0f3yJ", "30128": "wxC0GvN1vFnJ1kK3", "30129": "mH9qS8lpUKnQy3tq", "30130": "0xHvzaY55byhbUTv", "30132": "ulIYHicIUmJuBccI", "30133": "YLGDguxqJovnXQgy", "30135": "hgT4dAJer1a64cV4", "30136": "at2i9N2Tm32dFm5W", "30138": "2KGaZKv1aDjjNHLP", "30140": "SAoM7flxDDCMYhCL", "30141": "khKEkQfs1POovGvL", "30142": "AvGXfoznfRoo3C0Y", "30143": "DXpQAKpXUaTphvOz", "30145": "adb7IgOikWLaQq1r", "30147": "5mIrrZCyk5CN0Fh1", "30148": "99p7GqHhvdYoFzny", "30149": "5U72BMCuE9htRpFt", "30150": "aSFkeP0MW2EzBkLk", "30152": "LQSTThA7a35kYgQ1", "30153": "6dMpO9kai0VM7htd", "30155": "CwEw7ogWGNpe33O6", "30157": "kHYPKuLvSTULGn0T", "30158": "HuSIHlPQofNyRq7F", "30159": "QTDRuf86sCnSQkfi", "30161": "1SjlpTpHzyDEBxKC", "30163": "YcPYvP7C7bdGKop9", "30165": "fNOPCx5iz1gaNQ0o", "30167": "ZyHsFIsjFb8bUOyv", "30169": "Y6vqIEpW6vzsw44c", "30170": "JIrs4iJEY1f2QZYV", "30172": "VE8YKMXQFB7OLEhO", "30174": "r6BDi7UNuMfPRIhi", "30175": "hjzsXdMTs4sRhW2F", "30176": "aMHyz4rUzuS7oE6J", "30177": "8IBF3pD0M0VMc4PQ", "30178": "1u4JjO9R5bWILU53", "30179": "mb81HIz0v43cZEAk", "30181": "0G2sdGowjTF7HANG", "30182": "4hvnxg5aHrjalpus", "30183": "2l7aW8WATIziFh5f", "30184": "HMtGRTF62ENMYN18", "30186": "YgFhSO8zNHrkkGXJ", "30188": "RFFHmGt5ABP3cH5i", "30190": "OEniRjhlDYJkgPKd", "30192": "eF2AG8jMy6lIoxaF", "30194": "2aW3MQsm983fvOWC", "30195": "ukg9utcO3o2REfDw", "29928": "yP35NaW3Bp3oDeum", "29930": "TtTYzK7bkGynx4hQ", "29932": "utyiheZSj6nFvMSB", "29934": "Yj3Q2DgLcH7k3xgX", "29936": "VXImPy3UHN3hiyy8", "29937": "ITpLXn2YfUgSmaJG", "29938": "UC0uDFgqHkEOnKg9", "29940": "tpoWAXIZvHA7rnKf", "29941": "jvbfVQmUTDOOZ6ff", "30212": "czsQqvh7Qec1tweb", "30213": "P1VFd7CeNEuUXpwx", "30215": "ZYZ7XcNyM3nIWjD9", "30217": "cKENG5uaG2EyyeoC", "30219": "sABIypkIRl2JPiAa", "30220": "BsSBULHRdqwwl7XD", "30222": "0KCXmug2fz6HD4QN", "30224": "XceDx15OPrKZkqjP", "30225": "rLMy5MsV3hathDfH", "30227": "lQXfLcsHjgyGjlIP", "30228": "eOVeuYGYvGRcOF88", "30230": "WUzVjtbo4mtjPKcA", "30231": "scGHMikoQh6rH84B", "30232": "ih7mGW7kjKSemAVg", "30233": "XchHv7EcoXD3m84z", "30235": "IpWoOiBA5VWGfg62", "30236": "8JVwTnsuTQB1jcGv", "30238": "lIgvqGAGRZ7WNlh4", "30239": "CDzPahk16pFtpOV9", "30241": "rLCFPTQUOMYTkcRX", "30242": "HEEq7tubUPWBUHxx", "30244": "TVCrIX0rXfnzyMuE", "30245": "fBqYZEtZnKnyn96U", "30247": "Fp7Vj9OvdGPtL9E0", "30248": "2L8Hme9kEEh7FOAL", "30249": "HWSEzYLP4bZESRdj", "30250": "Wk1cfA5e0bMI57DE", "30252": "uizGg3YRWPVB7oMz", "30253": "E4aitqIZiKVwnCil", "30255": "tGZoYUBReaCZJKDn", "30256": "tx9HFjKpPnzIvFkl", "30257": "lonPsrmA4Igv9m9K", "30259": "mG8GgyaY1hHRCmyQ", "30261": "PEpRK5RrMSYJqjpT", "30263": "8lKpu05qAG4g3QDU", "30264": "ILCw0xu5gnQMNuEF", "30265": "qjnWOJhH2flS3Gr3", "30266": "iDfCIqtpk3mfNC2D", "30267": "dBLh3j7VAEM92uDl", "30268": "JpfSKeKQhEExI2PD", "30269": "AYBwigyw8uFPeN9P", "30270": "uzFdx5ToCRMNslNe", "30271": "QCWrsMg4kjhaKQvy", "30273": "dTCaBSbkl2mtXHSw", "30274": "c1BpJfNRnlCYfkPg", "30275": "qdduMcr9uzCaNgrC", "30277": "RgJt5kIX8C4C2TYu", "30278": "hwLAhgxTJFxZgRfF", "30279": "bCc66uRPkQYI2U07", "30280": "u9eaKn9sIaw0IaTa", "30281": "RdNmObWkViKausX1", "30283": "oO8E9elbOapCgB6t", "30284": "PYG4vhVxksOYQJdt", "30285": "pRvfSdZHoTs1ES6F", "30287": "Y7FP9kzTmvgdwbRp", "30288": "EXbtA1ToTvnCVAQw", "30290": "MfL2OSzTxQ6F6aYK", "30291": "ADw4wJev0Mqdc3DG", "30292": "zAWEjOep8YPVThBc", "30294": "ZQ3nEYBXEUnMFBFQ", "30295": "e6P2YFclioBqC5dK", "30297": "flOjAovmKffy2p53", "30299": "SQZ6Go9wKnOb3DNt", "30300": "KAJtVusKSmQJnBWE", "30301": "UTQZS0QwBRrrLxUj", "30302": "zvSTvQVRpKMoAHn6", "30303": "cOkp08LreOBnN5Nt", "30304": "85ZqxzkIABIRrwH2", "30305": "i0cqI7AQ8OeRbEpz", "30307": "WrZsB5bL1bGa3DVZ", "30308": "3aIrVBmOa1mMj5TI", "30309": "cW4NUWdUCWe8lirD", "30310": "tbwtgF2sERpiBIQn", "30311": "kawyHFy7cGql4o7G", "30312": "oc5TnuznJ8jzmpcC", "30314": "DNShdQNlh996Gu32", "30315": "oTsA3jNLl79kQm2t", "30317": "2MOsf5GGGOT7rOIG", "30318": "8S3LObD87hUJ42G6", "30320": "WXgNRdADPc9hx06Z", "30322": "P7ozXkrTvwKdNcOY", "30324": "9dYI1Q6eMxTGWmK8", "30325": "ll8JkzR6zw65LqV1", "30327": "IiDPlhtFynWUcRLZ", "30328": "wp16EyRhkYcqtrFo", "30330": "0YKVFf0bIlZQM7YA", "30332": "rfpb9ZsMkjkLYA7T", "30333": "Eqsn6SkYOjdJ4uCB", "30335": "9sBHp0aUiGWyymKQ", "30337": "R5nUikLFwuYMkl9R", "30338": "0kMv0OslTQ7apmjr", "30339": "mdoDaJ30dXcofgCc", "30340": "H9MN9Lw8tXjTz92i", "30342": "p7npEiAs3SofeUA2", "30343": "ct6JYjOl2Jpnmt9M", "30345": "DjXrUCWE9GFYWwN3", "30346": "Rl6Rfj8mPkwa232l", "30347": "Y9eZSE13EHOM8eq5", "30348": "XZCgK9c613CDXUKM", "30350": "w7RQywyfafFWEQR0", "30352": "cyBFGrYb4Ve23niA", "30354": "HcD0GtbZWMzZudzk", "30356": "I9u08bje9nV10xzP", "30357": "rItS8RYG0dpr2lYH", "30359": "7c6d1rcMprq8jga3", "30361": "OleVNIObxHebp13P", "30362": "lkVOg8fk7fCQKfjb", "30364": "IT8AGNIM4XGy22I8", "30365": "PzVC5j3RcKSCP1EH", "30366": "ZV0nICCUcebJNpiO", "30367": "yS7BcoGpnPcoisjL", "30368": "i47ZGgHeRb69hHVC", "30370": "6my8LuDHg0OBHMIg", "30372": "scNZW5qPqwTiP3lj", "30373": "Sv1Bfg35zN9SXniC", "30374": "BJa9wyZJoTzQDwHh", "30376": "sF8AXXy4GvRZXeKP", "30378": "JnNCfP3OJevvTNNU", "30379": "Vn2VY6FVNrb4PjTe", "30380": "HGyJn3co3Yu6o2xq", "30381": "vprp9YiaQMuTonms", "30382": "PGw05vbQFZ3DLVnW", "30384": "GAEfw1a1CPq3dAYM", "30385": "laicK7OYj4v4KtPO", "30386": "Rq6KClpW5Xj05rBL", "30388": "IoCuVYEFwrveUtMV", "30389": "s8yNZGoUhwdLt2r8", "30390": "5l7GvvSPvwXQpUC0", "30392": "tyEKPD7PO4CYGTXH", "30394": "yGjNowCohNesZhg3", "30395": "PzwJjXm8YBOjOHwi", "30397": "T2WUcZEX0brmq1Gn", "30399": "CoGalxkksPV3vgZj", "30400": "XlN9NETfGZT3x7e9", "30401": "74PDJoHaXHkJfX1D", "30403": "MnCygK8Hdz48maLm", "30404": "un8MiUQ3idnN7zSZ", "30406": "CJ5eOXwk2eBpj0hJ", "30407": "loDf3AGZssocuv2Y", "30408": "h5LdnWrI4jwrt27O", "30410": "ZT4Pvku61R64Z33u", "30412": "Y8x8ke2B0Mp2aRKV", "30414": "wPiyyagKBnHKWPhd", "30415": "0iAp7rF3Xr9PY6OJ", "30417": "EZLJe8nOBXblDV1t", "30418": "2IYeIYYaKUrdTgga", "30419": "3ZFL044D5tbuamUu", "30421": "xYI2R5bR1woEeFRh", "30423": "x7dOUGFl5Jiq3SKz", "30425": "LQOdxZEzCNMDt99U", "30427": "QCV7fn7QylbaT15q", "30428": "9ZZACFAG3x2P83cR", "30429": "RFxr6zbdSNoFIQx1", "30431": "cIXYAuCeO8D4xnW1", "30432": "hnFs49GPsB7nuGGj", "30433": "Q1IgR5mpgRcobCE5", "30434": "tZOyLsmBBiT6Dncd", "30436": "oKYOo3lPJBrwtUlK", "30438": "eMZwgpw0WO4Qv6dV", "30440": "Xc355iJ1OoUXs23I", "30441": "11lLzY2qYaswNybm", "30443": "EBZgsvbNTj5Tl98j", "30444": "gibgsq4PRRLl8gC6", "30446": "FPmBtOWiq02U85pW", "30447": "QsWWOyHbMJju4dYD", "30448": "ZKEQDLX7vjwU1jv9", "30449": "wbnkbzRMygKcM25I", "30197": "Co0Av5l98cc2dhFB", "30199": "TiLd7Y3SzwO9fuF3", "30200": "DmqQ9mrrB5orH9H6", "30201": "ITKziVwPDOEwWExs", "30202": "GufP17wJWNXROfnc", "30204": "tg9ElfobRjPpCyjo", "30205": "nYSE7e0aLWoQoe1C", "30207": "7RCT4kfSJY4aRQdY", "30209": "W8FpR9xeenTngrfv", "30451": "hS1HPbwqKx9g7YSm", "30452": "yPzo9TKFjMANzKEj", "30211": "tASeMHxGOVLLnchh", "30468": "nQrnILB8qyBfcg0t", "30469": "oVYldGVEdwpQQOkF", "30470": "5Bkm1q4MI2Q4H81m", "30472": "sI10ZwGRS2yANkPP", "30474": "0MARmcuQAxi7MUrO", "30475": "NtTuEOa39pZLAmpx", "30477": "YaNlHykreRvzm3nB", "30478": "ytI4wFckZKlPbMow", "30479": "NqEjJvfyOiOPwBkh", "30481": "Xek6E1BBjF2JDeX2", "30482": "SX9Za5tK7LcGwj0B", "30484": "cXgyRdnlCur9OFyr", "30485": "7LfxD8PXsjbMMHkD", "30486": "5inauXpN8UdXkSu2", "30487": "QesvWRu3ZUUDrMjX", "30489": "yD6xNhFsG5L4WUni", "30491": "5Yr7M5KtgbyecQGA", "30492": "jk91lcSylu6JwniO", "30494": "alDer5Bmw8BbJMjo", "30496": "frG38SbsPyW91HNZ", "30497": "V6AlpgGwMaf1LCjx", "30499": "xzj8cM4HmNjJY1jr", "30501": "N0j0BczB2xwezepf", "30503": "DbasXqIFxWstt7j3", "30505": "4eETYIwR5lTMc9q7", "30507": "8JGvIhVQNmgYImJQ", "30509": "QEF9fkiQeiVscc2i", "30510": "6XHbyiMRhLoDxxPt", "30511": "vLC0YHfMIv2GEXEW", "30512": "TXeSSpuoGZ5fLiaX", "30513": "MRoI82ND2f7DuHvY", "30514": "2gwlGZLXhsFiKAYH", "30515": "t9Gk7i1jBjLkPEah", "30516": "8OLk0wbw6KiWWx5o", "30518": "SAZ1F0CfDzfErM3R", "30519": "E3ODgZh9pvWcD0gl", "30521": "EnpeyD0GKkM8ur9m", "30523": "7YfmBhNddtWSwJYO", "30524": "wQBTV1oi4ceBrGxi", "30526": "EMXiYmtzBqY5rS7K", "30527": "dR9a2cH1neLKQHUm", "30528": "8LZkm15knEYTHgqD", "30529": "ZGzzUVM1eJuk8v3x", "30530": "jpdsDVxjtsD6CmWa", "30531": "FZFTKSiEJGud9lyN", "30532": "iZhltOKyEhFWfgm9", "30533": "3JuUBgCvek6X3CcH", "30535": "yzDsChr2MzCdd8uT", "30536": "9BFVnkY9IxrZ64d2", "30537": "wAU8hijdcMkK8DU1", "30539": "znvpBIsGX5x3lyeC", "30541": "FN0cCRwLruW2JvCR", "30543": "MyBaV808WPbBxBzN", "30545": "n1lhS5edo870Gcic", "30547": "4RMcH0ZllXAXFaTG", "30548": "dSpeucirY6pwTWtd", "30550": "nMvz5QZqNmw9ox9t", "30552": "b7aMQyGdeSXXL02I", "30553": "F4BXEKStIQ8jqR1b", "30555": "fQSowFHeimZTrVtd", "30556": "J9EttFtLTKVBCeun", "30558": "IrGFFT8aMxnP9I28", "30560": "EME46WbyFePipfgC", "30561": "y4PbTyWuW47s10kR", "30562": "2XmWyyLYH9TzbRiT", "30564": "c2s89JHcsSjTFpHy", "30565": "eOgRsTtemoTJRdjd", "30567": "obDr44hqV7tvEOPQ", "30568": "ZSkbYfFjl9dY2K8M", "30569": "LILrFkaruEc0Fq46", "30570": "TQ1FFN2XGE9VnNdI", "30571": "7gXypp4e7APjga6x", "30573": "RkSkEPNqKNrlvwyZ", "30574": "QSfKBUpcDYenYRAi", "30575": "N7U6QufSGjNIx5En", "30576": "7phe1Pud5T5WABwC", "30577": "x6o5qQaicRQlCueW", "30578": "25ksHoKSVRRRoHJi", "30580": "ThdF7wHL37veu4sL", "30582": "aIyTRTLSUHE9eU5K", "30584": "WJ4o6efY3BN9pTvj", "30585": "a46EzYoXxGjO6plZ", "30586": "EbromMbPXt2JuMs6", "30588": "kaOzK6kJyAMhsAGO", "30590": "6jKCZJJIo8TvzdiY", "30592": "tL0b728Ezr5GKbL4", "30594": "pIkxYIJhK9bVvRed", "30596": "kjq3tL0D1OpA7gRp", "30597": "l1UnuAWXW5YyvqXy", "30599": "SekZry0cgCkpubUw", "30600": "pDxThjN1JPO1glem", "30602": "Z3QzZOXmsa4x3Igp", "30603": "6LeDwmHiGRjktjuL", "30605": "gxKOcKp4IQzJ4Hbl", "30607": "TVrtMANFcApSfKIs", "30609": "jGJuIkS1EjxjbbmP", "30610": "ZBrY7khPS98iS0Pd", "30612": "Krbq7kKYsb7Mo2xE", "30613": "Ex8LWuhSaBeXUf52", "30614": "W4nc6rH9ECaeXgRI", "30616": "81LiDCVYq6vPe663", "30617": "JmDJ3wG4tSE3fewG", "30618": "RcHkAOSDs9ghMzJY", "30620": "14kwLy1qENcz2pFb", "30621": "XAISZw0Sig3YZbnS", "30623": "1CA4dj6ett9jhGKv", "30624": "9D87olupmywDiKyR", "30626": "mq6Dcu4HNrwNOsnV", "30628": "A5lwUbd8FcQqTXWN", "30629": "OhGLtLEF8ohpSr2K", "30630": "uJiB1JDcVQ8DSfPk", "30632": "b4uZADgrYzMVbC3X", "30633": "uojxeyfbaXsd6Nwo", "30634": "SJy65Orsw4jajEV4", "30636": "AL3WCQrvR011OgNN", "30638": "SrhJPb7hLXrN03gG", "30639": "NGDQj0QttBJ0jtPY", "30640": "byB9eB1qGqRuIxNa", "30641": "jOAvapazrGE5Is5C", "30643": "nxWajGMlQ7sdagMr", "30645": "ztjXEHv3n3AdRsYw", "30647": "jkXRXM7gDaUKvpUb", "30649": "mZOMnW4Z8UNo3diy", "30651": "p3mbEaRhcF1iGmbv", "30652": "Ul6eHYZlU7IKzlfm", "30654": "rmRr7O8w6tLqxIyX", "30656": "xrAIIbUE6QpIX79u", "30657": "BAYbuJguBLTM7iZF", "30659": "XGjg1yx9LtPRXgHn", "30660": "bFWvHGZnYqKtLES0", "30661": "JcPlNf5lbcv3C4DW", "30663": "QNCP3ShCfXLgdEbs", "30665": "3Hogee86Gm5P7bXS", "30667": "D2t0pUP8CaUT2BB1", "30669": "OOl8q1gnEGeVqb4R", "30670": "ZZiE3PsZblNfrZ4P", "30671": "SWgzPD9QLGmh7kPi", "30672": "B6O88et8USKanX8T", "30674": "wjWm1VK5MPmUAhxq", "30675": "lT8hlAQ5s45IEVWZ", "30676": "lZTo3H8Bbp8inrTi", "30678": "XoCjtpG9c01YzsaM", "30680": "ZDUS8Ce7kitgfR1r", "30682": "TMJ0RZbr3tUk1CzV", "30683": "sPx7hwx7AaMMNl79", "30684": "ctHPn9rn1dwIvxwb", "30686": "L5ndNlE7Knna3xYP", "30688": "GbLdhrBKusEpdkpc", "30689": "Lo3bzIZLbBwl85Rg", "30691": "l7DuYohnM0YEnAWx", "30692": "kA5ZIB0Q13k0bqhc", "30693": "Cwhvb2hkfJ0aWoGb", "30694": "67K3YFDxIXOHdUdk", "30696": "rFUEZbSoAiwz9c3H", "30698": "EHhtwdmdmfQPjcSr", "30700": "nfsjvUvYCcD9c0Tr", "30701": "oexOpaNQz0Q6xU0U", "30703": "6SEosIk6BI1SmtIi", "30704": "Lc93VOv0qImh4qmX", "30706": "n2FSQghxIl3vcM4H", "30707": "cjrqB3k9PQJDzpaJ", "30708": "nvWOJxUuLQBK5u8Z", "30710": "o6LMnyIuYZxiHM4k", "30711": "W7qH1qMG2MvxGNX3", "30712": "lcVRggEwCerbVmHq", "30714": "s92YnHzUgxWK0SY7", "30716": "X1owaOH7Iy8JQj3S", "30717": "LYv3uXGFSreLLVun", "30454": "2TRNMlbGphF6ibbA", "30455": "LQoWn3hKpiPc2QUp", "30457": "gRFprKqL8c9PUSm4", "30458": "L8YhaqlrIsb20nzg", "30460": "thvYsOPqIFqdD1TQ", "30462": "IGovwKj1D2p01Jrt", "30464": "jRt1Qyv6dpmfJL9g", "30466": "1EJeiiCTV0mPZ0cq", "30467": "B5eC72MoNDHKko1t", "29411": "y4PbTyWuW47s10kR", "29412": "EME46WbyFePipfgC", "29413": "IrGFFT8aMxnP9I28", "29414": "J9EttFtLTKVBCeun", "29416": "fQSowFHeimZTrVtd", "29418": "F4BXEKStIQ8jqR1b", "29419": "b7aMQyGdeSXXL02I", "29421": "rLCFPTQUOMYTkcRX", "29422": "nMvz5QZqNmw9ox9t", "29424": "dSpeucirY6pwTWtd", "29425": "4RMcH0ZllXAXFaTG", "29427": "n1lhS5edo870Gcic", "29428": "MyBaV808WPbBxBzN", "29430": "FN0cCRwLruW2JvCR", "29432": "znvpBIsGX5x3lyeC", "29433": "wAU8hijdcMkK8DU1", "29435": "9BFVnkY9IxrZ64d2", "29437": "yzDsChr2MzCdd8uT", "29438": "CDzPahk16pFtpOV9", "29440": "3JuUBgCvek6X3CcH", "29441": "iZhltOKyEhFWfgm9", "29442": "FZFTKSiEJGud9lyN", "29444": "jpdsDVxjtsD6CmWa", "29445": "ZGzzUVM1eJuk8v3x", "29446": "8LZkm15knEYTHgqD", "29448": "dR9a2cH1neLKQHUm", "29449": "EMXiYmtzBqY5rS7K", "29451": "wQBTV1oi4ceBrGxi", "29452": "7YfmBhNddtWSwJYO", "29453": "lIgvqGAGRZ7WNlh4", "29455": "EnpeyD0GKkM8ur9m", "29457": "E3ODgZh9pvWcD0gl", "29458": "SAZ1F0CfDzfErM3R", "29460": "8OLk0wbw6KiWWx5o", "29461": "t9Gk7i1jBjLkPEah", "29463": "2gwlGZLXhsFiKAYH", "29464": "MRoI82ND2f7DuHvY", "29466": "TXeSSpuoGZ5fLiaX", "29467": "vLC0YHfMIv2GEXEW", "29469": "6XHbyiMRhLoDxxPt", "29471": "8JVwTnsuTQB1jcGv", "29473": "QEF9fkiQeiVscc2i", "29474": "8JGvIhVQNmgYImJQ", "29475": "4eETYIwR5lTMc9q7", "29476": "DbasXqIFxWstt7j3", "29478": "N0j0BczB2xwezepf", "29480": "xzj8cM4HmNjJY1jr", "29482": "V6AlpgGwMaf1LCjx", "29483": "frG38SbsPyW91HNZ", "29484": "alDer5Bmw8BbJMjo", "29485": "jk91lcSylu6JwniO", "29487": "IpWoOiBA5VWGfg62", "29489": "7RCT4kfSJY4aRQdY", "29491": "5Yr7M5KtgbyecQGA", "29492": "yD6xNhFsG5L4WUni", "29494": "QesvWRu3ZUUDrMjX", "29496": "5inauXpN8UdXkSu2", "29497": "7LfxD8PXsjbMMHkD", "29499": "cXgyRdnlCur9OFyr", "29501": "SX9Za5tK7LcGwj0B", "29503": "Xek6E1BBjF2JDeX2", "29505": "NqEjJvfyOiOPwBkh", "29506": "ytI4wFckZKlPbMow", "29508": "XchHv7EcoXD3m84z", "29509": "YaNlHykreRvzm3nB", "29511": "NtTuEOa39pZLAmpx", "29513": "0MARmcuQAxi7MUrO", "29515": "sI10ZwGRS2yANkPP", "29516": "5Bkm1q4MI2Q4H81m", "29518": "oVYldGVEdwpQQOkF", "29519": "nQrnILB8qyBfcg0t", "29521": "B5eC72MoNDHKko1t", "29523": "1EJeiiCTV0mPZ0cq", "29524": "jRt1Qyv6dpmfJL9g", "29526": "ih7mGW7kjKSemAVg", "29527": "IGovwKj1D2p01Jrt", "29529": "thvYsOPqIFqdD1TQ", "29530": "L8YhaqlrIsb20nzg", "29531": "gRFprKqL8c9PUSm4", "29533": "LQoWn3hKpiPc2QUp", "29534": "2TRNMlbGphF6ibbA", "29535": "yPzo9TKFjMANzKEj", "29537": "hS1HPbwqKx9g7YSm", "29538": "wbnkbzRMygKcM25I", "29540": "ZKEQDLX7vjwU1jv9", "29541": "scGHMikoQh6rH84B", "29543": "QsWWOyHbMJju4dYD", "29544": "FPmBtOWiq02U85pW", "29546": "gibgsq4PRRLl8gC6", "29547": "EBZgsvbNTj5Tl98j", "29548": "11lLzY2qYaswNybm", "29549": "Xc355iJ1OoUXs23I", "29551": "eMZwgpw0WO4Qv6dV", "29553": "oKYOo3lPJBrwtUlK", "29555": "tZOyLsmBBiT6Dncd", "29556": "Q1IgR5mpgRcobCE5", "29557": "WUzVjtbo4mtjPKcA", "29559": "hnFs49GPsB7nuGGj", "29561": "cIXYAuCeO8D4xnW1", "29563": "RFxr6zbdSNoFIQx1", "29564": "9ZZACFAG3x2P83cR", "29566": "QCV7fn7QylbaT15q", "29567": "LQOdxZEzCNMDt99U", "29569": "x7dOUGFl5Jiq3SKz", "29571": "xYI2R5bR1woEeFRh", "29573": "3ZFL044D5tbuamUu", "29574": "2IYeIYYaKUrdTgga", "29576": "eOVeuYGYvGRcOF88", "29578": "EZLJe8nOBXblDV1t", "29580": "0iAp7rF3Xr9PY6OJ", "29582": "wPiyyagKBnHKWPhd", "29583": "Y8x8ke2B0Mp2aRKV", "29584": "ZT4Pvku61R64Z33u", "29585": "h5LdnWrI4jwrt27O", "29586": "loDf3AGZssocuv2Y", "29588": "CJ5eOXwk2eBpj0hJ", "29589": "un8MiUQ3idnN7zSZ", "29590": "MnCygK8Hdz48maLm", "29592": "lQXfLcsHjgyGjlIP", "29593": "74PDJoHaXHkJfX1D", "29595": "XlN9NETfGZT3x7e9", "29596": "CoGalxkksPV3vgZj", "29597": "T2WUcZEX0brmq1Gn", "29598": "PzwJjXm8YBOjOHwi", "29600": "yGjNowCohNesZhg3", "29601": "tyEKPD7PO4CYGTXH", "29603": "5l7GvvSPvwXQpUC0", "29605": "s8yNZGoUhwdLt2r8", "29606": "IoCuVYEFwrveUtMV", "29607": "rLMy5MsV3hathDfH", "29608": "Rq6KClpW5Xj05rBL", "29609": "laicK7OYj4v4KtPO", "29610": "GAEfw1a1CPq3dAYM", "29611": "PGw05vbQFZ3DLVnW", "29613": "vprp9YiaQMuTonms", "29615": "HGyJn3co3Yu6o2xq", "29617": "Vn2VY6FVNrb4PjTe", "29618": "JnNCfP3OJevvTNNU", "29620": "sF8AXXy4GvRZXeKP", "29622": "BJa9wyZJoTzQDwHh", "29623": "XceDx15OPrKZkqjP", "29625": "Sv1Bfg35zN9SXniC", "29626": "scNZW5qPqwTiP3lj", "29627": "6my8LuDHg0OBHMIg", "29628": "i47ZGgHeRb69hHVC", "29629": "yS7BcoGpnPcoisjL", "29631": "ZV0nICCUcebJNpiO", "29632": "PzVC5j3RcKSCP1EH", "29634": "IT8AGNIM4XGy22I8", "29635": "lkVOg8fk7fCQKfjb", "29636": "OleVNIObxHebp13P", "29638": "0KCXmug2fz6HD4QN", "29640": "7c6d1rcMprq8jga3", "29642": "rItS8RYG0dpr2lYH", "29644": "I9u08bje9nV10xzP", "29646": "HcD0GtbZWMzZudzk", "29648": "cyBFGrYb4Ve23niA", "29650": "w7RQywyfafFWEQR0", "29652": "XZCgK9c613CDXUKM", "29654": "Y9eZSE13EHOM8eq5", "29655": "Rl6Rfj8mPkwa232l", "29657": "tg9ElfobRjPpCyjo", "29659": "DjXrUCWE9GFYWwN3", "29660": "BsSBULHRdqwwl7XD", "29661": "nYSE7e0aLWoQoe1C", "29396": "7gXypp4e7APjga6x", "29398": "TQ1FFN2XGE9VnNdI", "29400": "LILrFkaruEc0Fq46", "29401": "ZSkbYfFjl9dY2K8M", "29402": "obDr44hqV7tvEOPQ", "29404": "HEEq7tubUPWBUHxx", "29406": "eOgRsTtemoTJRdjd", "29408": "c2s89JHcsSjTFpHy", "29409": "2XmWyyLYH9TzbRiT", "28162": "RFFHmGt5ABP3cH5i", "28163": "ct6JYjOl2Jpnmt9M", "28165": "YgFhSO8zNHrkkGXJ", "28166": "HMtGRTF62ENMYN18", "28168": "2l7aW8WATIziFh5f", "28169": "4hvnxg5aHrjalpus", "28170": "0G2sdGowjTF7HANG", "28171": "mb81HIz0v43cZEAk", "28173": "1u4JjO9R5bWILU53", "28174": "8IBF3pD0M0VMc4PQ", "28175": "aMHyz4rUzuS7oE6J", "28176": "hjzsXdMTs4sRhW2F", "28178": "p7npEiAs3SofeUA2", "28180": "r6BDi7UNuMfPRIhi", "28182": "VE8YKMXQFB7OLEhO", "28184": "JIrs4iJEY1f2QZYV", "28185": "Y6vqIEpW6vzsw44c", "28186": "ZyHsFIsjFb8bUOyv", "28187": "fNOPCx5iz1gaNQ0o", "28189": "YcPYvP7C7bdGKop9", "28191": "1SjlpTpHzyDEBxKC", "28192": "QTDRuf86sCnSQkfi", "28193": "HuSIHlPQofNyRq7F", "28195": "H9MN9Lw8tXjTz92i", "28196": "kHYPKuLvSTULGn0T", "28198": "CwEw7ogWGNpe33O6", "28199": "6dMpO9kai0VM7htd", "28201": "LQSTThA7a35kYgQ1", "28203": "aSFkeP0MW2EzBkLk", "28204": "5U72BMCuE9htRpFt", "28206": "99p7GqHhvdYoFzny", "28207": "5mIrrZCyk5CN0Fh1", "28208": "adb7IgOikWLaQq1r", "28210": "DXpQAKpXUaTphvOz", "28211": "mdoDaJ30dXcofgCc", "28213": "AvGXfoznfRoo3C0Y", "28214": "khKEkQfs1POovGvL", "28216": "SAoM7flxDDCMYhCL", "28218": "2KGaZKv1aDjjNHLP", "28219": "at2i9N2Tm32dFm5W", "28221": "hgT4dAJer1a64cV4", "28222": "YLGDguxqJovnXQgy", "28223": "ulIYHicIUmJuBccI", "28224": "0xHvzaY55byhbUTv", "28225": "mH9qS8lpUKnQy3tq", "28226": "0kMv0OslTQ7apmjr", "28227": "wxC0GvN1vFnJ1kK3", "28228": "eO5ceGjsYrh0f3yJ", "28230": "9F7oKXbYNkLPWjtq", "28231": "ideewz04V1ESRfr8", "28232": "Cm32S3GLBtfzL5q5", "28234": "wfRRLigCuHZVKnuw", "28236": "DmAFUN0bLMCBGTKC", "28237": "JfOutQHPGLrEDA05", "28239": "j4JOVyJM2uftpLor", "28240": "tfP4WugO8f7StOPW", "28241": "R5nUikLFwuYMkl9R", "28242": "6EDSTzk9wGt1lg0b", "28243": "Xdv5F3EYhKstcRFw", "28245": "0yuqwe49URZeNC7V", "28247": "13f3IomW8BKFpsc7", "28249": "GvppZbTaihIzVROh", "28250": "tMEuO9wvV6AoPfpt", "28251": "N9wVpTYWol5XcckL", "28253": "6FhO564dvr8Z0Ya1", "28255": "HovBZ8qGj5MPSPru", "28256": "dOUT3I4EkVO0ccFH", "28257": "9sBHp0aUiGWyymKQ", "28259": "ZyuiDiepVDUOsnRK", "28261": "7L5dhs4JqBknD4wL", "28262": "C08Bm0vvRQ9mdO3m", "28264": "sZGttZeV3RbaNf6W", "28266": "n2QHIn4FDiiuGble", "28267": "ul1YLtMzRftm31Tn", "28269": "JVpLyrXmGaL6OR57", "28271": "VNhz9TAfU6tMpKMc", "28273": "lspVwJkyy7tezhFx", "28274": "MAvEmfrabjU6E9G6", "28276": "Eqsn6SkYOjdJ4uCB", "28278": "sesu48Z5vqcQjz2G", "28280": "WMDvgfiga5qKEUGx", "28282": "1XVIrCtO5Szo9aZC", "28283": "c24FSWSCpiQXCy2N", "28284": "6poiqEx0OjNcCqNt", "28286": "di1vL42H0nqbIBsL", "28288": "FYyK7HBkaLhcspog", "28289": "bMqRV4nkiiEqqLK7", "28291": "aClWTUS2isExH1KT", "28293": "7AocP2TgemCNWzou", "28295": "rfpb9ZsMkjkLYA7T", "28297": "9xFLWzkd0yNR2c7b", "28299": "g2hij5R3M6uRAcDO", "28300": "Qc3PWQ0vvAby55E7", "28301": "y4qpif6hZJwIssRy", "28303": "hCuZjjxZ4yoUcfLK", "28304": "Vc1tjbgsyvHvC2lv", "28306": "LihCqT3hlippcYb6", "28307": "FhL0c2rg9AUOtaf7", "28308": "2cslxwGAjzKGNK5S", "28310": "pjobUJuuzwhmGQD3", "28311": "0YKVFf0bIlZQM7YA", "28312": "sABIypkIRl2JPiAa", "28313": "CQWcmbLYYKzMh4ul", "28314": "sZiyLhz2FsakS2M7", "28315": "CmeOe5OEo9jl6fIy", "28317": "L57NdcjnXfhYTxDT", "28318": "hKZtqp9lZCwDuKoN", "28319": "jCTfPB4Lt44ygFQk", "28321": "WVoIwZOT3RSG3n93", "28323": "ZyYfQgmYEqsKH0IQ", "28324": "tiEC71thwa0WVQrU", "28325": "ML1geW0kBCUtVXld", "28327": "wp16EyRhkYcqtrFo", "28329": "aI8Lzb2tcaYhJUj8", "28330": "JJwXFRU8lgMLASEd", "28332": "rB1oM6Z823bTo4tJ", "28333": "UR232GeLoTozOwSG", "28335": "Tm0sF92nuE35beUx", "28337": "tY88DMvmnPkeoMai", "28338": "PgCoTMYkFY6Ab9Qw", "28339": "WMCfUXIcSxO8CTAp", "28341": "jYxXFTWAl2qdYHHn", "28343": "4TaqfCA3Hd5MWh6y", "28344": "IiDPlhtFynWUcRLZ", "28346": "1LCw0eugd5yg5Z8z", "28348": "oYDtHzYGZuIHrojO", "28349": "yhcWD2kmRSc4v6Ay", "28351": "zaAZHZiCJvuZpQ0E", "28352": "lRIrPIWWXVvwAdHp", "28354": "DjMVf3F9s8hgtamV", "28356": "QcLHWuN7WGzfHIZf", "28358": "tmAH116dOGsOatcE", "28360": "td0wPrJMwt0VO40X", "28361": "DXwMauwGaVVIgkCG", "28362": "ll8JkzR6zw65LqV1", "28363": "Wt1D1Xmvd6RGkSaO", "28365": "5husYBEFjd8qEV2h", "28367": "fejDqZJg2zyx6y08", "28369": "Ha1sF40LlLqlttxl", "28371": "yjBfJcoxA70BTbtL", "28372": "x1wIvaHppuNezCFY", "28373": "7PXOAkqMBAP2aatK", "28375": "EkbxdZjZSXwhGnon", "28376": "NMzm2XtWZ6VbG3Es", "28377": "uMVf4A42balgVxBb", "28379": "9dYI1Q6eMxTGWmK8", "28381": "PctWhME0kQb7ZBge", "28383": "Inp6T1elcQV3ph1L", "28385": "NdqhjV2BuCnYcsfx", "28387": "Br4PLRz6uvNQuhLQ", "28389": "gOsYvgSa7sce2WiW", "28390": "VkDmiOtmimOWgzlR", "28392": "9AgoaqYPhMPQtiis", "28393": "uTUKWarqMMwelAkS", "28395": "1HCxW0nOrV4sTlSk", "28397": "ry9P6pkEcL1lD4aw", "28398": "P7ozXkrTvwKdNcOY", "28399": "oXnncWINzqDwybOX", "28401": "PXoFduoxCQdlulSd", "28403": "Hfg5AvzqPpzZqApa", "28405": "57EuEU1pi8DnyulC", "28407": "31RBKdpRsjjHsTV6", "28408": "RPtdkjSCvt6PgUxv", "28409": "QJRq9BmZ2WFpUkkM", "28411": "XznZ8z47PpQ0yQzA", "28412": "ysv9nUHnKCeLGmuB", "28413": "VY9iB7Lsix6VYBVq", "28414": "WXgNRdADPc9hx06Z", "28150": "GufP17wJWNXROfnc", "28151": "ITKziVwPDOEwWExs", "28152": "DmqQ9mrrB5orH9H6", "28153": "TiLd7Y3SzwO9fuF3", "28155": "Co0Av5l98cc2dhFB", "28157": "ukg9utcO3o2REfDw", "28158": "2aW3MQsm983fvOWC", "28159": "eF2AG8jMy6lIoxaF", "28160": "OEniRjhlDYJkgPKd", "28428": "Zs0MOEoWs758tLhu", "28430": "8S3LObD87hUJ42G6", "28431": "lacUn4JUctRhBD9E", "28433": "ARZnQRV3q4S5LJhx", "28435": "jvbfVQmUTDOOZ6ff", "28437": "tpoWAXIZvHA7rnKf", "28439": "UC0uDFgqHkEOnKg9", "28441": "ITpLXn2YfUgSmaJG", "28442": "VXImPy3UHN3hiyy8", "28444": "Yj3Q2DgLcH7k3xgX", "28446": "utyiheZSj6nFvMSB", "28447": "TtTYzK7bkGynx4hQ", "28449": "2MOsf5GGGOT7rOIG", "28451": "yP35NaW3Bp3oDeum", "28452": "rS2AONWahApjTbY7", "28454": "bFN7jo2xvUnkQj5M", "28455": "zfkYPBz2TRQRqCmb", "28456": "3sA78EzT0dI46mbF", "28457": "5xuW6ywJPnSOViYt", "28459": "FIm3fHAxGsdIl8pE", "28460": "0FLcYeEF528vUtYv", "28462": "LgutUca9Xcvsii80", "28464": "DGArk7jIqKVHNlqG", "28466": "oTsA3jNLl79kQm2t", "28468": "QaqyDd9JkG2Db46o", "28469": "r9riRtxsBNiaQOpp", "28471": "lethzihZsE76etll", "28472": "MMrKUYpElMWCgMEd", "28473": "KQM36xX8E52tb05I", "28474": "znkheykGjSHmMzfx", "28476": "gpIoztJQEwMRfEy4", "28478": "hfddtGLSGZjcQTGR", "28479": "mvjUP8siF41K3SOF", "28480": "vmoX341szA2ZgIEz", "28482": "DNShdQNlh996Gu32", "28484": "cKENG5uaG2EyyeoC", "28485": "JSqWWbUhyf6Q9Rw6", "28486": "lYRcpE2G7vkxaCIb", "28487": "oS0w8GC7q0pEWpKU", "28488": "PkYdswKQGRxLVG0b", "28490": "FD9QLE4bzdMA3cGG", "28491": "jYtL7Z7C0HKbQSzI", "28492": "sz1YE7moEByEsyYu", "28493": "Z2nA34k4vZUs9YHo", "28494": "j83ptuoDfEusX0x0", "28496": "8Q5yzFIftSBcxwXb", "28498": "oc5TnuznJ8jzmpcC", "28499": "nu0KNXZnovgqqxLW", "28500": "Dh2W0RJ5y1EnfR30", "28502": "6OYdhJAG9Pd3exXG", "28504": "yCNnhEl2moNe9VrK", "28506": "4jA9CqdHnuKnFNMq", "28507": "zanZsmMbBdEBsKWb", "28508": "K7ImhqkfyPAUbfc8", "28510": "Y2FBuSfZ8lsUb48d", "28511": "PWs4YRUCffmAN1sy", "28513": "x9jqX5rCXR2Qk9Ej", "28514": "kawyHFy7cGql4o7G", "28516": "L07rqXH6yt3gmiUt", "28518": "6mNagliKRtj8CioC", "28519": "gagnC8YET4I7te73", "28521": "fvGJRFRXFWhL1wed", "28522": "pXP0bf5h0uvEauca", "28524": "6cyewkVndJbWx3vM", "28526": "f0RyOEgYUTcL1qcF", "28528": "CbR0ilsI7lKKnEk7", "28529": "IJrIW0K1ZB0qDcjk", "28530": "jPAQzmJleO2BzpKU", "28531": "tbwtgF2sERpiBIQn", "28533": "52ua8y32xmzEPQP1", "28535": "vPimQPFG4xgl1p9N", "28536": "IxOKOPAxOdQzx17x", "28538": "BjhVzgTcW7OL7CFL", "28540": "CYrODTV3YGVwnFdg", "28542": "bmGrNe2Nces5jwxy", "28543": "EVd8foGnSfeeH3v5", "28545": "15i7WCkfYqx9T1M5", "28547": "7F9qGrc9Qm1j7dEt", "28549": "P2tFR6yJHVFszXe8", "28550": "cW4NUWdUCWe8lirD", "28551": "AfunqnSLVVtu47wV", "28553": "5rSXkR7bCCVYeMRv", "28555": "THh6DRVWuqMUkn43", "28557": "wp1cGLxdBzCrg7V1", "28559": "HNUFMwBJrlwzRGoX", "28561": "JgFcUIRaXeKiXiVi", "28563": "TxrUMTYDsdPI0nQ4", "28564": "eYF7PIwsS6PsKRPN", "28565": "Kccc0y7QALRIHU98", "28567": "V5zZsTHd0yqyCN0u", "28569": "3aIrVBmOa1mMj5TI", "28570": "TXk3e4BTj2yosTBG", "28571": "LhYiLsYh9qqGp6ET", "28573": "214ZvA66E6HqI26o", "28575": "XVN3MUBjvKO6BVm6", "28576": "e2mbmKrZpGvZb0v0", "28577": "WQkscSgSsFNDpPyx", "28578": "o3bVIfK8qgIlQKp9", "28579": "c47czgCiAdiNLePd", "28581": "QU4dxXsY7fFecOkW", "28582": "jTBQBr8Ra1MApPxc", "28584": "WrZsB5bL1bGa3DVZ", "28585": "3iHRJ1a53Ame69vR", "28586": "31wKDVGyxZNMEP5H", "28588": "lEMABEV7JDIAyWHv", "28589": "nqHWVtH3hO0ZVm12", "28591": "F1XK6jlL3vTQjOiP", "28592": "bmtffdo09e6lw10y", "28594": "3kJQJHffDD9pRnBQ", "28596": "irf6PB4Gl4zpmm0S", "28598": "8RYBXtRDmyR5wO5T", "28600": "8A9qSKSHrgUhZphU", "28601": "i0cqI7AQ8OeRbEpz", "28602": "HuCFGRTD63muTthp", "28604": "HjVCFmB43IPttda4", "28606": "scpBsdf1g3HNciSq", "28608": "5kKqrG5kVU7tyjUh", "28609": "FwXsx5qCP2ItIAL4", "28611": "kvso2Fmrni5biQOI", "28613": "FfELFObgNBqCXOXH", "28614": "z2HybH0w1ejxZSyx", "28616": "yXP8AbEQAQqPgpVB", "28618": "5ZBjfHBmw36rrFD1", "28620": "85ZqxzkIABIRrwH2", "28621": "C9J57qJn05CPPBrx", "28622": "4mL4l8vEiziedl1v", "28624": "DGA0J0JN5YOsHn71", "28626": "i8QqORuQsOCPsaaP", "28628": "5x9pboO3NN44skkX", "28630": "1Q2zuBru3B0xtzZL", "28632": "jlagOAiYTy7hrYIU", "28633": "PiHc2uITovlIouDo", "28634": "bZif7z2gH1hjg4x5", "28635": "eoE3yfqsqBfCOF3T", "28636": "cOkp08LreOBnN5Nt", "28638": "iW982ZUd4T5mY9VY", "28639": "M35gAB2nFpOUvE9b", "28641": "cnFJZVE1HA9zYB9z", "28643": "Df0WBjZMWblyI7eH", "28644": "LEJhtBQA3vksnqQh", "28645": "p9rqW9AZSiRR6yPN", "28647": "Y1OJZ4uhP0nRGaW6", "28648": "XRuDtmqwCxaIz0Tj", "28649": "TGYCHa24AJ3NG6Mf", "28651": "Jxd6oZgz1ryTlRab", "28652": "zvSTvQVRpKMoAHn6", "28653": "ZYZ7XcNyM3nIWjD9", "28654": "xC02He2is1lZPxAz", "28656": "aLYJ9dTjsu0TS3Tf", "28658": "dafhyzV1ZR1oS4kq", "28659": "tBfDQvysB0IAYrKq", "28661": "GWNAfOIBTegrHYNM", "28662": "j8g7dj5SNP63HPBq", "28664": "7XQGCyxgULvnJLF7", "28665": "fEN9gK2eFZnceQBq", "28667": "PwbvR8bH2IFLAVY2", "28669": "aoMYfdtbNryiH7qv", "28670": "UTQZS0QwBRrrLxUj", "28672": "i87M1Da7jN3WjVq3", "28673": "EBDXSGR7nBkO7gIU", "28674": "Cxdi6CQ8JhbpkXJV", "28676": "zXYMEerUPv3ZZQZk", "28677": "jAC32g1GwHazzg9L", "28678": "S1Y4aFILwaubCS2x", "28680": "duO4pfwHuIrg45HE", "28681": "tcCpycv5DsMdQrqA", "28683": "Xt3GDyQJ9dSk02zh", "28684": "IUSxKjxrNQ2OHGuf", "28415": "wtYHSRkHAKChv9JQ", "28417": "LG69HvkzMpP2s4nL", "28418": "Wk13YyT0kzeBw51j", "28420": "57Vl4ZVd4Jo2f4m8", "28421": "sqH6qp1erZkDh3VD", "28423": "NqWS0F5S8fCixPDO", "28425": "FNl5Jd22lYNaqCi5", "28426": "KUd5bdEqzzLrd47J", "28427": "wqmDx9080YKwa7DY", "28698": "Xys0qA4PyTTP2xsX", "28700": "jtQzXvrbWcOyAFqR", "28702": "SQZ6Go9wKnOb3DNt", "28704": "ScmtSxXycUeCDTs6", "28705": "Yy0b857IqCSri0WF", "28706": "RRDcOylGpEZKxU4G", "28707": "JVuGBem9tkVKy1Uh", "28709": "J8SSeOntSQr6nWTH", "28710": "y2bwSL5SUx5mJorA", "28712": "rUM3edVnEdXdRzas", "28713": "mDFzoAIfrHfuSOvs", "28714": "lPSDoSXYFQBrBNbw", "28715": "T0ihACruHGtwpG43", "28716": "flOjAovmKffy2p53", "28718": "LLFHRxXqmPMdDP6d", "28719": "CI937Qw95h3P4Eox", "28721": "XfSHve9n8M37xhYd", "28723": "uW9TVWOIs7DBKnhB", "28724": "5rKUKu5JpcX18f4q", "28726": "sneGA2rp3M1BN773", "28728": "35JiqPEVR3E6gYDQ", "28730": "hvdvJ1zh8VbiSKEk", "28732": "xHbaaPsu0Ac83mM2", "28734": "OAntOkPx802P7M12", "28735": "e6P2YFclioBqC5dK", "28737": "gYF6Ilxyx2oxCThK", "28738": "wsKqtRmlB8qxBChB", "28740": "v7QXjlDHorm2O0Hb", "28742": "5uhOCvSSGi7XkYB8", "28744": "LuHU8BVZgKxnF1JZ", "28745": "9VGT0riTxKKfqvVh", "28747": "NvTVI0gRUBsdFmPs", "28749": "dJ0W34hCmXhVj31X", "28751": "vtNvl44kAAbhfSm4", "28753": "M3v3TWxbOSA4dnXj", "28754": "ZQ3nEYBXEUnMFBFQ", "28755": "nZHRmVirYlUvTsD6", "28756": "mUTuLI5eZHK8k8XE", "28757": "ZR8Jho2KNaYwCIGb", "28759": "kEJ4XPSfGmq3t1x7", "28761": "GMETb1dy2EjMUVYZ", "28762": "7dnHl7glrU8EKIcS", "28763": "feV5ufsWy4FtfODt", "28764": "me3WdlaQ4tpAjnLc", "28766": "DHAXpdbSDO2LojTJ", "28768": "MGnMkop427OjdB7a", "28769": "zAWEjOep8YPVThBc", "28770": "FszJp9LqbwG2C2qX", "28772": "QUZRP2X08GYUQmVH", "28773": "Pb43lYcwND8ALiX8", "28774": "8PG3e4ZPtHm83qZ1", "28776": "vlv3eqWNAOO81GCw", "28777": "nIBfgaQYGzduZyWH", "28778": "8IsPG8bygFiQThZO", "28780": "wOzCua8hLfLaPUFq", "28781": "41EuFRn1RqO0NdG3", "28783": "v9UnitYhQ0OxQ0kA", "28784": "ADw4wJev0Mqdc3DG", "28786": "Kf2zkFlfrsUMLhjW", "28788": "q1oLuLVN3qIlSPSF", "28789": "VeFzsAm1nE4KG6EI", "28790": "88FnprhuZz3NCD1q", "28792": "T8cnXenWfsNydKqS", "28794": "6fVsBVHuNbcbURCT", "28795": "Wjf7ZLF1E93b7OHt", "28797": "a3ow5EE8O3B7Lvx4", "28798": "fdZmhNwuqqxg3F3e", "28800": "ESnW6fIzypDGAH5b", "28801": "MfL2OSzTxQ6F6aYK", "28803": "R2bCnwdSc2nu1O8n", "28805": "TgMO1eontpeUJKB4", "28807": "7TKnZzrHQF5MigQT", "28809": "7n6QYxbgc2jbPbgy", "28810": "jfAnxxDEVJMsZtWi", "28812": "TgRLSVqx5JIjQPB3", "28814": "sSvu9b1R2By2OtN8", "28816": "x225oMNAyEQdQuoa", "28818": "W8X9Oo4ESPDZWxge", "28820": "sNiP6qJ89SDCjYep", "28821": "EXbtA1ToTvnCVAQw", "28822": "P1VFd7CeNEuUXpwx", "28824": "hx4Htu5eN8H4XyMb", "28826": "C10fvKJ2CnDZklSq", "28828": "LkaYzJ2se2IDQLNE", "28830": "jqwpNl87ApWZg2mq", "28831": "33ENz4N0FD7bNzwt", "28833": "axPoBSoxerca0IRN", "28835": "eiAdWvHXti4fjM5R", "28836": "zD0VAcarbPWWKnWa", "28838": "vuJjTvER8J7TzRz9", "28840": "Jwyhh4UqLDxefhcT", "28842": "Y7FP9kzTmvgdwbRp", "28844": "OU3V8vdYTC0hJG0R", "28846": "UkMJ2R6IzS6UJe8b", "28848": "EYkVZQRGDiAOHIXX", "28849": "SUe1tHRIGZ3eGgFP", "28850": "LtI5DJQaZlG0Q060", "28851": "fo84TCZ3wyYL9zTa", "28853": "v3q7X4XGkXspyHCB", "28854": "BD3dB7fVD2dvlGwM", "28856": "QwE7uPFSeHScMcz4", "28857": "CM7BYW3F44fvPHe2", "28859": "pRvfSdZHoTs1ES6F", "28860": "BwL4JzKHFJscYTlO", "28861": "08cwzAYpDHeUCHFm", "28862": "jdrpp1KZIfGVkTkv", "28864": "YSwKGJImchI13Fxg", "28866": "tA4uV90dZx3VxLa7", "28868": "rcm52TR3QBCReTxe", "28870": "3TCayelJfuF0L0iy", "28871": "yb8nWd74n3u7Zm3P", "28873": "uYkvYjZEDotAHE9O", "28875": "bbvV99IJzw2kQT6R", "28876": "PYG4vhVxksOYQJdt", "28878": "KZTC0WwWqyeStZD2", "28880": "KXhPo50ptOKVIZeH", "28881": "Rn4UauoqK2HW1yjK", "28882": "6lSojeHIZdLwjHVd", "28884": "ehDcmSgLNMz6mYoe", "28885": "vg2UrbMiMMPyZhds", "28886": "JQT1g01nfT3lHdhH", "28887": "TibT82JLWlRPSuCc", "28888": "Ig02q6KHYgzR2Pfd", "28889": "KyTOqbWe54vDV7jI", "28891": "oO8E9elbOapCgB6t", "28892": "eLAxW1e0si8cF7jj", "28894": "FV0EtTgkyDtRulTv", "28896": "q1FChXgHKQXWQYbp", "28897": "H9XHY6Zl4laSKVVa", "28899": "P0uZg3wQ6fb9Er7d", "28901": "Vmtlbu7FyKKhzIH8", "28902": "u4Do6yGYTI4EJxkd", "28904": "KcPD1WVrpaFxWq4r", "28906": "MNgy7zEIDIRYVJ2k", "28907": "iDWqgFha6Ap1JNyM", "28908": "RdNmObWkViKausX1", "28910": "t11J6CIRxsDO6xJP", "28911": "hPeoIEpoHySH4qjF", "28913": "ur6nERX3v075ttDz", "28915": "nEiRE9Q0CEI77W2v", "28917": "ozSE6Ne7dCj3ivaL", "28919": "YlRJOcLhZftETsZ5", "28920": "2oQP06HkAfFiRwA3", "28921": "tUdRI5fBCyNuw3Ir", "28923": "gk3nWln1T0U8y5ZY", "28925": "mg6TnSAXudBvCJPX", "28926": "u9eaKn9sIaw0IaTa", "28927": "MmvIA6Jr481afxEE", "28928": "FuwZdTIe7mCltjWG", "28929": "jk1C0auQt33rhwbl", "28931": "Ruv30XgurswmElNo", "28933": "2kRnlcgUSHhfOI3h", "28935": "P9JWNO9alOjxF12S", "28936": "6Wy08MyCwK4cacPT", "28938": "Qnym2qS63nIIr6MO", "28939": "iaKwtWDYOROA7h06", "28941": "UjPLhekBjxnYHoaR", "28943": "bCc66uRPkQYI2U07", "28944": "V9HZBD11TZHGsibY", "28946": "eVZdG1cAb89uJhVd", "28948": "dEUXYMMmUjwxpLHT", "28950": "eJ8464rKRYdJi4y0", "28952": "YNwaWpK84SLJXHlo", "28954": "q95VgRcugr6518xt", "28955": "chS7tSE0JVB1bOtn", "28957": "10Qvwlx1x3BTCipW", "28958": "2Wbfgl8xvcDzgIok", "28960": "Jlv0oBetxMsHH21Y", "28686": "KAJtVusKSmQJnBWE", "28687": "GzX9TzzgB5EJl0kv", "28688": "gqLLzqUyFBEyc4kr", "28690": "O7wUqwnU72VDd27X", "28692": "Qzl9tjVRtaDryqYX", "28693": "CkARpbEwPj9bIzBP", "28694": "7jsUxjkupaNtPCqz", "28695": "wpFjRs9tDs4KuFBD", "28696": "nGyjOeHggeIgkSSs", "28961": "hwLAhgxTJFxZgRfF", "28962": "d9hylTJPg57o3EIO", "28964": "P9Q9FXSkaRK1hOKY", "28965": "AqncKTJx9bKJgo7G", "28966": "p3qF7YUGd0KNWGnH", "28967": "oqRVa6wAS71cOvGQ", "28968": "yZ0ANEtcdS95y8D0", "28969": "mCnilIqqsmVhOfCP", "28971": "oqlkNROt1268Tobk", "28973": "dKEi7f4ndl0xiCdo", "28975": "7LJYZ9osj83ixFOs", "28977": "RgJt5kIX8C4C2TYu", "28979": "hSfSil54HbmZQphL", "28980": "LqgWs6rcu24xSajF", "28981": "JezJ3MOYEUpuukv0", "28983": "j8TXCXvURQCnwq2E", "28985": "y39Vfhczfpl0xqKf", "28987": "a5Bec1FwEECf8WqG", "28988": "R9cSaKPI7VQTWVEE", "28990": "COty1HpXD9fd5eIB", "28991": "ORuqsJ6TxQMplnwH", "28993": "SvVNHGFbIdZ8EadO", "28995": "qdduMcr9uzCaNgrC", "28997": "czsQqvh7Qec1tweb", "28999": "xGsOLRfkd7YM8TNR", "29000": "RPq3KM4Tputu6Jmd", "29002": "S3szXa2Zi2QAtk9T", "29004": "6ysMlHgThDE49wF3", "29006": "fYHDyMOgxHDXj6Ul", "29008": "Fegxv7YcuBFVRc4V", "29010": "frwmNVUVVDb2yeRz", "29011": "4sGrhA3lJQQwfDBu", "29013": "Lo5joLHByf6S4jS1", "29014": "R5koyp41aIvYS9AI", "29015": "c1BpJfNRnlCYfkPg", "29017": "4Rx5qYzzIbNwibEV", "29018": "IDoZWXMOvwu6TzGs", "29020": "L2XQdRcarJ8JnPME", "29022": "osS963vWLssNpNws", "29023": "rZIlBBIDNwQNndCr", "29025": "CPhXd7i6t1UTfoxa", "29026": "IPBQ8OyyRRJQ5kWf", "29027": "A9A7caU9RyBsQkXR", "29028": "JxfTRIRd1SM8PINp", "29029": "5rjlhAXnAVw3Dt51", "29031": "dTCaBSbkl2mtXHSw", "29033": "uFSsN75pxt8mdQMz", "29035": "DdG7jvQ9vTSr5VpC", "29036": "bhG4QSfVaaqjtlKe", "29037": "56DOGL5fwmz4OtvO", "29038": "dCvWLaelO15ighoZ", "29040": "ONn0lPswKO9Os7HS", "29041": "eDXWyeotmO0kSrs9", "29043": "ECsk1xXz8QLwCyQh", "29044": "47dF17GxVZMqycaq", "29045": "2843G7neWmiDntHc", "29047": "QCWrsMg4kjhaKQvy", "29048": "ayUcDlIPgCpGHZaY", "29049": "ZWqdpZNH61a9LMZt", "29050": "wKcAC4Rs70OFYSOo", "29052": "LvBKSAkc7WBoi437", "29053": "IWrmyTekc7YO23M9", "29054": "B14pEq01bYrZXImz", "29056": "jnpR1KPG7H6edLxw", "29058": "DXv6FewRYYuKDPQb", "29060": "ZCWg7fE5OakmXdHt", "29061": "QsCfYQ5JaxrGkiLl", "29062": "uzFdx5ToCRMNslNe", "29063": "kZjYbQHy0WvJkcC2", "29064": "RffaN9f318Gcfh5o", "29065": "mKVgstDMIgoGDmgp", "29067": "JMSA7NHoyY7I6spd", "29069": "UVfcSCa6hwPMBLAR", "29070": "txmDHaYDv6nU3b3n", "29072": "Ol6gLpcIBTIyiCty", "29074": "QlAHv7mnI4IgjtaD", "29075": "r42tI9aDNIxtSkXB", "29077": "YC8OOvChjFJaHuOg", "29079": "AYBwigyw8uFPeN9P", "29081": "VOR1yf7q8r5kw1d1", "29083": "0OdPOXHTZx5oYvkO", "29084": "ZAI3AIMBviCLr75I", "29086": "O6a3DYdcqqL8LrJL", "29088": "ryL1fn18hCb4KMvk", "29090": "MDe1KbsSNtgJhlTC", "29091": "1hJVIXNnLu0lUDIi", "29092": "zQnUGH2ygnkIxGVv", "29094": "ERfOv3fM8flOVvJR", "29096": "EWy6zaQ0U7oacvn6", "29097": "JpfSKeKQhEExI2PD", "29099": "Qkw0fXrU62Nf41E4", "29101": "5Jb4qOlflyrndU60", "29102": "jhT487wMpvhJoKr3", "29103": "p2HsnpAL2YsPqbVd", "29104": "ANwNHHgHOt9cy4sF", "29105": "ddsuHlyEUgp3jJVY", "29106": "tzxEzzczIimssQ6v", "29108": "r7uJPSTUuAGLVZRB", "29109": "9cATZDKIdBc6K6qy", "29111": "xB2XylkAEX52wMwc", "29113": "dBLh3j7VAEM92uDl", "29114": "yvJOej36kvtlzDAA", "29116": "bQl0o8yOl0Z3ZwCQ", "29118": "qfIT5ZYwrnkmNTXJ", "29120": "aqwr0zZbJQNxnScL", "29121": "Q3X65vo0EN91hSAO", "29122": "dp0HjiZGaGhwTqGE", "29124": "e0naJG4XrvhAuTiu", "29126": "dPgKxGF9UJI7ASh2", "29127": "YQEpfqeIk9Y5R5rm", "29128": "9xiJPHCn0MdH7rAc", "29130": "iDfCIqtpk3mfNC2D", "29132": "00ZLq1KDLX8Pydd6", "29134": "ec4G8cdndttKXLzQ", "29136": "UrVGROAv8GZ7sjpW", "29137": "dJE4DCqAUFVX6gZR", "29138": "MQ0YVAt8qFiOh0yZ", "29140": "SzaZuOdKXmpVhe3s", "29154": "SRFey7GaiTW4c21p", "29156": "d1vjjMRs0EwNzP8q", "29157": "kytzLT5CBkwxLc96", "29158": "hNEBkacbQotMveCz", "29159": "icY6WZNL0N62zVin", "29161": "WcrBCVNheEMydkY5", "29162": "ILCw0xu5gnQMNuEF", "29164": "tASeMHxGOVLLnchh", "29165": "Gpy1pi2DNixfvljB", "29166": "SfYOtDoXrNOxVf7F", "29167": "4B4aeYcTjaaoSmrX", "29168": "mbN06iV5qa9RAnYd", "29169": "Htf9k60mlW2qrOpP", "29170": "gIoHb9GvvOpG7DAz", "29171": "BWLoOJ2PNne7r5aX", "29172": "npnbP3lkNWxnbsNR", "29173": "9xJ6aBbMYI51AXZl", "29174": "0p5eTESDYNJjZcX4", "29176": "8lKpu05qAG4g3QDU", "29178": "XRzQvqenrj3OlkQe", "29179": "r27JbsuIc0K0m8s0", "29181": "FWC3Ktbu7lvk0rtH", "29182": "476QrgdtX8CVvmsG", "29184": "qPPwOL8TunheCIUl", "29186": "8usYDzo4orNgk9zB", "29188": "mYzFuAVpcCC7kiQc", "29189": "SR57POjpKNIQToyW", "29190": "1kMceMyYZ1lx9CQz", "29191": "1DUGhYdC6aeE5uKR", "29193": "PEpRK5RrMSYJqjpT", "29195": "unAMUl00qxJCBpaC", "29197": "dC3eoRacXgylTuB3", "29199": "NdwrFKgPnBfQmzVV", "29200": "iHNj56WgckePXerJ", "29202": "49gmWBTm2tKTeX0a", "29204": "hi4j7uBis9U2B3kX", "29205": "2Gx3eCbSef0daMQG", "29206": "T4H9fKjud0XRnBjO", "29208": "bSkZY9JtLtfj985g", "29209": "MnKwY6WYVyuTRiBm", "29210": "mG8GgyaY1hHRCmyQ", "29212": "kBKcseEPT2m9GkFA", "29213": "9J7Xd8sy1nBpWHU0", "29214": "CzBR8I5rSI28NKJg", "29215": "OomeumstrctEHCUe", "29216": "v2QcGBxqgzDLJ0mI", "29217": "DfM8yrhJkevzkN9G", "29218": "P7U30bqH1WKmaIcQ", "29220": "C8Ei186F7D2kWWd5", "29222": "bjh9UASMYsM1wIED", "29224": "xuRCuCdINKmFDVVv", "29226": "lonPsrmA4Igv9m9K", "29227": "Ypcyp5dyMIJd9bHZ", "29229": "OkWZxyzhGhIxK47Y", "29231": "UZ2HVHGI597PAp07", "29232": "K1nsWUkdzeACjgcA", "29234": "l9Xps9SV7yxlA3QM", "29235": "lfu9ZOnGYIkIX8oE", "29236": "h18tkGyDs6sLCS6A", "29238": "SiBoHudZEbcANSVJ", "29239": "g80dXwL7joogBOvF", "29240": "LYv3uXGFSreLLVun", "29241": "tx9HFjKpPnzIvFkl", "29242": "X1owaOH7Iy8JQj3S", "29244": "s92YnHzUgxWK0SY7", "29246": "lcVRggEwCerbVmHq", "29247": "W7qH1qMG2MvxGNX3", "29248": "o6LMnyIuYZxiHM4k", "29250": "nvWOJxUuLQBK5u8Z", "29251": "cjrqB3k9PQJDzpaJ", "29252": "n2FSQghxIl3vcM4H", "29253": "Lc93VOv0qImh4qmX", "29255": "6SEosIk6BI1SmtIi", "29257": "tGZoYUBReaCZJKDn", "29258": "oexOpaNQz0Q6xU0U", "29259": "nfsjvUvYCcD9c0Tr", "29261": "EHhtwdmdmfQPjcSr", "29262": "rFUEZbSoAiwz9c3H", "29263": "67K3YFDxIXOHdUdk", "29264": "Cwhvb2hkfJ0aWoGb", "29265": "kA5ZIB0Q13k0bqhc", "29266": "l7DuYohnM0YEnAWx", "29268": "Lo3bzIZLbBwl85Rg", "29270": "GbLdhrBKusEpdkpc", "29272": "E4aitqIZiKVwnCil", "29274": "L5ndNlE7Knna3xYP", "29275": "ctHPn9rn1dwIvxwb", "29276": "sPx7hwx7AaMMNl79", "29278": "TMJ0RZbr3tUk1CzV", "29279": "ZDUS8Ce7kitgfR1r", "29280": "XoCjtpG9c01YzsaM", "29282": "lZTo3H8Bbp8inrTi", "29284": "lT8hlAQ5s45IEVWZ", "29285": "wjWm1VK5MPmUAhxq", "29286": "B6O88et8USKanX8T", "29288": "uizGg3YRWPVB7oMz", "29290": "SWgzPD9QLGmh7kPi", "29291": "ZZiE3PsZblNfrZ4P", "29292": "OOl8q1gnEGeVqb4R", "29294": "D2t0pUP8CaUT2BB1", "29295": "3Hogee86Gm5P7bXS", "29296": "QNCP3ShCfXLgdEbs", "29298": "JcPlNf5lbcv3C4DW", "29300": "bFWvHGZnYqKtLES0", "29301": "XGjg1yx9LtPRXgHn", "29302": "BAYbuJguBLTM7iZF", "29303": "Wk1cfA5e0bMI57DE", "29304": "xrAIIbUE6QpIX79u", "29306": "rmRr7O8w6tLqxIyX", "29307": "Ul6eHYZlU7IKzlfm", "29309": "p3mbEaRhcF1iGmbv", "29311": "mZOMnW4Z8UNo3diy", "29313": "jkXRXM7gDaUKvpUb", "29314": "ztjXEHv3n3AdRsYw", "29315": "nxWajGMlQ7sdagMr", "29316": "jOAvapazrGE5Is5C", "29317": "byB9eB1qGqRuIxNa", "29319": "HWSEzYLP4bZESRdj", "29321": "W8FpR9xeenTngrfv", "29323": "NGDQj0QttBJ0jtPY", "29324": "SrhJPb7hLXrN03gG", "29325": "AL3WCQrvR011OgNN", "29327": "SJy65Orsw4jajEV4", "29328": "uojxeyfbaXsd6Nwo", "29329": "b4uZADgrYzMVbC3X", "29331": "uJiB1JDcVQ8DSfPk", "29332": "OhGLtLEF8ohpSr2K", "29334": "A5lwUbd8FcQqTXWN", "29335": "mq6Dcu4HNrwNOsnV", "29336": "2L8Hme9kEEh7FOAL", "29337": "9D87olupmywDiKyR", "29338": "1CA4dj6ett9jhGKv", "29339": "XAISZw0Sig3YZbnS", "29340": "14kwLy1qENcz2pFb", "29342": "RcHkAOSDs9ghMzJY", "29344": "JmDJ3wG4tSE3fewG", "29345": "81LiDCVYq6vPe663", "29347": "W4nc6rH9ECaeXgRI", "29349": "Ex8LWuhSaBeXUf52", "29351": "Krbq7kKYsb7Mo2xE", "29352": "Fp7Vj9OvdGPtL9E0", "29354": "ZBrY7khPS98iS0Pd", "29355": "jGJuIkS1EjxjbbmP", "29356": "TVrtMANFcApSfKIs", "29358": "gxKOcKp4IQzJ4Hbl", "29360": "6LeDwmHiGRjktjuL", "29362": "Z3QzZOXmsa4x3Igp", "29364": "pDxThjN1JPO1glem", "29366": "SekZry0cgCkpubUw", "29368": "l1UnuAWXW5YyvqXy", "29369": "kjq3tL0D1OpA7gRp", "29370": "fBqYZEtZnKnyn96U", "29372": "pIkxYIJhK9bVvRed", "29373": "tL0b728Ezr5GKbL4", "29374": "6jKCZJJIo8TvzdiY", "29376": "kaOzK6kJyAMhsAGO", "29378": "EbromMbPXt2JuMs6", "29380": "a46EzYoXxGjO6plZ", "29381": "WJ4o6efY3BN9pTvj", "29383": "aIyTRTLSUHE9eU5K", "29384": "ThdF7wHL37veu4sL", "29386": "25ksHoKSVRRRoHJi", "29387": "TVCrIX0rXfnzyMuE", "29388": "x6o5qQaicRQlCueW", "29389": "7phe1Pud5T5WABwC", "29391": "N7U6QufSGjNIx5En", "29393": "QSfKBUpcDYenYRAi", "29395": "RkSkEPNqKNrlvwyZ", "29142": "Nw3KLhdIiNedQR9L", "29143": "CW6rymI3Q20u5K0m", "29144": "YqxYTYUJsps6TILf", "29145": "kIq7QbFkMyOFcdVJ", "29147": "qjnWOJhH2flS3Gr3", "29148": "4zw3b1GqvA06l3JP", "29149": "G4EHXMALUVTuAfQu", "29151": "7CIpDIlTYuvHMEKU", "29152": "z1aKFd2RotweJZjZ"}}