{"C_DATA": ["BtNvZRIN9X1jztsQ", "aerQHvu3w7synV7R"], "enc_code2": ["kG1JCIrJGzzFIwYs", "2UOGASWoxd5ks6Zz"], "enc_code1": ["yqcxihDIYbQSGH5o", "H3eOz49w9fgIm9TG"], "IG_dict": {"10354": "Rl6Rfj8mPkwa232l", "10355": "Y9eZSE13EHOM8eq5", "10357": "XZCgK9c613CDXUKM", "10358": "w7RQywyfafFWEQR0", "10360": "cyBFGrYb4Ve23niA", "10361": "HcD0GtbZWMzZudzk", "10363": "I9u08bje9nV10xzP", "10364": "rItS8RYG0dpr2lYH", "10365": "7c6d1rcMprq8jga3", "10366": "OleVNIObxHebp13P", "10368": "lkVOg8fk7fCQKfjb", "10369": "IT8AGNIM4XGy22I8", "10370": "PzVC5j3RcKSCP1EH", "10371": "ZV0nICCUcebJNpiO", "10372": "yS7BcoGpnPcoisjL", "10374": "i47ZGgHeRb69hHVC", "10375": "6my8LuDHg0OBHMIg", "10376": "scNZW5qPqwTiP3lj", "10378": "Sv1Bfg35zN9SXniC", "10380": "BJa9wyZJoTzQDwHh", "10381": "sF8AXXy4GvRZXeKP", "10382": "JnNCfP3OJevvTNNU", "10384": "Vn2VY6FVNrb4PjTe", "10385": "HGyJn3co3Yu6o2xq", "10387": "vprp9YiaQMuTonms", "10389": "PGw05vbQFZ3DLVnW", "10390": "GAEfw1a1CPq3dAYM", "10392": "laicK7OYj4v4KtPO", "10394": "Rq6KClpW5Xj05rBL", "10395": "IoCuVYEFwrveUtMV", "10396": "s8yNZGoUhwdLt2r8", "10397": "5l7GvvSPvwXQpUC0", "10398": "tyEKPD7PO4CYGTXH", "10400": "yGjNowCohNesZhg3", "10401": "PzwJjXm8YBOjOHwi", "10403": "T2WUcZEX0brmq1Gn", "10405": "CoGalxkksPV3vgZj", "10406": "XlN9NETfGZT3x7e9", "10407": "74PDJoHaXHkJfX1D", "10408": "MnCygK8Hdz48maLm", "10410": "un8MiUQ3idnN7zSZ", "10411": "CJ5eOXwk2eBpj0hJ", "10413": "loDf3AGZssocuv2Y", "10415": "h5LdnWrI4jwrt27O", "10417": "ZT4Pvku61R64Z33u", "10418": "Y8x8ke2B0Mp2aRKV", "10419": "wPiyyagKBnHKWPhd", "10421": "0iAp7rF3Xr9PY6OJ", "10422": "EZLJe8nOBXblDV1t", "10423": "2IYeIYYaKUrdTgga", "10425": "3ZFL044D5tbuamUu", "10426": "xYI2R5bR1woEeFRh", "10427": "x7dOUGFl5Jiq3SKz", "10428": "LQOdxZEzCNMDt99U", "10430": "QCV7fn7QylbaT15q", "10432": "9ZZACFAG3x2P83cR", "10433": "RFxr6zbdSNoFIQx1", "10435": "cIXYAuCeO8D4xnW1", "10436": "hnFs49GPsB7nuGGj", "10438": "Q1IgR5mpgRcobCE5", "10439": "tZOyLsmBBiT6Dncd", "10440": "oKYOo3lPJBrwtUlK", "10441": "eMZwgpw0WO4Qv6dV", "10443": "Xc355iJ1OoUXs23I", "10445": "11lLzY2qYaswNybm", "10447": "EBZgsvbNTj5Tl98j", "10448": "gibgsq4PRRLl8gC6", "10450": "FPmBtOWiq02U85pW", "10451": "QsWWOyHbMJju4dYD", "10453": "ZKEQDLX7vjwU1jv9", "10454": "wbnkbzRMygKcM25I", "10455": "hS1HPbwqKx9g7YSm", "10456": "yPzo9TKFjMANzKEj", "10458": "2TRNMlbGphF6ibbA", "10460": "LQoWn3hKpiPc2QUp", "10461": "gRFprKqL8c9PUSm4", "10462": "L8YhaqlrIsb20nzg", "10463": "thvYsOPqIFqdD1TQ", "10465": "IGovwKj1D2p01Jrt", "10466": "jRt1Qyv6dpmfJL9g", "10468": "1EJeiiCTV0mPZ0cq", "10469": "B5eC72MoNDHKko1t", "10470": "nQrnILB8qyBfcg0t", "10472": "oVYldGVEdwpQQOkF", "10473": "5Bkm1q4MI2Q4H81m", "10474": "sI10ZwGRS2yANkPP", "10476": "0MARmcuQAxi7MUrO", "10478": "NtTuEOa39pZLAmpx", "10480": "YaNlHykreRvzm3nB", "10481": "ytI4wFckZKlPbMow", "10482": "NqEjJvfyOiOPwBkh", "10484": "Xek6E1BBjF2JDeX2", "10485": "SX9Za5tK7LcGwj0B", "10487": "cXgyRdnlCur9OFyr", "10489": "7LfxD8PXsjbMMHkD", "10491": "5inauXpN8UdXkSu2", "10493": "QesvWRu3ZUUDrMjX", "10494": "yD6xNhFsG5L4WUni", "10495": "5Yr7M5KtgbyecQGA", "10496": "jk91lcSylu6JwniO", "10497": "alDer5Bmw8BbJMjo", "10499": "frG38SbsPyW91HNZ", "10501": "V6AlpgGwMaf1LCjx", "10503": "xzj8cM4HmNjJY1jr", "10504": "N0j0BczB2xwezepf", "10506": "DbasXqIFxWstt7j3", "10507": "4eETYIwR5lTMc9q7", "10509": "8JGvIhVQNmgYImJQ", "10511": "QEF9fkiQeiVscc2i", "10513": "6XHbyiMRhLoDxxPt", "10515": "vLC0YHfMIv2GEXEW", "10516": "TXeSSpuoGZ5fLiaX", "10517": "MRoI82ND2f7DuHvY", "10519": "2gwlGZLXhsFiKAYH", "10520": "t9Gk7i1jBjLkPEah", "10521": "8OLk0wbw6KiWWx5o", "10522": "SAZ1F0CfDzfErM3R", "10523": "E3ODgZh9pvWcD0gl", "10524": "EnpeyD0GKkM8ur9m", "10525": "7YfmBhNddtWSwJYO", "10527": "wQBTV1oi4ceBrGxi", "10528": "EMXiYmtzBqY5rS7K", "10530": "dR9a2cH1neLKQHUm", "10532": "8LZkm15knEYTHgqD", "10534": "ZGzzUVM1eJuk8v3x", "10535": "jpdsDVxjtsD6CmWa", "10537": "FZFTKSiEJGud9lyN", "10538": "iZhltOKyEhFWfgm9", "10540": "3JuUBgCvek6X3CcH", "10542": "yzDsChr2MzCdd8uT", "10543": "9BFVnkY9IxrZ64d2", "10545": "wAU8hijdcMkK8DU1", "10547": "znvpBIsGX5x3lyeC", "10548": "FN0cCRwLruW2JvCR", "10549": "MyBaV808WPbBxBzN", "10550": "n1lhS5edo870Gcic", "10552": "4RMcH0ZllXAXFaTG", "10554": "dSpeucirY6pwTWtd", "10556": "nMvz5QZqNmw9ox9t", "10558": "b7aMQyGdeSXXL02I", "10560": "F4BXEKStIQ8jqR1b", "10562": "fQSowFHeimZTrVtd", "10564": "J9EttFtLTKVBCeun", "10566": "IrGFFT8aMxnP9I28", "10568": "EME46WbyFePipfgC", "10570": "y4PbTyWuW47s10kR", "10571": "2XmWyyLYH9TzbRiT", "10572": "c2s89JHcsSjTFpHy", "10573": "eOgRsTtemoTJRdjd", "10574": "obDr44hqV7tvEOPQ", "10575": "ZSkbYfFjl9dY2K8M", "10577": "LILrFkaruEc0Fq46", "10578": "TQ1FFN2XGE9VnNdI", "10579": "7gXypp4e7APjga6x", "10581": "RkSkEPNqKNrlvwyZ", "10583": "QSfKBUpcDYenYRAi", "10585": "N7U6QufSGjNIx5En", "10587": "7phe1Pud5T5WABwC", "10589": "x6o5qQaicRQlCueW", "10590": "25ksHoKSVRRRoHJi", "10591": "ThdF7wHL37veu4sL", "10593": "aIyTRTLSUHE9eU5K", "10594": "WJ4o6efY3BN9pTvj", "10596": "a46EzYoXxGjO6plZ", "10597": "EbromMbPXt2JuMs6", "10599": "kaOzK6kJyAMhsAGO", "10600": "6jKCZJJIo8TvzdiY", "10342": "Eqsn6SkYOjdJ4uCB", "10343": "9sBHp0aUiGWyymKQ", "10344": "R5nUikLFwuYMkl9R", "10345": "0kMv0OslTQ7apmjr", "10347": "mdoDaJ30dXcofgCc", "10348": "H9MN9Lw8tXjTz92i", "10349": "p7npEiAs3SofeUA2", "10350": "ct6JYjOl2Jpnmt9M", "10352": "DjXrUCWE9GFYWwN3", "10615": "TVrtMANFcApSfKIs", "10617": "jGJuIkS1EjxjbbmP", "10619": "ZBrY7khPS98iS0Pd", "10620": "Krbq7kKYsb7Mo2xE", "10621": "Ex8LWuhSaBeXUf52", "10622": "W4nc6rH9ECaeXgRI", "10624": "81LiDCVYq6vPe663", "10625": "JmDJ3wG4tSE3fewG", "10626": "RcHkAOSDs9ghMzJY", "10627": "14kwLy1qENcz2pFb", "10628": "XAISZw0Sig3YZbnS", "10629": "1CA4dj6ett9jhGKv", "10631": "9D87olupmywDiKyR", "10633": "mq6Dcu4HNrwNOsnV", "10634": "A5lwUbd8FcQqTXWN", "10635": "OhGLtLEF8ohpSr2K", "10636": "uJiB1JDcVQ8DSfPk", "10638": "b4uZADgrYzMVbC3X", "10639": "uojxeyfbaXsd6Nwo", "10641": "SJy65Orsw4jajEV4", "10643": "AL3WCQrvR011OgNN", "10645": "SrhJPb7hLXrN03gG", "10647": "NGDQj0QttBJ0jtPY", "10648": "byB9eB1qGqRuIxNa", "10650": "jOAvapazrGE5Is5C", "10651": "nxWajGMlQ7sdagMr", "10652": "ztjXEHv3n3AdRsYw", "10653": "jkXRXM7gDaUKvpUb", "10655": "mZOMnW4Z8UNo3diy", "10656": "p3mbEaRhcF1iGmbv", "10657": "Ul6eHYZlU7IKzlfm", "10658": "rmRr7O8w6tLqxIyX", "10660": "xrAIIbUE6QpIX79u", "10662": "BAYbuJguBLTM7iZF", "10664": "XGjg1yx9LtPRXgHn", "10666": "bFWvHGZnYqKtLES0", "10668": "JcPlNf5lbcv3C4DW", "10670": "QNCP3ShCfXLgdEbs", "10671": "3Hogee86Gm5P7bXS", "10673": "D2t0pUP8CaUT2BB1", "10675": "OOl8q1gnEGeVqb4R", "10676": "ZZiE3PsZblNfrZ4P", "10678": "SWgzPD9QLGmh7kPi", "10679": "B6O88et8USKanX8T", "10681": "wjWm1VK5MPmUAhxq", "10682": "lT8hlAQ5s45IEVWZ", "10683": "lZTo3H8Bbp8inrTi", "10685": "XoCjtpG9c01YzsaM", "10687": "ZDUS8Ce7kitgfR1r", "10688": "TMJ0RZbr3tUk1CzV", "10690": "sPx7hwx7AaMMNl79", "10692": "ctHPn9rn1dwIvxwb", "10693": "L5ndNlE7Knna3xYP", "10695": "GbLdhrBKusEpdkpc", "10697": "Lo3bzIZLbBwl85Rg", "10698": "l7DuYohnM0YEnAWx", "10700": "kA5ZIB0Q13k0bqhc", "10701": "Cwhvb2hkfJ0aWoGb", "10702": "67K3YFDxIXOHdUdk", "10704": "rFUEZbSoAiwz9c3H", "10706": "EHhtwdmdmfQPjcSr", "10707": "nfsjvUvYCcD9c0Tr", "10709": "oexOpaNQz0Q6xU0U", "10711": "6SEosIk6BI1SmtIi", "10713": "Lc93VOv0qImh4qmX", "10715": "n2FSQghxIl3vcM4H", "10716": "cjrqB3k9PQJDzpaJ", "10718": "nvWOJxUuLQBK5u8Z", "10720": "o6LMnyIuYZxiHM4k", "10722": "W7qH1qMG2MvxGNX3", "10724": "lcVRggEwCerbVmHq", "10725": "s92YnHzUgxWK0SY7", "10726": "X1owaOH7Iy8JQj3S", "10727": "LYv3uXGFSreLLVun", "10729": "g80dXwL7joogBOvF", "10730": "SiBoHudZEbcANSVJ", "10731": "h18tkGyDs6sLCS6A", "10733": "lfu9ZOnGYIkIX8oE", "10734": "l9Xps9SV7yxlA3QM", "10735": "K1nsWUkdzeACjgcA", "10737": "UZ2HVHGI597PAp07", "10738": "OkWZxyzhGhIxK47Y", "10739": "Ypcyp5dyMIJd9bHZ", "10740": "xuRCuCdINKmFDVVv", "10741": "bjh9UASMYsM1wIED", "10742": "C8Ei186F7D2kWWd5", "10744": "P7U30bqH1WKmaIcQ", "10745": "DfM8yrhJkevzkN9G", "10747": "v2QcGBxqgzDLJ0mI", "10748": "OomeumstrctEHCUe", "10749": "CzBR8I5rSI28NKJg", "10750": "9J7Xd8sy1nBpWHU0", "10751": "kBKcseEPT2m9GkFA", "10753": "MnKwY6WYVyuTRiBm", "10754": "bSkZY9JtLtfj985g", "10755": "T4H9fKjud0XRnBjO", "10756": "2Gx3eCbSef0daMQG", "10757": "hi4j7uBis9U2B3kX", "10759": "49gmWBTm2tKTeX0a", "10761": "iHNj56WgckePXerJ", "10763": "NdwrFKgPnBfQmzVV", "10765": "dC3eoRacXgylTuB3", "10766": "unAMUl00qxJCBpaC", "10768": "1DUGhYdC6aeE5uKR", "10770": "1kMceMyYZ1lx9CQz", "10772": "SR57POjpKNIQToyW", "10773": "mYzFuAVpcCC7kiQc", "10775": "8usYDzo4orNgk9zB", "10777": "qPPwOL8TunheCIUl", "10779": "476QrgdtX8CVvmsG", "10781": "FWC3Ktbu7lvk0rtH", "10782": "r27JbsuIc0K0m8s0", "10783": "XRzQvqenrj3OlkQe", "10785": "0p5eTESDYNJjZcX4", "10787": "9xJ6aBbMYI51AXZl", "10789": "npnbP3lkNWxnbsNR", "10791": "BWLoOJ2PNne7r5aX", "10792": "gIoHb9GvvOpG7DAz", "10793": "Htf9k60mlW2qrOpP", "10794": "mbN06iV5qa9RAnYd", "10795": "4B4aeYcTjaaoSmrX", "10796": "SfYOtDoXrNOxVf7F", "10797": "Gpy1pi2DNixfvljB", "10799": "WcrBCVNheEMydkY5", "10801": "icY6WZNL0N62zVin", "10802": "hNEBkacbQotMveCz", "10804": "kytzLT5CBkwxLc96", "10806": "d1vjjMRs0EwNzP8q", "10807": "SRFey7GaiTW4c21p", "10809": "z1aKFd2RotweJZjZ", "10810": "7CIpDIlTYuvHMEKU", "10812": "G4EHXMALUVTuAfQu", "10814": "4zw3b1GqvA06l3JP", "10815": "kIq7QbFkMyOFcdVJ", "10816": "YqxYTYUJsps6TILf", "10817": "CW6rymI3Q20u5K0m", "10819": "Nw3KLhdIiNedQR9L", "10820": "SzaZuOdKXmpVhe3s", "10822": "MQ0YVAt8qFiOh0yZ", "10824": "dJE4DCqAUFVX6gZR", "10825": "UrVGROAv8GZ7sjpW", "10826": "ec4G8cdndttKXLzQ", "10828": "00ZLq1KDLX8Pydd6", "10829": "9xiJPHCn0MdH7rAc", "10831": "YQEpfqeIk9Y5R5rm", "10832": "dPgKxGF9UJI7ASh2", "10833": "e0naJG4XrvhAuTiu", "10835": "dp0HjiZGaGhwTqGE", "10836": "Q3X65vo0EN91hSAO", "10837": "aqwr0zZbJQNxnScL", "10839": "qfIT5ZYwrnkmNTXJ", "10841": "bQl0o8yOl0Z3ZwCQ", "10843": "yvJOej36kvtlzDAA", "10845": "xB2XylkAEX52wMwc", "10846": "9cATZDKIdBc6K6qy", "10847": "r7uJPSTUuAGLVZRB", "10849": "tzxEzzczIimssQ6v", "10851": "ddsuHlyEUgp3jJVY", "10853": "ANwNHHgHOt9cy4sF", "10854": "p2HsnpAL2YsPqbVd", "10855": "jhT487wMpvhJoKr3", "10856": "5Jb4qOlflyrndU60", "10858": "Qkw0fXrU62Nf41E4", "10859": "EWy6zaQ0U7oacvn6", "10860": "ERfOv3fM8flOVvJR", "10862": "zQnUGH2ygnkIxGVv", "10864": "1hJVIXNnLu0lUDIi", "10602": "tL0b728Ezr5GKbL4", "10603": "pIkxYIJhK9bVvRed", "10605": "kjq3tL0D1OpA7gRp", "10606": "l1UnuAWXW5YyvqXy", "10607": "SekZry0cgCkpubUw", "10608": "pDxThjN1JPO1glem", "10610": "Z3QzZOXmsa4x3Igp", "10611": "6LeDwmHiGRjktjuL", "10613": "gxKOcKp4IQzJ4Hbl", "10915": "bhG4QSfVaaqjtlKe", "10917": "DdG7jvQ9vTSr5VpC", "10918": "uFSsN75pxt8mdQMz", "10920": "5rjlhAXnAVw3Dt51", "10921": "JxfTRIRd1SM8PINp", "10922": "A9A7caU9RyBsQkXR", "10924": "IPBQ8OyyRRJQ5kWf", "10925": "CPhXd7i6t1UTfoxa", "10926": "rZIlBBIDNwQNndCr", "10928": "osS963vWLssNpNws", "10929": "L2XQdRcarJ8JnPME", "10930": "IDoZWXMOvwu6TzGs", "10932": "4Rx5qYzzIbNwibEV", "10934": "R5koyp41aIvYS9AI", "10936": "Lo5joLHByf6S4jS1", "10938": "4sGrhA3lJQQwfDBu", "10940": "frwmNVUVVDb2yeRz", "10942": "Fegxv7YcuBFVRc4V", "10944": "fYHDyMOgxHDXj6Ul", "10946": "6ysMlHgThDE49wF3", "10948": "S3szXa2Zi2QAtk9T", "10950": "RPq3KM4Tputu6Jmd", "10952": "xGsOLRfkd7YM8TNR", "10954": "SvVNHGFbIdZ8EadO", "10956": "ORuqsJ6TxQMplnwH", "10957": "COty1HpXD9fd5eIB", "10958": "R9cSaKPI7VQTWVEE", "10960": "a5Bec1FwEECf8WqG", "10961": "y39Vfhczfpl0xqKf", "10962": "j8TXCXvURQCnwq2E", "10964": "JezJ3MOYEUpuukv0", "10966": "LqgWs6rcu24xSajF", "10967": "hSfSil54HbmZQphL", "10969": "7LJYZ9osj83ixFOs", "10971": "dKEi7f4ndl0xiCdo", "10973": "oqlkNROt1268Tobk", "10975": "mCnilIqqsmVhOfCP", "10977": "yZ0ANEtcdS95y8D0", "10978": "oqRVa6wAS71cOvGQ", "10980": "p3qF7YUGd0KNWGnH", "10982": "AqncKTJx9bKJgo7G", "10984": "P9Q9FXSkaRK1hOKY", "10986": "d9hylTJPg57o3EIO", "10988": "Jlv0oBetxMsHH21Y", "10990": "2Wbfgl8xvcDzgIok", "10991": "10Qvwlx1x3BTCipW", "10992": "chS7tSE0JVB1bOtn", "10994": "q95VgRcugr6518xt", "10995": "YNwaWpK84SLJXHlo", "10997": "eJ8464rKRYdJi4y0", "10999": "dEUXYMMmUjwxpLHT", "11000": "eVZdG1cAb89uJhVd", "11001": "V9HZBD11TZHGsibY", "11002": "UjPLhekBjxnYHoaR", "11004": "iaKwtWDYOROA7h06", "11006": "Qnym2qS63nIIr6MO", "11007": "6Wy08MyCwK4cacPT", "11009": "P9JWNO9alOjxF12S", "11011": "2kRnlcgUSHhfOI3h", "11012": "Ruv30XgurswmElNo", "11013": "jk1C0auQt33rhwbl", "11015": "FuwZdTIe7mCltjWG", "11016": "MmvIA6Jr481afxEE", "11017": "mg6TnSAXudBvCJPX", "11019": "gk3nWln1T0U8y5ZY", "11021": "tUdRI5fBCyNuw3Ir", "11023": "2oQP06HkAfFiRwA3", "11025": "YlRJOcLhZftETsZ5", "11027": "ozSE6Ne7dCj3ivaL", "11028": "nEiRE9Q0CEI77W2v", "11029": "ur6nERX3v075ttDz", "11031": "hPeoIEpoHySH4qjF", "11033": "t11J6CIRxsDO6xJP", "11035": "iDWqgFha6Ap1JNyM", "11036": "MNgy7zEIDIRYVJ2k", "11038": "KcPD1WVrpaFxWq4r", "11039": "u4Do6yGYTI4EJxkd", "11041": "Vmtlbu7FyKKhzIH8", "11042": "P0uZg3wQ6fb9Er7d", "11043": "H9XHY6Zl4laSKVVa", "11044": "q1FChXgHKQXWQYbp", "11045": "FV0EtTgkyDtRulTv", "11046": "eLAxW1e0si8cF7jj", "11047": "KyTOqbWe54vDV7jI", "11048": "Ig02q6KHYgzR2Pfd", "11050": "TibT82JLWlRPSuCc", "11052": "JQT1g01nfT3lHdhH", "11053": "vg2UrbMiMMPyZhds", "11054": "ehDcmSgLNMz6mYoe", "11056": "6lSojeHIZdLwjHVd", "11058": "Rn4UauoqK2HW1yjK", "11060": "KXhPo50ptOKVIZeH", "11062": "KZTC0WwWqyeStZD2", "11063": "bbvV99IJzw2kQT6R", "11065": "uYkvYjZEDotAHE9O", "11066": "yb8nWd74n3u7Zm3P", "11068": "3TCayelJfuF0L0iy", "11070": "rcm52TR3QBCReTxe", "11071": "tA4uV90dZx3VxLa7", "11073": "YSwKGJImchI13Fxg", "11075": "jdrpp1KZIfGVkTkv", "11077": "08cwzAYpDHeUCHFm", "11078": "BwL4JzKHFJscYTlO", "11080": "CM7BYW3F44fvPHe2", "11081": "QwE7uPFSeHScMcz4", "11082": "BD3dB7fVD2dvlGwM", "11084": "v3q7X4XGkXspyHCB", "11085": "fo84TCZ3wyYL9zTa", "11086": "LtI5DJQaZlG0Q060", "11087": "SUe1tHRIGZ3eGgFP", "11088": "EYkVZQRGDiAOHIXX", "11089": "UkMJ2R6IzS6UJe8b", "11091": "OU3V8vdYTC0hJG0R", "11093": "Jwyhh4UqLDxefhcT", "11094": "vuJjTvER8J7TzRz9", "11095": "zD0VAcarbPWWKnWa", "11096": "eiAdWvHXti4fjM5R", "11098": "axPoBSoxerca0IRN", "11100": "33ENz4N0FD7bNzwt", "11101": "jqwpNl87ApWZg2mq", "11103": "LkaYzJ2se2IDQLNE", "11105": "C10fvKJ2CnDZklSq", "11106": "hx4Htu5eN8H4XyMb", "11107": "sNiP6qJ89SDCjYep", "11109": "W8X9Oo4ESPDZWxge", "11110": "x225oMNAyEQdQuoa", "11112": "sSvu9b1R2By2OtN8", "11113": "TgRLSVqx5JIjQPB3", "11114": "jfAnxxDEVJMsZtWi", "11116": "7n6QYxbgc2jbPbgy", "11117": "7TKnZzrHQF5MigQT", "11119": "TgMO1eontpeUJKB4", "11121": "R2bCnwdSc2nu1O8n", "11123": "ESnW6fIzypDGAH5b", "11124": "fdZmhNwuqqxg3F3e", "11125": "a3ow5EE8O3B7Lvx4", "11126": "Wjf7ZLF1E93b7OHt", "11128": "6fVsBVHuNbcbURCT", "11129": "T8cnXenWfsNydKqS", "11130": "88FnprhuZz3NCD1q", "11132": "VeFzsAm1nE4KG6EI", "11134": "q1oLuLVN3qIlSPSF", "11135": "Kf2zkFlfrsUMLhjW", "10865": "MDe1KbsSNtgJhlTC", "10866": "ryL1fn18hCb4KMvk", "10868": "O6a3DYdcqqL8LrJL", "10870": "ZAI3AIMBviCLr75I", "10872": "0OdPOXHTZx5oYvkO", "10874": "VOR1yf7q8r5kw1d1", "10876": "YC8OOvChjFJaHuOg", "10878": "r42tI9aDNIxtSkXB", "10879": "QlAHv7mnI4IgjtaD", "10881": "Ol6gLpcIBTIyiCty", "10882": "txmDHaYDv6nU3b3n", "10883": "UVfcSCa6hwPMBLAR", "10885": "JMSA7NHoyY7I6spd", "10886": "mKVgstDMIgoGDmgp", "10887": "RffaN9f318Gcfh5o", "10888": "kZjYbQHy0WvJkcC2", "10890": "QsCfYQ5JaxrGkiLl", "10891": "ZCWg7fE5OakmXdHt", "10893": "DXv6FewRYYuKDPQb", "10894": "jnpR1KPG7H6edLxw", "10896": "B14pEq01bYrZXImz", "10898": "IWrmyTekc7YO23M9", "10900": "LvBKSAkc7WBoi437", "10901": "wKcAC4Rs70OFYSOo", "10902": "ZWqdpZNH61a9LMZt", "10904": "ayUcDlIPgCpGHZaY", "10905": "2843G7neWmiDntHc", "10907": "47dF17GxVZMqycaq", "10908": "ECsk1xXz8QLwCyQh", "10909": "eDXWyeotmO0kSrs9", "10910": "ONn0lPswKO9Os7HS", "10911": "dCvWLaelO15ighoZ", "10913": "56DOGL5fwmz4OtvO", "11149": "FszJp9LqbwG2C2qX", "11151": "MGnMkop427OjdB7a", "11152": "DHAXpdbSDO2LojTJ", "11153": "me3WdlaQ4tpAjnLc", "11154": "feV5ufsWy4FtfODt", "11155": "7dnHl7glrU8EKIcS", "11156": "GMETb1dy2EjMUVYZ", "11157": "kEJ4XPSfGmq3t1x7", "11159": "ZR8Jho2KNaYwCIGb", "11160": "mUTuLI5eZHK8k8XE", "11162": "nZHRmVirYlUvTsD6", "11164": "M3v3TWxbOSA4dnXj", "11166": "vtNvl44kAAbhfSm4", "11137": "v9UnitYhQ0OxQ0kA", "11139": "41EuFRn1RqO0NdG3", "11140": "wOzCua8hLfLaPUFq", "11141": "8IsPG8bygFiQThZO", "11143": "nIBfgaQYGzduZyWH", "11144": "vlv3eqWNAOO81GCw", "11145": "8PG3e4ZPtHm83qZ1", "11147": "Pb43lYcwND8ALiX8", "11148": "QUZRP2X08GYUQmVH", "9679": "dJ0W34hCmXhVj31X", "9680": "NvTVI0gRUBsdFmPs", "9681": "9VGT0riTxKKfqvVh", "9683": "LuHU8BVZgKxnF1JZ", "9685": "5uhOCvSSGi7XkYB8", "9686": "v7QXjlDHorm2O0Hb", "9688": "wsKqtRmlB8qxBChB", "9690": "gYF6Ilxyx2oxCThK", "9691": "OAntOkPx802P7M12", "9693": "xHbaaPsu0Ac83mM2", "9694": "hvdvJ1zh8VbiSKEk", "9695": "35JiqPEVR3E6gYDQ", "9696": "sneGA2rp3M1BN773", "9697": "5rKUKu5JpcX18f4q", "9699": "uW9TVWOIs7DBKnhB", "9701": "XfSHve9n8M37xhYd", "9702": "CI937Qw95h3P4Eox", "9704": "LLFHRxXqmPMdDP6d", "9706": "T0ihACruHGtwpG43", "9708": "lPSDoSXYFQBrBNbw", "9709": "mDFzoAIfrHfuSOvs", "9711": "rUM3edVnEdXdRzas", "9713": "y2bwSL5SUx5mJorA", "9715": "J8SSeOntSQr6nWTH", "9716": "JVuGBem9tkVKy1Uh", "9717": "RRDcOylGpEZKxU4G", "9719": "Yy0b857IqCSri0WF", "9721": "ScmtSxXycUeCDTs6", "9722": "jtQzXvrbWcOyAFqR", "9723": "Xys0qA4PyTTP2xsX", "9725": "nGyjOeHggeIgkSSs", "9727": "wpFjRs9tDs4KuFBD", "9728": "7jsUxjkupaNtPCqz", "9730": "CkARpbEwPj9bIzBP", "9731": "Qzl9tjVRtaDryqYX", "9732": "O7wUqwnU72VDd27X", "9734": "gqLLzqUyFBEyc4kr", "9736": "GzX9TzzgB5EJl0kv", "9738": "IUSxKjxrNQ2OHGuf", "9740": "Xt3GDyQJ9dSk02zh", "9741": "tcCpycv5DsMdQrqA", "9743": "duO4pfwHuIrg45HE", "9745": "S1Y4aFILwaubCS2x", "9746": "jAC32g1GwHazzg9L", "9747": "zXYMEerUPv3ZZQZk", "9749": "Cxdi6CQ8JhbpkXJV", "9750": "EBDXSGR7nBkO7gIU", "9752": "i87M1Da7jN3WjVq3", "9753": "aoMYfdtbNryiH7qv", "9755": "PwbvR8bH2IFLAVY2", "9757": "fEN9gK2eFZnceQBq", "9758": "7XQGCyxgULvnJLF7", "9760": "j8g7dj5SNP63HPBq", "9761": "GWNAfOIBTegrHYNM", "9762": "tBfDQvysB0IAYrKq", "9764": "dafhyzV1ZR1oS4kq", "9765": "aLYJ9dTjsu0TS3Tf", "9767": "xC02He2is1lZPxAz", "9768": "Jxd6oZgz1ryTlRab", "9769": "TGYCHa24AJ3NG6Mf", "9771": "XRuDtmqwCxaIz0Tj", "9772": "Y1OJZ4uhP0nRGaW6", "9773": "p9rqW9AZSiRR6yPN", "9774": "LEJhtBQA3vksnqQh", "9775": "Df0WBjZMWblyI7eH", "9776": "cnFJZVE1HA9zYB9z", "9778": "M35gAB2nFpOUvE9b", "9780": "iW982ZUd4T5mY9VY", "9781": "eoE3yfqsqBfCOF3T", "9782": "bZif7z2gH1hjg4x5", "9784": "PiHc2uITovlIouDo", "9786": "jlagOAiYTy7hrYIU", "9787": "1Q2zuBru3B0xtzZL", "9788": "5x9pboO3NN44skkX", "9790": "i8QqORuQsOCPsaaP", "9791": "DGA0J0JN5YOsHn71", "9793": "4mL4l8vEiziedl1v", "9795": "C9J57qJn05CPPBrx", "9796": "5ZBjfHBmw36rrFD1", "9797": "yXP8AbEQAQqPgpVB", "9799": "z2HybH0w1ejxZSyx", "9800": "FfELFObgNBqCXOXH", "9802": "kvso2Fmrni5biQOI", "9803": "FwXsx5qCP2ItIAL4", "9804": "5kKqrG5kVU7tyjUh", "9806": "scpBsdf1g3HNciSq", "9807": "HjVCFmB43IPttda4", "9808": "HuCFGRTD63muTthp", "9809": "8A9qSKSHrgUhZphU", "9810": "8RYBXtRDmyR5wO5T", "9812": "irf6PB4Gl4zpmm0S", "9813": "3kJQJHffDD9pRnBQ", "9814": "bmtffdo09e6lw10y", "9815": "F1XK6jlL3vTQjOiP", "9816": "nqHWVtH3hO0ZVm12", "9817": "lEMABEV7JDIAyWHv", "9819": "31wKDVGyxZNMEP5H", "9821": "3iHRJ1a53Ame69vR", "9822": "jTBQBr8Ra1MApPxc", "9823": "QU4dxXsY7fFecOkW", "9824": "c47czgCiAdiNLePd", "9826": "o3bVIfK8qgIlQKp9", "9827": "WQkscSgSsFNDpPyx", "9828": "e2mbmKrZpGvZb0v0", "9829": "XVN3MUBjvKO6BVm6", "9831": "214ZvA66E6HqI26o", "9832": "LhYiLsYh9qqGp6ET", "9834": "TXk3e4BTj2yosTBG", "9836": "V5zZsTHd0yqyCN0u", "9838": "Kccc0y7QALRIHU98", "9839": "eYF7PIwsS6PsKRPN", "9840": "TxrUMTYDsdPI0nQ4", "9841": "JgFcUIRaXeKiXiVi", "9843": "HNUFMwBJrlwzRGoX", "9844": "wp1cGLxdBzCrg7V1", "9845": "THh6DRVWuqMUkn43", "9847": "5rSXkR7bCCVYeMRv", "9849": "AfunqnSLVVtu47wV", "9851": "P2tFR6yJHVFszXe8", "9853": "7F9qGrc9Qm1j7dEt", "9855": "15i7WCkfYqx9T1M5", "9857": "EVd8foGnSfeeH3v5", "9858": "bmGrNe2Nces5jwxy", "9859": "CYrODTV3YGVwnFdg", "9861": "BjhVzgTcW7OL7CFL", "9862": "IxOKOPAxOdQzx17x", "9863": "vPimQPFG4xgl1p9N", "9865": "52ua8y32xmzEPQP1", "9866": "jPAQzmJleO2BzpKU", "9868": "IJrIW0K1ZB0qDcjk", "9869": "CbR0ilsI7lKKnEk7", "9870": "f0RyOEgYUTcL1qcF", "9872": "6cyewkVndJbWx3vM", "9874": "pXP0bf5h0uvEauca", "9875": "fvGJRFRXFWhL1wed", "9876": "gagnC8YET4I7te73", "9877": "6mNagliKRtj8CioC", "9879": "L07rqXH6yt3gmiUt", "9881": "x9jqX5rCXR2Qk9Ej", "9882": "PWs4YRUCffmAN1sy", "9884": "Y2FBuSfZ8lsUb48d", "9886": "K7ImhqkfyPAUbfc8", "9888": "zanZsmMbBdEBsKWb", "9890": "4jA9CqdHnuKnFNMq", "9891": "yCNnhEl2moNe9VrK", "9914": "znkheykGjSHmMzfx", "9915": "KQM36xX8E52tb05I", "9917": "MMrKUYpElMWCgMEd", "9919": "lethzihZsE76etll", "9921": "r9riRtxsBNiaQOpp", "9922": "QaqyDd9JkG2Db46o", "9924": "DGArk7jIqKVHNlqG", "9925": "LgutUca9Xcvsii80", "9926": "0FLcYeEF528vUtYv", "9928": "FIm3fHAxGsdIl8pE", "9929": "5xuW6ywJPnSOViYt", "9931": "3sA78EzT0dI46mbF", "9932": "zfkYPBz2TRQRqCmb", "9933": "bFN7jo2xvUnkQj5M", "9935": "rS2AONWahApjTbY7", "9937": "yP35NaW3Bp3oDeum", "9938": "TtTYzK7bkGynx4hQ", "9939": "utyiheZSj6nFvMSB", "9941": "Yj3Q2DgLcH7k3xgX", "9942": "VXImPy3UHN3hiyy8", "9943": "ITpLXn2YfUgSmaJG", "9944": "UC0uDFgqHkEOnKg9", "9945": "tpoWAXIZvHA7rnKf", "9946": "jvbfVQmUTDOOZ6ff", "9948": "ARZnQRV3q4S5LJhx", "9950": "lacUn4JUctRhBD9E", "9951": "Zs0MOEoWs758tLhu", "9953": "wqmDx9080YKwa7DY", "9955": "KUd5bdEqzzLrd47J", "9957": "FNl5Jd22lYNaqCi5", "9958": "NqWS0F5S8fCixPDO", "9960": "sqH6qp1erZkDh3VD", "9962": "57Vl4ZVd4Jo2f4m8", "9963": "Wk13YyT0kzeBw51j", "9964": "LG69HvkzMpP2s4nL", "9965": "wtYHSRkHAKChv9JQ", "9967": "VY9iB7Lsix6VYBVq", "9968": "ysv9nUHnKCeLGmuB", "9970": "XznZ8z47PpQ0yQzA", "9972": "QJRq9BmZ2WFpUkkM", "9974": "RPtdkjSCvt6PgUxv", "9975": "31RBKdpRsjjHsTV6", "9976": "57EuEU1pi8DnyulC", "9978": "Hfg5AvzqPpzZqApa", "9980": "PXoFduoxCQdlulSd", "9982": "oXnncWINzqDwybOX", "9984": "ry9P6pkEcL1lD4aw", "9985": "1HCxW0nOrV4sTlSk", "9986": "uTUKWarqMMwelAkS", "9988": "9AgoaqYPhMPQtiis", "9990": "VkDmiOtmimOWgzlR", "9991": "gOsYvgSa7sce2WiW", "9993": "Br4PLRz6uvNQuhLQ", "9995": "NdqhjV2BuCnYcsfx", "9997": "Inp6T1elcQV3ph1L", "9999": "PctWhME0kQb7ZBge", "10001": "uMVf4A42balgVxBb", "10003": "NMzm2XtWZ6VbG3Es", "10004": "EkbxdZjZSXwhGnon", "10005": "7PXOAkqMBAP2aatK", "10007": "x1wIvaHppuNezCFY", "10008": "yjBfJcoxA70BTbtL", "10010": "Ha1sF40LlLqlttxl", "10012": "fejDqZJg2zyx6y08", "10014": "5husYBEFjd8qEV2h", "10015": "Wt1D1Xmvd6RGkSaO", "10016": "DXwMauwGaVVIgkCG", "10017": "td0wPrJMwt0VO40X", "10018": "tmAH116dOGsOatcE", "10019": "QcLHWuN7WGzfHIZf", "10020": "DjMVf3F9s8hgtamV", "10022": "lRIrPIWWXVvwAdHp", "10023": "zaAZHZiCJvuZpQ0E", "10025": "yhcWD2kmRSc4v6Ay", "10027": "oYDtHzYGZuIHrojO", "10029": "1LCw0eugd5yg5Z8z", "10030": "4TaqfCA3Hd5MWh6y", "10031": "jYxXFTWAl2qdYHHn", "10033": "WMCfUXIcSxO8CTAp", "10034": "PgCoTMYkFY6Ab9Qw", "10035": "tY88DMvmnPkeoMai", "10036": "Tm0sF92nuE35beUx", "10038": "UR232GeLoTozOwSG", "10039": "rB1oM6Z823bTo4tJ", "10041": "JJwXFRU8lgMLASEd", "10043": "aI8Lzb2tcaYhJUj8", "10044": "ML1geW0kBCUtVXld", "10045": "tiEC71thwa0WVQrU", "10047": "ZyYfQgmYEqsKH0IQ", "10048": "WVoIwZOT3RSG3n93", "10049": "jCTfPB4Lt44ygFQk", "10051": "hKZtqp9lZCwDuKoN", "10052": "L57NdcjnXfhYTxDT", "10053": "CmeOe5OEo9jl6fIy", "10054": "sZiyLhz2FsakS2M7", "10055": "CQWcmbLYYKzMh4ul", "10057": "pjobUJuuzwhmGQD3", "10058": "2cslxwGAjzKGNK5S", "10060": "FhL0c2rg9AUOtaf7", "10062": "LihCqT3hlippcYb6", "10063": "Vc1tjbgsyvHvC2lv", "10064": "hCuZjjxZ4yoUcfLK", "10065": "y4qpif6hZJwIssRy", "10067": "Qc3PWQ0vvAby55E7", "10069": "g2hij5R3M6uRAcDO", "10071": "9xFLWzkd0yNR2c7b", "10072": "7AocP2TgemCNWzou", "10073": "aClWTUS2isExH1KT", "10075": "bMqRV4nkiiEqqLK7", "10076": "FYyK7HBkaLhcspog", "9892": "6OYdhJAG9Pd3exXG", "9893": "Dh2W0RJ5y1EnfR30", "9894": "nu0KNXZnovgqqxLW", "9896": "8Q5yzFIftSBcxwXb", "9897": "j83ptuoDfEusX0x0", "9898": "Z2nA34k4vZUs9YHo", "9899": "sz1YE7moEByEsyYu", "9900": "jYtL7Z7C0HKbQSzI", "9901": "FD9QLE4bzdMA3cGG", "9902": "PkYdswKQGRxLVG0b", "9904": "oS0w8GC7q0pEWpKU", "9905": "lYRcpE2G7vkxaCIb", "9907": "JSqWWbUhyf6Q9Rw6", "9908": "vmoX341szA2ZgIEz", "9909": "mvjUP8siF41K3SOF", "9911": "hfddtGLSGZjcQTGR", "9912": "gpIoztJQEwMRfEy4", "10091": "JVpLyrXmGaL6OR57", "10093": "ul1YLtMzRftm31Tn", "10095": "n2QHIn4FDiiuGble", "10096": "sZGttZeV3RbaNf6W", "10098": "C08Bm0vvRQ9mdO3m", "10100": "7L5dhs4JqBknD4wL", "10102": "ZyuiDiepVDUOsnRK", "10103": "dOUT3I4EkVO0ccFH", "10104": "HovBZ8qGj5MPSPru", "10105": "6FhO564dvr8Z0Ya1", "10107": "N9wVpTYWol5XcckL", "10109": "tMEuO9wvV6AoPfpt", "10110": "GvppZbTaihIzVROh", "10111": "13f3IomW8BKFpsc7", "10113": "0yuqwe49URZeNC7V", "10115": "Xdv5F3EYhKstcRFw", "10117": "6EDSTzk9wGt1lg0b", "10118": "tfP4WugO8f7StOPW", "10119": "j4JOVyJM2uftpLor", "10120": "JfOutQHPGLrEDA05", "10121": "DmAFUN0bLMCBGTKC", "10122": "wfRRLigCuHZVKnuw", "10124": "Cm32S3GLBtfzL5q5", "10126": "ideewz04V1ESRfr8", "10127": "9F7oKXbYNkLPWjtq", "10128": "eO5ceGjsYrh0f3yJ", "10130": "wxC0GvN1vFnJ1kK3", "10131": "mH9qS8lpUKnQy3tq", "10132": "0xHvzaY55byhbUTv", "10133": "ulIYHicIUmJuBccI", "10135": "YLGDguxqJovnXQgy", "10137": "hgT4dAJer1a64cV4", "10138": "at2i9N2Tm32dFm5W", "10140": "2KGaZKv1aDjjNHLP", "10142": "SAoM7flxDDCMYhCL", "10144": "khKEkQfs1POovGvL", "10146": "AvGXfoznfRoo3C0Y", "10148": "DXpQAKpXUaTphvOz", "10149": "adb7IgOikWLaQq1r", "10151": "5mIrrZCyk5CN0Fh1", "10153": "99p7GqHhvdYoFzny", "10154": "5U72BMCuE9htRpFt", "10155": "aSFkeP0MW2EzBkLk", "10156": "LQSTThA7a35kYgQ1", "10157": "6dMpO9kai0VM7htd", "10158": "CwEw7ogWGNpe33O6", "10159": "kHYPKuLvSTULGn0T", "10160": "HuSIHlPQofNyRq7F", "10161": "QTDRuf86sCnSQkfi", "10162": "1SjlpTpHzyDEBxKC", "10164": "YcPYvP7C7bdGKop9", "10165": "fNOPCx5iz1gaNQ0o", "10166": "ZyHsFIsjFb8bUOyv", "10168": "Y6vqIEpW6vzsw44c", "10170": "JIrs4iJEY1f2QZYV", "10172": "VE8YKMXQFB7OLEhO", "10173": "r6BDi7UNuMfPRIhi", "10174": "hjzsXdMTs4sRhW2F", "10175": "aMHyz4rUzuS7oE6J", "10177": "8IBF3pD0M0VMc4PQ", "10178": "1u4JjO9R5bWILU53", "10179": "mb81HIz0v43cZEAk", "10180": "0G2sdGowjTF7HANG", "10181": "4hvnxg5aHrjalpus", "10182": "2l7aW8WATIziFh5f", "10183": "HMtGRTF62ENMYN18", "10184": "YgFhSO8zNHrkkGXJ", "10185": "RFFHmGt5ABP3cH5i", "10186": "OEniRjhlDYJkgPKd", "10187": "eF2AG8jMy6lIoxaF", "10188": "2aW3MQsm983fvOWC", "10190": "ukg9utcO3o2REfDw", "10191": "Co0Av5l98cc2dhFB", "10193": "TiLd7Y3SzwO9fuF3", "10195": "DmqQ9mrrB5orH9H6", "10197": "ITKziVwPDOEwWExs", "10199": "GufP17wJWNXROfnc", "10201": "tg9ElfobRjPpCyjo", "10203": "nYSE7e0aLWoQoe1C", "10204": "7RCT4kfSJY4aRQdY", "10206": "W8FpR9xeenTngrfv", "10208": "tASeMHxGOVLLnchh", "10209": "czsQqvh7Qec1tweb", "10211": "P1VFd7CeNEuUXpwx", "10212": "ZYZ7XcNyM3nIWjD9", "10214": "cKENG5uaG2EyyeoC", "10216": "sABIypkIRl2JPiAa", "10218": "BsSBULHRdqwwl7XD", "10219": "0KCXmug2fz6HD4QN", "10220": "XceDx15OPrKZkqjP", "10222": "rLMy5MsV3hathDfH", "10224": "lQXfLcsHjgyGjlIP", "10225": "eOVeuYGYvGRcOF88", "10227": "WUzVjtbo4mtjPKcA", "10228": "scGHMikoQh6rH84B", "10230": "ih7mGW7kjKSemAVg", "10232": "XchHv7EcoXD3m84z", "10234": "IpWoOiBA5VWGfg62", "10236": "8JVwTnsuTQB1jcGv", "10237": "lIgvqGAGRZ7WNlh4", "10239": "CDzPahk16pFtpOV9", "10241": "rLCFPTQUOMYTkcRX", "10243": "HEEq7tubUPWBUHxx", "10245": "TVCrIX0rXfnzyMuE", "10246": "fBqYZEtZnKnyn96U", "10248": "Fp7Vj9OvdGPtL9E0", "10250": "2L8Hme9kEEh7FOAL", "10252": "HWSEzYLP4bZESRdj", "10253": "Wk1cfA5e0bMI57DE", "10255": "uizGg3YRWPVB7oMz", "10257": "E4aitqIZiKVwnCil", "10258": "tGZoYUBReaCZJKDn", "10259": "tx9HFjKpPnzIvFkl", "10261": "lonPsrmA4Igv9m9K", "10263": "mG8GgyaY1hHRCmyQ", "10264": "PEpRK5RrMSYJqjpT", "10265": "8lKpu05qAG4g3QDU", "10267": "ILCw0xu5gnQMNuEF", "10268": "qjnWOJhH2flS3Gr3", "10270": "iDfCIqtpk3mfNC2D", "10272": "dBLh3j7VAEM92uDl", "10273": "JpfSKeKQhEExI2PD", "10275": "AYBwigyw8uFPeN9P", "10276": "uzFdx5ToCRMNslNe", "10277": "QCWrsMg4kjhaKQvy", "10278": "dTCaBSbkl2mtXHSw", "10280": "c1BpJfNRnlCYfkPg", "10281": "qdduMcr9uzCaNgrC", "10282": "RgJt5kIX8C4C2TYu", "10283": "hwLAhgxTJFxZgRfF", "10285": "bCc66uRPkQYI2U07", "10286": "u9eaKn9sIaw0IaTa", "10287": "RdNmObWkViKausX1", "10289": "oO8E9elbOapCgB6t", "10291": "PYG4vhVxksOYQJdt", "10293": "pRvfSdZHoTs1ES6F", "10294": "Y7FP9kzTmvgdwbRp", "10295": "EXbtA1ToTvnCVAQw", "10296": "MfL2OSzTxQ6F6aYK", "10297": "ADw4wJev0Mqdc3DG", "10298": "zAWEjOep8YPVThBc", "10299": "ZQ3nEYBXEUnMFBFQ", "10301": "e6P2YFclioBqC5dK", "10303": "flOjAovmKffy2p53", "10304": "SQZ6Go9wKnOb3DNt", "10305": "KAJtVusKSmQJnBWE", "10307": "UTQZS0QwBRrrLxUj", "10308": "zvSTvQVRpKMoAHn6", "10309": "cOkp08LreOBnN5Nt", "10310": "85ZqxzkIABIRrwH2", "10312": "i0cqI7AQ8OeRbEpz", "10314": "WrZsB5bL1bGa3DVZ", "10316": "3aIrVBmOa1mMj5TI", "10317": "cW4NUWdUCWe8lirD", "10319": "tbwtgF2sERpiBIQn", "10321": "kawyHFy7cGql4o7G", "10323": "oc5TnuznJ8jzmpcC", "10325": "DNShdQNlh996Gu32", "10327": "oTsA3jNLl79kQm2t", "10328": "2MOsf5GGGOT7rOIG", "10329": "8S3LObD87hUJ42G6", "10330": "WXgNRdADPc9hx06Z", "10331": "P7ozXkrTvwKdNcOY", "10333": "9dYI1Q6eMxTGWmK8", "10335": "ll8JkzR6zw65LqV1", "10336": "IiDPlhtFynWUcRLZ", "10337": "wp16EyRhkYcqtrFo", "10338": "0YKVFf0bIlZQM7YA", "10340": "rfpb9ZsMkjkLYA7T", "10078": "di1vL42H0nqbIBsL", "10079": "6poiqEx0OjNcCqNt", "10080": "c24FSWSCpiQXCy2N", "10081": "1XVIrCtO5Szo9aZC", "10082": "WMDvgfiga5qKEUGx", "10084": "sesu48Z5vqcQjz2G", "10086": "MAvEmfrabjU6E9G6", "10088": "lspVwJkyy7tezhFx", "10089": "VNhz9TAfU6tMpKMc", "9280": "cW4NUWdUCWe8lirD", "9281": "P2tFR6yJHVFszXe8", "9283": "7F9qGrc9Qm1j7dEt", "9284": "15i7WCkfYqx9T1M5", "9286": "EVd8foGnSfeeH3v5", "9288": "bmGrNe2Nces5jwxy", "9289": "CYrODTV3YGVwnFdg", "9291": "BjhVzgTcW7OL7CFL", "9292": "IxOKOPAxOdQzx17x", "9293": "vPimQPFG4xgl1p9N", "9295": "52ua8y32xmzEPQP1", "9296": "tbwtgF2sERpiBIQn", "9297": "jPAQzmJleO2BzpKU", "9299": "IJrIW0K1ZB0qDcjk", "9301": "CbR0ilsI7lKKnEk7", "9303": "f0RyOEgYUTcL1qcF", "9305": "6cyewkVndJbWx3vM", "9307": "pXP0bf5h0uvEauca", "9309": "fvGJRFRXFWhL1wed", "9310": "gagnC8YET4I7te73", "9311": "6mNagliKRtj8CioC", "9312": "L07rqXH6yt3gmiUt", "9314": "kawyHFy7cGql4o7G", "9315": "x9jqX5rCXR2Qk9Ej", "9316": "PWs4YRUCffmAN1sy", "9318": "Y2FBuSfZ8lsUb48d", "9320": "K7ImhqkfyPAUbfc8", "9321": "zanZsmMbBdEBsKWb", "9322": "4jA9CqdHnuKnFNMq", "9324": "yCNnhEl2moNe9VrK", "9326": "6OYdhJAG9Pd3exXG", "9327": "Dh2W0RJ5y1EnfR30", "9329": "nu0KNXZnovgqqxLW", "9331": "oc5TnuznJ8jzmpcC", "9332": "8Q5yzFIftSBcxwXb", "9334": "j83ptuoDfEusX0x0", "9336": "Z2nA34k4vZUs9YHo", "9338": "sz1YE7moEByEsyYu", "9340": "jYtL7Z7C0HKbQSzI", "9342": "FD9QLE4bzdMA3cGG", "9343": "PkYdswKQGRxLVG0b", "9345": "oS0w8GC7q0pEWpKU", "9347": "lYRcpE2G7vkxaCIb", "9348": "JSqWWbUhyf6Q9Rw6", "9349": "cKENG5uaG2EyyeoC", "9350": "DNShdQNlh996Gu32", "9351": "vmoX341szA2ZgIEz", "9353": "mvjUP8siF41K3SOF", "9355": "hfddtGLSGZjcQTGR", "9356": "gpIoztJQEwMRfEy4", "9358": "znkheykGjSHmMzfx", "9360": "KQM36xX8E52tb05I", "9361": "MMrKUYpElMWCgMEd", "9362": "lethzihZsE76etll", "9364": "r9riRtxsBNiaQOpp", "9366": "QaqyDd9JkG2Db46o", "9367": "oTsA3jNLl79kQm2t", "9369": "DGArk7jIqKVHNlqG", "9370": "LgutUca9Xcvsii80", "9372": "0FLcYeEF528vUtYv", "9374": "FIm3fHAxGsdIl8pE", "9375": "5xuW6ywJPnSOViYt", "9376": "3sA78EzT0dI46mbF", "9377": "zfkYPBz2TRQRqCmb", "9378": "bFN7jo2xvUnkQj5M", "9379": "rS2AONWahApjTbY7", "9381": "yP35NaW3Bp3oDeum", "9382": "2MOsf5GGGOT7rOIG", "9384": "TtTYzK7bkGynx4hQ", "9386": "utyiheZSj6nFvMSB", "9387": "Yj3Q2DgLcH7k3xgX", "9388": "VXImPy3UHN3hiyy8", "9390": "ITpLXn2YfUgSmaJG", "9391": "UC0uDFgqHkEOnKg9", "9392": "tpoWAXIZvHA7rnKf", "9394": "jvbfVQmUTDOOZ6ff", "9396": "ARZnQRV3q4S5LJhx", "9397": "lacUn4JUctRhBD9E", "9398": "8S3LObD87hUJ42G6", "9399": "Zs0MOEoWs758tLhu", "9400": "wqmDx9080YKwa7DY", "9402": "KUd5bdEqzzLrd47J", "9404": "FNl5Jd22lYNaqCi5", "9405": "NqWS0F5S8fCixPDO", "9406": "sqH6qp1erZkDh3VD", "9407": "57Vl4ZVd4Jo2f4m8", "9408": "Wk13YyT0kzeBw51j", "9409": "LG69HvkzMpP2s4nL", "9410": "wtYHSRkHAKChv9JQ", "9412": "WXgNRdADPc9hx06Z", "9413": "VY9iB7Lsix6VYBVq", "9415": "ysv9nUHnKCeLGmuB", "9416": "XznZ8z47PpQ0yQzA", "9417": "QJRq9BmZ2WFpUkkM", "9419": "RPtdkjSCvt6PgUxv", "9421": "31RBKdpRsjjHsTV6", "9422": "57EuEU1pi8DnyulC", "9424": "Hfg5AvzqPpzZqApa", "9425": "PXoFduoxCQdlulSd", "9427": "oXnncWINzqDwybOX", "9428": "P7ozXkrTvwKdNcOY", "9430": "ry9P6pkEcL1lD4aw", "9431": "1HCxW0nOrV4sTlSk", "9432": "uTUKWarqMMwelAkS", "9434": "9AgoaqYPhMPQtiis", "9435": "VkDmiOtmimOWgzlR", "9436": "gOsYvgSa7sce2WiW", "9438": "Br4PLRz6uvNQuhLQ", "9439": "NdqhjV2BuCnYcsfx", "9441": "Inp6T1elcQV3ph1L", "9443": "PctWhME0kQb7ZBge", "9444": "9dYI1Q6eMxTGWmK8", "9445": "uMVf4A42balgVxBb", "9446": "NMzm2XtWZ6VbG3Es", "9447": "EkbxdZjZSXwhGnon", "9448": "7PXOAkqMBAP2aatK", "9449": "x1wIvaHppuNezCFY", "9450": "yjBfJcoxA70BTbtL", "9451": "Ha1sF40LlLqlttxl", "9453": "fejDqZJg2zyx6y08", "9454": "5husYBEFjd8qEV2h", "9455": "Wt1D1Xmvd6RGkSaO", "9457": "ll8JkzR6zw65LqV1", "9459": "DXwMauwGaVVIgkCG", "9461": "td0wPrJMwt0VO40X", "9462": "tmAH116dOGsOatcE", "9464": "QcLHWuN7WGzfHIZf", "9466": "DjMVf3F9s8hgtamV", "9468": "lRIrPIWWXVvwAdHp", "9470": "zaAZHZiCJvuZpQ0E", "9472": "yhcWD2kmRSc4v6Ay", "9474": "oYDtHzYGZuIHrojO", "9476": "1LCw0eugd5yg5Z8z", "9477": "IiDPlhtFynWUcRLZ", "9478": "4TaqfCA3Hd5MWh6y", "9480": "jYxXFTWAl2qdYHHn", "9482": "WMCfUXIcSxO8CTAp", "9483": "PgCoTMYkFY6Ab9Qw", "9484": "tY88DMvmnPkeoMai", "9486": "Tm0sF92nuE35beUx", "9487": "UR232GeLoTozOwSG", "9488": "rB1oM6Z823bTo4tJ", "9490": "JJwXFRU8lgMLASEd", "9492": "aI8Lzb2tcaYhJUj8", "9494": "wp16EyRhkYcqtrFo", "9495": "ML1geW0kBCUtVXld", "9496": "tiEC71thwa0WVQrU", "9497": "ZyYfQgmYEqsKH0IQ", "9498": "WVoIwZOT3RSG3n93", "9500": "jCTfPB4Lt44ygFQk", "9501": "hKZtqp9lZCwDuKoN", "9502": "L57NdcjnXfhYTxDT", "9504": "CmeOe5OEo9jl6fIy", "9505": "sZiyLhz2FsakS2M7", "9507": "CQWcmbLYYKzMh4ul", "9509": "sABIypkIRl2JPiAa", "9511": "0YKVFf0bIlZQM7YA", "9512": "pjobUJuuzwhmGQD3", "9513": "2cslxwGAjzKGNK5S", "9514": "FhL0c2rg9AUOtaf7", "9516": "LihCqT3hlippcYb6", "9517": "Vc1tjbgsyvHvC2lv", "9519": "hCuZjjxZ4yoUcfLK", "9520": "y4qpif6hZJwIssRy", "9522": "Qc3PWQ0vvAby55E7", "9523": "g2hij5R3M6uRAcDO", "9524": "9xFLWzkd0yNR2c7b", "9525": "rfpb9ZsMkjkLYA7T", "9266": "Kccc0y7QALRIHU98", "9268": "eYF7PIwsS6PsKRPN", "9270": "TxrUMTYDsdPI0nQ4", "9272": "JgFcUIRaXeKiXiVi", "9274": "HNUFMwBJrlwzRGoX", "9275": "wp1cGLxdBzCrg7V1", "9276": "THh6DRVWuqMUkn43", "9278": "5rSXkR7bCCVYeMRv", "9279": "AfunqnSLVVtu47wV", "9527": "7AocP2TgemCNWzou", "9528": "aClWTUS2isExH1KT", "9529": "bMqRV4nkiiEqqLK7", "9531": "FYyK7HBkaLhcspog", "9629": "ZyHsFIsjFb8bUOyv", "9630": "Y6vqIEpW6vzsw44c", "9632": "JIrs4iJEY1f2QZYV", "9634": "VE8YKMXQFB7OLEhO", "9635": "r6BDi7UNuMfPRIhi", "9637": "p7npEiAs3SofeUA2", "9639": "hjzsXdMTs4sRhW2F", "9640": "aMHyz4rUzuS7oE6J", "9641": "8IBF3pD0M0VMc4PQ", "9642": "1u4JjO9R5bWILU53", "9644": "mb81HIz0v43cZEAk", "9645": "0G2sdGowjTF7HANG", "9646": "4hvnxg5aHrjalpus", "9647": "2l7aW8WATIziFh5f", "9648": "HMtGRTF62ENMYN18", "9650": "YgFhSO8zNHrkkGXJ", "9652": "ct6JYjOl2Jpnmt9M", "9653": "RFFHmGt5ABP3cH5i", "9655": "OEniRjhlDYJkgPKd", "9657": "eF2AG8jMy6lIoxaF", "9659": "2aW3MQsm983fvOWC", "9660": "ukg9utcO3o2REfDw", "9662": "Co0Av5l98cc2dhFB", "9664": "TiLd7Y3SzwO9fuF3", "9665": "DmqQ9mrrB5orH9H6", "9666": "ITKziVwPDOEwWExs", "9667": "GufP17wJWNXROfnc", "9532": "di1vL42H0nqbIBsL", "9534": "6poiqEx0OjNcCqNt", "9535": "c24FSWSCpiQXCy2N", "9537": "1XVIrCtO5Szo9aZC", "9538": "WMDvgfiga5qKEUGx", "9540": "sesu48Z5vqcQjz2G", "9541": "Eqsn6SkYOjdJ4uCB", "9542": "MAvEmfrabjU6E9G6", "9544": "lspVwJkyy7tezhFx", "9546": "VNhz9TAfU6tMpKMc", "9547": "JVpLyrXmGaL6OR57", "9548": "ul1YLtMzRftm31Tn", "9550": "n2QHIn4FDiiuGble", "9551": "sZGttZeV3RbaNf6W", "9553": "C08Bm0vvRQ9mdO3m", "9555": "7L5dhs4JqBknD4wL", "9556": "ZyuiDiepVDUOsnRK", "9558": "9sBHp0aUiGWyymKQ", "9559": "dOUT3I4EkVO0ccFH", "9561": "HovBZ8qGj5MPSPru", "9563": "6FhO564dvr8Z0Ya1", "9565": "N9wVpTYWol5XcckL", "9566": "tMEuO9wvV6AoPfpt", "9567": "GvppZbTaihIzVROh", "9568": "13f3IomW8BKFpsc7", "9570": "0yuqwe49URZeNC7V", "9572": "Xdv5F3EYhKstcRFw", "9574": "6EDSTzk9wGt1lg0b", "9575": "R5nUikLFwuYMkl9R", "9576": "tfP4WugO8f7StOPW", "9577": "j4JOVyJM2uftpLor", "9579": "JfOutQHPGLrEDA05", "9580": "DmAFUN0bLMCBGTKC", "9581": "wfRRLigCuHZVKnuw", "9582": "Cm32S3GLBtfzL5q5", "9584": "ideewz04V1ESRfr8", "9585": "9F7oKXbYNkLPWjtq", "9587": "eO5ceGjsYrh0f3yJ", "9588": "wxC0GvN1vFnJ1kK3", "9590": "0kMv0OslTQ7apmjr", "9591": "mH9qS8lpUKnQy3tq", "9592": "0xHvzaY55byhbUTv", "9594": "ulIYHicIUmJuBccI", "9596": "YLGDguxqJovnXQgy", "9598": "hgT4dAJer1a64cV4", "9599": "at2i9N2Tm32dFm5W", "9600": "2KGaZKv1aDjjNHLP", "9601": "SAoM7flxDDCMYhCL", "9603": "khKEkQfs1POovGvL", "9605": "AvGXfoznfRoo3C0Y", "9607": "mdoDaJ30dXcofgCc", "9608": "DXpQAKpXUaTphvOz", "9609": "adb7IgOikWLaQq1r", "9610": "5mIrrZCyk5CN0Fh1", "9612": "99p7GqHhvdYoFzny", "9614": "5U72BMCuE9htRpFt", "9615": "aSFkeP0MW2EzBkLk", "9617": "LQSTThA7a35kYgQ1", "9619": "6dMpO9kai0VM7htd", "9621": "CwEw7ogWGNpe33O6", "9622": "kHYPKuLvSTULGn0T", "9623": "H9MN9Lw8tXjTz92i", "9624": "HuSIHlPQofNyRq7F", "9625": "QTDRuf86sCnSQkfi", "9626": "1SjlpTpHzyDEBxKC", "9627": "YcPYvP7C7bdGKop9", "9628": "fNOPCx5iz1gaNQ0o", "8214": "I9u08bje9nV10xzP", "8215": "rItS8RYG0dpr2lYH", "8217": "7c6d1rcMprq8jga3", "8219": "0KCXmug2fz6HD4QN", "8221": "OleVNIObxHebp13P", "8223": "lkVOg8fk7fCQKfjb", "8224": "IT8AGNIM4XGy22I8", "8226": "PzVC5j3RcKSCP1EH", "8228": "ZV0nICCUcebJNpiO", "8229": "yS7BcoGpnPcoisjL", "8230": "i47ZGgHeRb69hHVC", "8232": "6my8LuDHg0OBHMIg", "8234": "scNZW5qPqwTiP3lj", "8235": "Sv1Bfg35zN9SXniC", "8236": "XceDx15OPrKZkqjP", "8237": "BJa9wyZJoTzQDwHh", "8239": "sF8AXXy4GvRZXeKP", "8240": "JnNCfP3OJevvTNNU", "8241": "Vn2VY6FVNrb4PjTe", "8242": "HGyJn3co3Yu6o2xq", "8244": "vprp9YiaQMuTonms", "8245": "PGw05vbQFZ3DLVnW", "8246": "GAEfw1a1CPq3dAYM", "8247": "laicK7OYj4v4KtPO", "8249": "Rq6KClpW5Xj05rBL", "8251": "rLMy5MsV3hathDfH", "8253": "IoCuVYEFwrveUtMV", "8254": "s8yNZGoUhwdLt2r8", "8256": "5l7GvvSPvwXQpUC0", "8257": "tyEKPD7PO4CYGTXH", "8258": "yGjNowCohNesZhg3", "8259": "PzwJjXm8YBOjOHwi", "8261": "T2WUcZEX0brmq1Gn", "8263": "CoGalxkksPV3vgZj", "8264": "XlN9NETfGZT3x7e9", "8266": "74PDJoHaXHkJfX1D", "8267": "lQXfLcsHjgyGjlIP", "8269": "MnCygK8Hdz48maLm", "8271": "un8MiUQ3idnN7zSZ", "8272": "CJ5eOXwk2eBpj0hJ", "8274": "loDf3AGZssocuv2Y", "8275": "h5LdnWrI4jwrt27O", "8277": "ZT4Pvku61R64Z33u", "8278": "Y8x8ke2B0Mp2aRKV", "8279": "wPiyyagKBnHKWPhd", "8281": "0iAp7rF3Xr9PY6OJ", "8283": "EZLJe8nOBXblDV1t", "8285": "eOVeuYGYvGRcOF88", "8286": "2IYeIYYaKUrdTgga", "8287": "3ZFL044D5tbuamUu", "8289": "xYI2R5bR1woEeFRh", "8290": "x7dOUGFl5Jiq3SKz", "8292": "LQOdxZEzCNMDt99U", "8294": "QCV7fn7QylbaT15q", "8296": "9ZZACFAG3x2P83cR", "8298": "RFxr6zbdSNoFIQx1", "8299": "cIXYAuCeO8D4xnW1", "8301": "hnFs49GPsB7nuGGj", "8302": "WUzVjtbo4mtjPKcA", "8304": "Q1IgR5mpgRcobCE5", "8305": "tZOyLsmBBiT6Dncd", "8306": "oKYOo3lPJBrwtUlK", "8308": "eMZwgpw0WO4Qv6dV", "8309": "Xc355iJ1OoUXs23I", "8311": "11lLzY2qYaswNybm", "8312": "EBZgsvbNTj5Tl98j", "8313": "gibgsq4PRRLl8gC6", "8315": "FPmBtOWiq02U85pW", "8317": "QsWWOyHbMJju4dYD", "8319": "scGHMikoQh6rH84B", "8321": "ZKEQDLX7vjwU1jv9", "8322": "wbnkbzRMygKcM25I", "8323": "hS1HPbwqKx9g7YSm", "8325": "yPzo9TKFjMANzKEj", "8326": "2TRNMlbGphF6ibbA", "8328": "LQoWn3hKpiPc2QUp", "8330": "gRFprKqL8c9PUSm4", "8331": "L8YhaqlrIsb20nzg", "8333": "thvYsOPqIFqdD1TQ", "8335": "IGovwKj1D2p01Jrt", "8336": "ih7mGW7kjKSemAVg", "8337": "jRt1Qyv6dpmfJL9g", "8339": "1EJeiiCTV0mPZ0cq", "8340": "B5eC72MoNDHKko1t", "8341": "nQrnILB8qyBfcg0t", "8343": "oVYldGVEdwpQQOkF", "8344": "5Bkm1q4MI2Q4H81m", "8345": "sI10ZwGRS2yANkPP", "8346": "0MARmcuQAxi7MUrO", "8347": "NtTuEOa39pZLAmpx", "8348": "YaNlHykreRvzm3nB", "8349": "XchHv7EcoXD3m84z", "8350": "ytI4wFckZKlPbMow", "8351": "NqEjJvfyOiOPwBkh", "8353": "Xek6E1BBjF2JDeX2", "8354": "SX9Za5tK7LcGwj0B", "8356": "cXgyRdnlCur9OFyr", "8358": "7LfxD8PXsjbMMHkD", "8359": "5inauXpN8UdXkSu2", "8360": "QesvWRu3ZUUDrMjX", "8361": "yD6xNhFsG5L4WUni", "8362": "5Yr7M5KtgbyecQGA", "8364": "7RCT4kfSJY4aRQdY", "8366": "IpWoOiBA5VWGfg62", "8367": "jk91lcSylu6JwniO", "8369": "alDer5Bmw8BbJMjo", "8370": "frG38SbsPyW91HNZ", "8371": "V6AlpgGwMaf1LCjx", "8373": "xzj8cM4HmNjJY1jr", "8374": "N0j0BczB2xwezepf", "8376": "DbasXqIFxWstt7j3", "8378": "4eETYIwR5lTMc9q7", "8380": "8JGvIhVQNmgYImJQ", "8382": "QEF9fkiQeiVscc2i", "8384": "8JVwTnsuTQB1jcGv", "8385": "6XHbyiMRhLoDxxPt", "8386": "vLC0YHfMIv2GEXEW", "8388": "TXeSSpuoGZ5fLiaX", "8389": "MRoI82ND2f7DuHvY", "8391": "2gwlGZLXhsFiKAYH", "8393": "t9Gk7i1jBjLkPEah", "8395": "8OLk0wbw6KiWWx5o", "8396": "SAZ1F0CfDzfErM3R", "8397": "E3ODgZh9pvWcD0gl", "8398": "EnpeyD0GKkM8ur9m", "8399": "lIgvqGAGRZ7WNlh4", "8401": "7YfmBhNddtWSwJYO", "8402": "wQBTV1oi4ceBrGxi", "8404": "EMXiYmtzBqY5rS7K", "8405": "dR9a2cH1neLKQHUm", "8407": "8LZkm15knEYTHgqD", "8409": "ZGzzUVM1eJuk8v3x", "8410": "jpdsDVxjtsD6CmWa", "8412": "FZFTKSiEJGud9lyN", "8414": "iZhltOKyEhFWfgm9", "8415": "3JuUBgCvek6X3CcH", "8417": "CDzPahk16pFtpOV9", "8418": "yzDsChr2MzCdd8uT", "8419": "9BFVnkY9IxrZ64d2", "8420": "wAU8hijdcMkK8DU1", "8421": "znvpBIsGX5x3lyeC", "8422": "FN0cCRwLruW2JvCR", "8424": "MyBaV808WPbBxBzN", "8425": "n1lhS5edo870Gcic", "8426": "4RMcH0ZllXAXFaTG", "8427": "dSpeucirY6pwTWtd", "8429": "nMvz5QZqNmw9ox9t", "8430": "rLCFPTQUOMYTkcRX", "8431": "b7aMQyGdeSXXL02I", "8432": "F4BXEKStIQ8jqR1b", "8433": "fQSowFHeimZTrVtd", "8434": "J9EttFtLTKVBCeun", "8435": "IrGFFT8aMxnP9I28", "8436": "EME46WbyFePipfgC", "8437": "y4PbTyWuW47s10kR", "8438": "2XmWyyLYH9TzbRiT", "8439": "c2s89JHcsSjTFpHy", "8440": "eOgRsTtemoTJRdjd", "8442": "HEEq7tubUPWBUHxx", "8444": "obDr44hqV7tvEOPQ", "8446": "ZSkbYfFjl9dY2K8M", "8447": "LILrFkaruEc0Fq46", "8448": "TQ1FFN2XGE9VnNdI", "8449": "7gXypp4e7APjga6x", "8450": "RkSkEPNqKNrlvwyZ", "8452": "QSfKBUpcDYenYRAi", "8454": "N7U6QufSGjNIx5En", "8456": "7phe1Pud5T5WABwC", "8457": "x6o5qQaicRQlCueW", "8458": "TVCrIX0rXfnzyMuE", "8459": "25ksHoKSVRRRoHJi", "8199": "nYSE7e0aLWoQoe1C", "8201": "BsSBULHRdqwwl7XD", "8203": "DjXrUCWE9GFYWwN3", "8204": "tg9ElfobRjPpCyjo", "8206": "Rl6Rfj8mPkwa232l", "8207": "Y9eZSE13EHOM8eq5", "8209": "XZCgK9c613CDXUKM", "8210": "w7RQywyfafFWEQR0", "8212": "cyBFGrYb4Ve23niA", "8213": "HcD0GtbZWMzZudzk", "8472": "kjq3tL0D1OpA7gRp", "8473": "l1UnuAWXW5YyvqXy", "8474": "SekZry0cgCkpubUw", "8476": "pDxThjN1JPO1glem", "8477": "Z3QzZOXmsa4x3Igp", "8478": "6LeDwmHiGRjktjuL", "8480": "gxKOcKp4IQzJ4Hbl", "8481": "TVrtMANFcApSfKIs", "8482": "jGJuIkS1EjxjbbmP", "8483": "ZBrY7khPS98iS0Pd", "8485": "Fp7Vj9OvdGPtL9E0", "8487": "Krbq7kKYsb7Mo2xE", "8489": "Ex8LWuhSaBeXUf52", "8490": "W4nc6rH9ECaeXgRI", "8491": "81LiDCVYq6vPe663", "8493": "JmDJ3wG4tSE3fewG", "8494": "RcHkAOSDs9ghMzJY", "8495": "14kwLy1qENcz2pFb", "8496": "XAISZw0Sig3YZbnS", "8498": "1CA4dj6ett9jhGKv", "8499": "9D87olupmywDiKyR", "8500": "2L8Hme9kEEh7FOAL", "8501": "mq6Dcu4HNrwNOsnV", "8502": "A5lwUbd8FcQqTXWN", "8503": "OhGLtLEF8ohpSr2K", "8505": "uJiB1JDcVQ8DSfPk", "8506": "b4uZADgrYzMVbC3X", "8507": "uojxeyfbaXsd6Nwo", "8509": "SJy65Orsw4jajEV4", "8510": "AL3WCQrvR011OgNN", "8512": "SrhJPb7hLXrN03gG", "8514": "NGDQj0QttBJ0jtPY", "8515": "W8FpR9xeenTngrfv", "8516": "HWSEzYLP4bZESRdj", "8518": "byB9eB1qGqRuIxNa", "8519": "jOAvapazrGE5Is5C", "8520": "nxWajGMlQ7sdagMr", "8522": "ztjXEHv3n3AdRsYw", "8523": "jkXRXM7gDaUKvpUb", "8524": "mZOMnW4Z8UNo3diy", "8526": "p3mbEaRhcF1iGmbv", "8528": "Ul6eHYZlU7IKzlfm", "8530": "rmRr7O8w6tLqxIyX", "8532": "xrAIIbUE6QpIX79u", "8534": "Wk1cfA5e0bMI57DE", "8535": "BAYbuJguBLTM7iZF", "8537": "XGjg1yx9LtPRXgHn", "8539": "bFWvHGZnYqKtLES0", "8540": "JcPlNf5lbcv3C4DW", "8542": "QNCP3ShCfXLgdEbs", "8544": "3Hogee86Gm5P7bXS", "8545": "D2t0pUP8CaUT2BB1", "8547": "OOl8q1gnEGeVqb4R", "8548": "ZZiE3PsZblNfrZ4P", "8549": "SWgzPD9QLGmh7kPi", "8551": "uizGg3YRWPVB7oMz", "8552": "B6O88et8USKanX8T", "8554": "wjWm1VK5MPmUAhxq", "8555": "lT8hlAQ5s45IEVWZ", "8557": "lZTo3H8Bbp8inrTi", "8558": "XoCjtpG9c01YzsaM", "8559": "ZDUS8Ce7kitgfR1r", "8561": "TMJ0RZbr3tUk1CzV", "8563": "sPx7hwx7AaMMNl79", "8564": "ctHPn9rn1dwIvxwb", "8565": "L5ndNlE7Knna3xYP", "8567": "E4aitqIZiKVwnCil", "8569": "GbLdhrBKusEpdkpc", "8570": "Lo3bzIZLbBwl85Rg", "8572": "l7DuYohnM0YEnAWx", "8574": "kA5ZIB0Q13k0bqhc", "8575": "Cwhvb2hkfJ0aWoGb", "8577": "67K3YFDxIXOHdUdk", "8579": "rFUEZbSoAiwz9c3H", "8581": "EHhtwdmdmfQPjcSr", "8582": "nfsjvUvYCcD9c0Tr", "8584": "oexOpaNQz0Q6xU0U", "8585": "tGZoYUBReaCZJKDn", "8587": "6SEosIk6BI1SmtIi", "8589": "Lc93VOv0qImh4qmX", "8591": "n2FSQghxIl3vcM4H", "8592": "cjrqB3k9PQJDzpaJ", "8594": "nvWOJxUuLQBK5u8Z", "8595": "o6LMnyIuYZxiHM4k", "8596": "W7qH1qMG2MvxGNX3", "8597": "lcVRggEwCerbVmHq", "8598": "s92YnHzUgxWK0SY7", "8599": "X1owaOH7Iy8JQj3S", "8601": "tx9HFjKpPnzIvFkl", "8603": "LYv3uXGFSreLLVun", "8604": "g80dXwL7joogBOvF", "8606": "SiBoHudZEbcANSVJ", "8607": "h18tkGyDs6sLCS6A", "8608": "lfu9ZOnGYIkIX8oE", "8610": "l9Xps9SV7yxlA3QM", "8611": "K1nsWUkdzeACjgcA", "8612": "UZ2HVHGI597PAp07", "8614": "OkWZxyzhGhIxK47Y", "8616": "Ypcyp5dyMIJd9bHZ", "8617": "lonPsrmA4Igv9m9K", "8618": "xuRCuCdINKmFDVVv", "8619": "bjh9UASMYsM1wIED", "8621": "C8Ei186F7D2kWWd5", "8623": "P7U30bqH1WKmaIcQ", "8625": "DfM8yrhJkevzkN9G", "8626": "v2QcGBxqgzDLJ0mI", "8627": "OomeumstrctEHCUe", "8628": "CzBR8I5rSI28NKJg", "8629": "9J7Xd8sy1nBpWHU0", "8630": "kBKcseEPT2m9GkFA", "8631": "mG8GgyaY1hHRCmyQ", "8633": "MnKwY6WYVyuTRiBm", "8635": "bSkZY9JtLtfj985g", "8637": "T4H9fKjud0XRnBjO", "8639": "2Gx3eCbSef0daMQG", "8641": "hi4j7uBis9U2B3kX", "8642": "49gmWBTm2tKTeX0a", "8644": "iHNj56WgckePXerJ", "8646": "NdwrFKgPnBfQmzVV", "8647": "dC3eoRacXgylTuB3", "8648": "unAMUl00qxJCBpaC", "8649": "PEpRK5RrMSYJqjpT", "8651": "1DUGhYdC6aeE5uKR", "8652": "1kMceMyYZ1lx9CQz", "8654": "SR57POjpKNIQToyW", "8655": "mYzFuAVpcCC7kiQc", "8656": "8usYDzo4orNgk9zB", "8657": "qPPwOL8TunheCIUl", "8658": "476QrgdtX8CVvmsG", "8659": "FWC3Ktbu7lvk0rtH", "8660": "r27JbsuIc0K0m8s0", "8662": "XRzQvqenrj3OlkQe", "8664": "8lKpu05qAG4g3QDU", "8666": "0p5eTESDYNJjZcX4", "8667": "9xJ6aBbMYI51AXZl", "8668": "npnbP3lkNWxnbsNR", "8669": "BWLoOJ2PNne7r5aX", "8671": "gIoHb9GvvOpG7DAz", "8673": "Htf9k60mlW2qrOpP", "8674": "mbN06iV5qa9RAnYd", "8675": "4B4aeYcTjaaoSmrX", "8676": "SfYOtDoXrNOxVf7F", "8677": "Gpy1pi2DNixfvljB", "8679": "tASeMHxGOVLLnchh", "8680": "ILCw0xu5gnQMNuEF", "8682": "WcrBCVNheEMydkY5", "8684": "icY6WZNL0N62zVin", "8686": "hNEBkacbQotMveCz", "8687": "kytzLT5CBkwxLc96", "8689": "d1vjjMRs0EwNzP8q", "8690": "SRFey7GaiTW4c21p", "8691": "z1aKFd2RotweJZjZ", "8693": "7CIpDIlTYuvHMEKU", "8695": "G4EHXMALUVTuAfQu", "8697": "4zw3b1GqvA06l3JP", "8699": "qjnWOJhH2flS3Gr3", "8701": "kIq7QbFkMyOFcdVJ", "8702": "YqxYTYUJsps6TILf", "8704": "CW6rymI3Q20u5K0m", "8705": "Nw3KLhdIiNedQR9L", "8707": "SzaZuOdKXmpVhe3s", "8708": "MQ0YVAt8qFiOh0yZ", "8709": "dJE4DCqAUFVX6gZR", "8711": "UrVGROAv8GZ7sjpW", "8713": "ec4G8cdndttKXLzQ", "8714": "00ZLq1KDLX8Pydd6", "8715": "iDfCIqtpk3mfNC2D", "8716": "9xiJPHCn0MdH7rAc", "8718": "YQEpfqeIk9Y5R5rm", "8720": "dPgKxGF9UJI7ASh2", "8721": "e0naJG4XrvhAuTiu", "8460": "ThdF7wHL37veu4sL", "8461": "aIyTRTLSUHE9eU5K", "8462": "WJ4o6efY3BN9pTvj", "8463": "a46EzYoXxGjO6plZ", "8465": "EbromMbPXt2JuMs6", "8466": "kaOzK6kJyAMhsAGO", "8467": "6jKCZJJIo8TvzdiY", "8468": "tL0b728Ezr5GKbL4", "8470": "pIkxYIJhK9bVvRed", "8471": "fBqYZEtZnKnyn96U", "8723": "dp0HjiZGaGhwTqGE", "8724": "Q3X65vo0EN91hSAO", "8726": "aqwr0zZbJQNxnScL", "8728": "qfIT5ZYwrnkmNTXJ", "8729": "bQl0o8yOl0Z3ZwCQ", "8731": "yvJOej36kvtlzDAA", "8733": "dBLh3j7VAEM92uDl", "8735": "xB2XylkAEX52wMwc", "8736": "9cATZDKIdBc6K6qy", "8738": "r7uJPSTUuAGLVZRB", "8739": "tzxEzzczIimssQ6v", "8740": "ddsuHlyEUgp3jJVY", "8741": "ANwNHHgHOt9cy4sF", "8742": "p2HsnpAL2YsPqbVd", "8744": "jhT487wMpvhJoKr3", "8746": "5Jb4qOlflyrndU60", "8748": "Qkw0fXrU62Nf41E4", "8750": "JpfSKeKQhEExI2PD", "8751": "EWy6zaQ0U7oacvn6", "8752": "ERfOv3fM8flOVvJR", "8753": "zQnUGH2ygnkIxGVv", "8754": "1hJVIXNnLu0lUDIi", "8756": "MDe1KbsSNtgJhlTC", "8757": "ryL1fn18hCb4KMvk", "8758": "O6a3DYdcqqL8LrJL", "8760": "ZAI3AIMBviCLr75I", "8761": "0OdPOXHTZx5oYvkO", "8762": "VOR1yf7q8r5kw1d1", "8763": "AYBwigyw8uFPeN9P", "8765": "YC8OOvChjFJaHuOg", "8767": "r42tI9aDNIxtSkXB", "8768": "QlAHv7mnI4IgjtaD", "8769": "Ol6gLpcIBTIyiCty", "8770": "txmDHaYDv6nU3b3n", "8772": "UVfcSCa6hwPMBLAR", "8774": "JMSA7NHoyY7I6spd", "8776": "mKVgstDMIgoGDmgp", "8777": "RffaN9f318Gcfh5o", "8779": "kZjYbQHy0WvJkcC2", "8781": "uzFdx5ToCRMNslNe", "8783": "QsCfYQ5JaxrGkiLl", "8785": "ZCWg7fE5OakmXdHt", "8786": "DXv6FewRYYuKDPQb", "8787": "jnpR1KPG7H6edLxw", "8789": "B14pEq01bYrZXImz", "8790": "IWrmyTekc7YO23M9", "8792": "LvBKSAkc7WBoi437", "8794": "wKcAC4Rs70OFYSOo", "8796": "ZWqdpZNH61a9LMZt", "8798": "ayUcDlIPgCpGHZaY", "8799": "QCWrsMg4kjhaKQvy", "8800": "2843G7neWmiDntHc", "8801": "47dF17GxVZMqycaq", "8802": "ECsk1xXz8QLwCyQh", "8803": "eDXWyeotmO0kSrs9", "8804": "ONn0lPswKO9Os7HS", "8806": "dCvWLaelO15ighoZ", "8807": "56DOGL5fwmz4OtvO", "8809": "bhG4QSfVaaqjtlKe", "8811": "DdG7jvQ9vTSr5VpC", "8813": "uFSsN75pxt8mdQMz", "8814": "dTCaBSbkl2mtXHSw", "8815": "5rjlhAXnAVw3Dt51", "8816": "JxfTRIRd1SM8PINp", "8817": "A9A7caU9RyBsQkXR", "8818": "IPBQ8OyyRRJQ5kWf", "8819": "CPhXd7i6t1UTfoxa", "8821": "rZIlBBIDNwQNndCr", "8823": "osS963vWLssNpNws", "8824": "L2XQdRcarJ8JnPME", "8826": "IDoZWXMOvwu6TzGs", "8827": "4Rx5qYzzIbNwibEV", "8829": "c1BpJfNRnlCYfkPg", "8831": "R5koyp41aIvYS9AI", "8832": "Lo5joLHByf6S4jS1", "8834": "4sGrhA3lJQQwfDBu", "8836": "frwmNVUVVDb2yeRz", "8838": "Fegxv7YcuBFVRc4V", "8840": "fYHDyMOgxHDXj6Ul", "8841": "6ysMlHgThDE49wF3", "8842": "S3szXa2Zi2QAtk9T", "8843": "RPq3KM4Tputu6Jmd", "8845": "xGsOLRfkd7YM8TNR", "8846": "czsQqvh7Qec1tweb", "8847": "qdduMcr9uzCaNgrC", "8848": "SvVNHGFbIdZ8EadO", "8849": "ORuqsJ6TxQMplnwH", "8851": "COty1HpXD9fd5eIB", "8853": "R9cSaKPI7VQTWVEE", "8855": "a5Bec1FwEECf8WqG", "8856": "y39Vfhczfpl0xqKf", "8857": "j8TXCXvURQCnwq2E", "8859": "JezJ3MOYEUpuukv0", "8861": "LqgWs6rcu24xSajF", "8862": "hSfSil54HbmZQphL", "8863": "RgJt5kIX8C4C2TYu", "8864": "7LJYZ9osj83ixFOs", "8866": "dKEi7f4ndl0xiCdo", "8868": "oqlkNROt1268Tobk", "8870": "mCnilIqqsmVhOfCP", "8871": "yZ0ANEtcdS95y8D0", "8873": "oqRVa6wAS71cOvGQ", "8875": "p3qF7YUGd0KNWGnH", "8876": "AqncKTJx9bKJgo7G", "8878": "P9Q9FXSkaRK1hOKY", "8880": "d9hylTJPg57o3EIO", "8881": "hwLAhgxTJFxZgRfF", "8883": "Jlv0oBetxMsHH21Y", "8956": "6lSojeHIZdLwjHVd", "8957": "Rn4UauoqK2HW1yjK", "8958": "KXhPo50ptOKVIZeH", "8960": "KZTC0WwWqyeStZD2", "8962": "PYG4vhVxksOYQJdt", "8963": "bbvV99IJzw2kQT6R", "8965": "uYkvYjZEDotAHE9O", "8966": "yb8nWd74n3u7Zm3P", "8968": "3TCayelJfuF0L0iy", "8969": "rcm52TR3QBCReTxe", "8971": "tA4uV90dZx3VxLa7", "8972": "YSwKGJImchI13Fxg", "8973": "jdrpp1KZIfGVkTkv", "8975": "08cwzAYpDHeUCHFm", "8977": "BwL4JzKHFJscYTlO", "8978": "pRvfSdZHoTs1ES6F", "8980": "CM7BYW3F44fvPHe2", "8982": "QwE7uPFSeHScMcz4", "8984": "BD3dB7fVD2dvlGwM", "8985": "v3q7X4XGkXspyHCB", "8987": "fo84TCZ3wyYL9zTa", "8988": "LtI5DJQaZlG0Q060", "8990": "SUe1tHRIGZ3eGgFP", "8991": "EYkVZQRGDiAOHIXX", "8993": "UkMJ2R6IzS6UJe8b", "8884": "2Wbfgl8xvcDzgIok", "8885": "10Qvwlx1x3BTCipW", "8886": "chS7tSE0JVB1bOtn", "8887": "q95VgRcugr6518xt", "8889": "YNwaWpK84SLJXHlo", "8890": "eJ8464rKRYdJi4y0", "8892": "dEUXYMMmUjwxpLHT", "8894": "eVZdG1cAb89uJhVd", "8895": "V9HZBD11TZHGsibY", "8897": "bCc66uRPkQYI2U07", "8898": "UjPLhekBjxnYHoaR", "8900": "iaKwtWDYOROA7h06", "8901": "Qnym2qS63nIIr6MO", "8903": "6Wy08MyCwK4cacPT", "8905": "P9JWNO9alOjxF12S", "8906": "2kRnlcgUSHhfOI3h", "8907": "Ruv30XgurswmElNo", "8909": "jk1C0auQt33rhwbl", "8911": "FuwZdTIe7mCltjWG", "8913": "MmvIA6Jr481afxEE", "8915": "u9eaKn9sIaw0IaTa", "8917": "mg6TnSAXudBvCJPX", "8918": "gk3nWln1T0U8y5ZY", "8919": "tUdRI5fBCyNuw3Ir", "8920": "2oQP06HkAfFiRwA3", "8922": "YlRJOcLhZftETsZ5", "8924": "ozSE6Ne7dCj3ivaL", "8925": "nEiRE9Q0CEI77W2v", "8926": "ur6nERX3v075ttDz", "8928": "hPeoIEpoHySH4qjF", "8929": "t11J6CIRxsDO6xJP", "8930": "RdNmObWkViKausX1", "8932": "iDWqgFha6Ap1JNyM", "8934": "MNgy7zEIDIRYVJ2k", "8936": "KcPD1WVrpaFxWq4r", "8937": "u4Do6yGYTI4EJxkd", "8938": "Vmtlbu7FyKKhzIH8", "8939": "P0uZg3wQ6fb9Er7d", "8941": "H9XHY6Zl4laSKVVa", "8942": "q1FChXgHKQXWQYbp", "8944": "FV0EtTgkyDtRulTv", "8945": "eLAxW1e0si8cF7jj", "8946": "oO8E9elbOapCgB6t", "8947": "KyTOqbWe54vDV7jI", "8949": "Ig02q6KHYgzR2Pfd", "8950": "TibT82JLWlRPSuCc", "8952": "JQT1g01nfT3lHdhH", "8953": "vg2UrbMiMMPyZhds", "8955": "ehDcmSgLNMz6mYoe", "9025": "7n6QYxbgc2jbPbgy", "9027": "7TKnZzrHQF5MigQT", "9028": "TgMO1eontpeUJKB4", "9030": "R2bCnwdSc2nu1O8n", "9032": "MfL2OSzTxQ6F6aYK", "9034": "ESnW6fIzypDGAH5b", "9036": "fdZmhNwuqqxg3F3e", "9037": "a3ow5EE8O3B7Lvx4", "9038": "Wjf7ZLF1E93b7OHt", "9040": "6fVsBVHuNbcbURCT", "9041": "T8cnXenWfsNydKqS", "9042": "88FnprhuZz3NCD1q", "9044": "VeFzsAm1nE4KG6EI", "9046": "q1oLuLVN3qIlSPSF", "9047": "Kf2zkFlfrsUMLhjW", "9049": "ADw4wJev0Mqdc3DG", "9051": "v9UnitYhQ0OxQ0kA", "9053": "41EuFRn1RqO0NdG3", "9055": "wOzCua8hLfLaPUFq", "9056": "8IsPG8bygFiQThZO", "9057": "nIBfgaQYGzduZyWH", "9058": "vlv3eqWNAOO81GCw", "9059": "8PG3e4ZPtHm83qZ1", "9061": "Pb43lYcwND8ALiX8", "9063": "QUZRP2X08GYUQmVH", "9064": "FszJp9LqbwG2C2qX", "9066": "zAWEjOep8YPVThBc", "9068": "MGnMkop427OjdB7a", "9069": "DHAXpdbSDO2LojTJ", "9071": "me3WdlaQ4tpAjnLc", "9072": "feV5ufsWy4FtfODt", "9073": "7dnHl7glrU8EKIcS", "9075": "GMETb1dy2EjMUVYZ", "9076": "kEJ4XPSfGmq3t1x7", "9078": "ZR8Jho2KNaYwCIGb", "9080": "mUTuLI5eZHK8k8XE", "9081": "nZHRmVirYlUvTsD6", "9082": "ZQ3nEYBXEUnMFBFQ", "9084": "M3v3TWxbOSA4dnXj", "9086": "vtNvl44kAAbhfSm4", "9088": "dJ0W34hCmXhVj31X", "9089": "NvTVI0gRUBsdFmPs", "9091": "9VGT0riTxKKfqvVh", "9092": "LuHU8BVZgKxnF1JZ", "9093": "5uhOCvSSGi7XkYB8", "9095": "v7QXjlDHorm2O0Hb", "9096": "wsKqtRmlB8qxBChB", "9098": "gYF6Ilxyx2oxCThK", "9100": "e6P2YFclioBqC5dK", "9101": "OAntOkPx802P7M12", "9102": "xHbaaPsu0Ac83mM2", "9104": "hvdvJ1zh8VbiSKEk", "9106": "35JiqPEVR3E6gYDQ", "9108": "sneGA2rp3M1BN773", "9110": "5rKUKu5JpcX18f4q", "9112": "uW9TVWOIs7DBKnhB", "9113": "XfSHve9n8M37xhYd", "9114": "CI937Qw95h3P4Eox", "9116": "LLFHRxXqmPMdDP6d", "9117": "flOjAovmKffy2p53", "9119": "T0ihACruHGtwpG43", "9120": "lPSDoSXYFQBrBNbw", "9122": "mDFzoAIfrHfuSOvs", "9124": "rUM3edVnEdXdRzas", "9126": "y2bwSL5SUx5mJorA", "9128": "J8SSeOntSQr6nWTH", "9130": "JVuGBem9tkVKy1Uh", "9131": "RRDcOylGpEZKxU4G", "9132": "Yy0b857IqCSri0WF", "9134": "ScmtSxXycUeCDTs6", "9135": "SQZ6Go9wKnOb3DNt", "9136": "jtQzXvrbWcOyAFqR", "9137": "Xys0qA4PyTTP2xsX", "9138": "nGyjOeHggeIgkSSs", "9140": "wpFjRs9tDs4KuFBD", "9142": "7jsUxjkupaNtPCqz", "9143": "CkARpbEwPj9bIzBP", "9144": "Qzl9tjVRtaDryqYX", "9146": "O7wUqwnU72VDd27X", "9147": "gqLLzqUyFBEyc4kr", "9148": "GzX9TzzgB5EJl0kv", "9149": "KAJtVusKSmQJnBWE", "9150": "IUSxKjxrNQ2OHGuf", "9151": "Xt3GDyQJ9dSk02zh", "9152": "tcCpycv5DsMdQrqA", "9154": "duO4pfwHuIrg45HE", "9155": "S1Y4aFILwaubCS2x", "9157": "jAC32g1GwHazzg9L", "9158": "zXYMEerUPv3ZZQZk", "9159": "Cxdi6CQ8JhbpkXJV", "9160": "EBDXSGR7nBkO7gIU", "9162": "i87M1Da7jN3WjVq3", "9164": "UTQZS0QwBRrrLxUj", "9165": "aoMYfdtbNryiH7qv", "9166": "PwbvR8bH2IFLAVY2", "9168": "fEN9gK2eFZnceQBq", "9169": "7XQGCyxgULvnJLF7", "9171": "j8g7dj5SNP63HPBq", "9172": "GWNAfOIBTegrHYNM", "9174": "tBfDQvysB0IAYrKq", "9176": "dafhyzV1ZR1oS4kq", "9177": "aLYJ9dTjsu0TS3Tf", "9178": "xC02He2is1lZPxAz", "9180": "ZYZ7XcNyM3nIWjD9", "9182": "zvSTvQVRpKMoAHn6", "9183": "Jxd6oZgz1ryTlRab", "9184": "TGYCHa24AJ3NG6Mf", "9185": "XRuDtmqwCxaIz0Tj", "9186": "Y1OJZ4uhP0nRGaW6", "9187": "p9rqW9AZSiRR6yPN", "9189": "LEJhtBQA3vksnqQh", "9190": "Df0WBjZMWblyI7eH", "9192": "cnFJZVE1HA9zYB9z", "9194": "M35gAB2nFpOUvE9b", "9195": "iW982ZUd4T5mY9VY", "9197": "cOkp08LreOBnN5Nt", "9199": "eoE3yfqsqBfCOF3T", "9201": "bZif7z2gH1hjg4x5", "9202": "PiHc2uITovlIouDo", "9203": "jlagOAiYTy7hrYIU", "9205": "1Q2zuBru3B0xtzZL", "9207": "5x9pboO3NN44skkX", "9209": "i8QqORuQsOCPsaaP", "9211": "DGA0J0JN5YOsHn71", "9212": "4mL4l8vEiziedl1v", "9214": "C9J57qJn05CPPBrx", "9215": "85ZqxzkIABIRrwH2", "9216": "5ZBjfHBmw36rrFD1", "9217": "yXP8AbEQAQqPgpVB", "9219": "z2HybH0w1ejxZSyx", "9220": "FfELFObgNBqCXOXH", "9222": "kvso2Fmrni5biQOI", "9224": "FwXsx5qCP2ItIAL4", "9225": "5kKqrG5kVU7tyjUh", "9227": "scpBsdf1g3HNciSq", "9229": "HjVCFmB43IPttda4", "9230": "HuCFGRTD63muTthp", "9232": "i0cqI7AQ8OeRbEpz", "9233": "8A9qSKSHrgUhZphU", "9235": "8RYBXtRDmyR5wO5T", "9236": "irf6PB4Gl4zpmm0S", "9238": "3kJQJHffDD9pRnBQ", "9240": "bmtffdo09e6lw10y", "9241": "F1XK6jlL3vTQjOiP", "9242": "nqHWVtH3hO0ZVm12", "9243": "lEMABEV7JDIAyWHv", "9245": "31wKDVGyxZNMEP5H", "9246": "3iHRJ1a53Ame69vR", "9247": "WrZsB5bL1bGa3DVZ", "9248": "jTBQBr8Ra1MApPxc", "9249": "QU4dxXsY7fFecOkW", "9251": "c47czgCiAdiNLePd", "9253": "o3bVIfK8qgIlQKp9", "9254": "WQkscSgSsFNDpPyx", "9255": "e2mbmKrZpGvZb0v0", "9256": "XVN3MUBjvKO6BVm6", "8995": "OU3V8vdYTC0hJG0R", "8996": "Y7FP9kzTmvgdwbRp", "8997": "Jwyhh4UqLDxefhcT", "8998": "vuJjTvER8J7TzRz9", "9000": "zD0VAcarbPWWKnWa", "9001": "eiAdWvHXti4fjM5R", "9002": "axPoBSoxerca0IRN", "9004": "33ENz4N0FD7bNzwt", "9005": "jqwpNl87ApWZg2mq", "9007": "LkaYzJ2se2IDQLNE", "9009": "C10fvKJ2CnDZklSq", "9010": "hx4Htu5eN8H4XyMb", "9258": "214ZvA66E6HqI26o", "9259": "LhYiLsYh9qqGp6ET", "9260": "TXk3e4BTj2yosTBG", "9262": "3aIrVBmOa1mMj5TI", "9264": "V5zZsTHd0yqyCN0u", "9011": "P1VFd7CeNEuUXpwx", "9013": "EXbtA1ToTvnCVAQw", "9015": "sNiP6qJ89SDCjYep", "9016": "W8X9Oo4ESPDZWxge", "9018": "x225oMNAyEQdQuoa", "9020": "sSvu9b1R2By2OtN8", "9021": "TgRLSVqx5JIjQPB3", "9023": "jfAnxxDEVJMsZtWi"}}